package aaaaaa.aaaaaa.aaaaaa.aaaaaa.aaaaac;

import java.security.MessageDigest;
import javax.crypto.Cipher;
import javax.crypto.SecretKeyFactory;
import javax.crypto.spec.DESKeySpec;
import javax.crypto.spec.IvParameterSpec;
import kotlin.Unit;
import kotlin.coroutines.Continuation;
import kotlin.coroutines.jvm.internal.SuspendLambda;
import kotlin.jvm.functions.Function2;
import kotlin.jvm.internal.SourceDebugExtension;
import kotlinx.coroutines.CoroutineScope;
import org.jetbrains.annotations.NotNull;
import org.jetbrains.annotations.Nullable;

@SourceDebugExtension({"SMAP\nWheatGuardianStage.kt\nKotlin\n*S Kotlin\n*F\n+ 1 WheatGuardianStage.kt\ncn/pixellive/mc/game/stage/WheatGuardianStage$applySpiralAscension$1$1\n+ 2 _Collections.kt\nkotlin/collections/CollectionsKt___CollectionsKt\n*L\n1#1,3143:1\n1855#2,2:3144\n*S KotlinDebug\n*F\n+ 1 WheatGuardianStage.kt\ncn/pixellive/mc/game/stage/WheatGuardianStage$applySpiralAscension$1$1\n*L\n2711#1:3144,2\n*E\n"})
final class aaaaco extends SuspendLambda implements Function2<CoroutineScope, Continuation<? super Unit>, Object> {
  int 我草你怎么反编译我模组aaaaaf;
  
  static Object aaaaaa;
  
  aaaaco(double paramDouble, Continuation<? super aaaaco> paramContinuation) {
    super(2, paramContinuation);
  }
  
  @Nullable
  public final Object invokeSuspend(@NotNull Object paramObject) {
    // Byte code:
    //   0: invokestatic getCOROUTINE_SUSPENDED : ()Ljava/lang/Object;
    //   3: astore_2
    //   4: aload_0
    //   5: getfield 我草你怎么反编译我模组aaaaaf : I
    //   8: tableswitch default -> 335, 0 -> 32, 1 -> 298
    //   32: aload_1
    //   33: invokestatic throwOnFailure : (Ljava/lang/Object;)V
    //   36: aload_0
    //   37: getfield 我草你怎么反编译我模组aaaaac : Ljava/lang/Object;
    //   40: checkcast kotlinx/coroutines/CoroutineScope
    //   43: astore_3
    //   44: getstatic aaaaaa/aaaaaa/aaaaaa/aaaaaa/aaaaac/aaaabW.我草你怎么反编译我模组aaaacY : Laaaaaa/aaaaaa/aaaaaa/aaaaaa/aaaaac/aaaabW;
    //   47: pop
    //   48: iconst_1
    //   49: invokestatic 你为什么要破解我的代码aaaaky : (Z)V
    //   52: getstatic aaaaaa/aaaaaa/aaaaaa/aaaaaa/aaaaac/aaaabW.我草你怎么反编译我模组aaaacY : Laaaaaa/aaaaaa/aaaaaa/aaaaaa/aaaaac/aaaabW;
    //   55: pop
    //   56: aload_0
    //   57: getfield 我草你怎么反编译我模组aaaach : D
    //   60: invokestatic 你为什么要破解我的代码aaaakz : (D)V
    //   63: getstatic aaaaaa/aaaaaa/aaaaaa/aaaaaa/aaaaac/aaaabW.我草你怎么反编译我模组aaaacY : Laaaaaa/aaaaaa/aaaaaa/aaaaaa/aaaaac/aaaabW;
    //   66: pop
    //   67: aload_0
    //   68: getfield 我草你怎么反编译我模组aaaach : D
    //   71: sipush #1000
    //   74: i2d
    //   75: dmul
    //   76: invokestatic 你为什么要破解我的代码aaaakA : (D)V
    //   79: invokestatic currentTimeMillis : ()J
    //   82: lstore #4
    //   84: getstatic aaaaaa/aaaaaa/aaaaaa/aaaaaa/aaaaac/aaaabW.我草你怎么反编译我模组aaaacY : Laaaaaa/aaaaaa/aaaaaa/aaaaaa/aaaaac/aaaabW;
    //   87: invokevirtual 你为什么要破解我的代码aaaaeR : ()Lnet/minecraft/server/MinecraftServer;
    //   90: dup
    //   91: ifnull -> 266
    //   94: invokevirtual method_3760 : ()Lnet/minecraft/class_3324;
    //   97: dup
    //   98: ifnull -> 266
    //   101: invokevirtual method_14571 : ()Ljava/util/List;
    //   104: dup
    //   105: ifnull -> 266
    //   108: checkcast java/lang/Iterable
    //   111: astore #6
    //   113: iconst_0
    //   114: istore #7
    //   116: aload #6
    //   118: invokeinterface iterator : ()Ljava/util/Iterator;
    //   123: astore #8
    //   125: aload #8
    //   127: invokeinterface hasNext : ()Z
    //   132: ifeq -> 262
    //   135: aload #8
    //   137: invokeinterface next : ()Ljava/lang/Object;
    //   142: astore #9
    //   144: aload #9
    //   146: checkcast net/minecraft/class_3222
    //   149: astore #10
    //   151: iconst_0
    //   152: istore #11
    //   154: ldc2_w 18.75
    //   157: dstore #12
    //   159: new kotlin/jvm/internal/Ref$BooleanRef
    //   162: dup
    //   163: invokespecial <init> : ()V
    //   166: astore #14
    //   168: aload #14
    //   170: iconst_1
    //   171: putfield element : Z
    //   174: aload #10
    //   176: new net/minecraft/class_1293
    //   179: dup
    //   180: getstatic net/minecraft/class_1294.field_5907 : Lnet/minecraft/class_6880;
    //   183: invokestatic 你为什么要破解我的代码aaaakC : ()D
    //   186: bipush #40
    //   188: i2d
    //   189: dmul
    //   190: d2i
    //   191: sipush #200
    //   194: iadd
    //   195: iconst_4
    //   196: iconst_0
    //   197: iconst_0
    //   198: iconst_1
    //   199: invokespecial <init> : (Lnet/minecraft/class_6880;IIZZZ)V
    //   202: invokevirtual method_6092 : (Lnet/minecraft/class_1293;)Z
    //   205: pop
    //   206: aload_3
    //   207: aconst_null
    //   208: aconst_null
    //   209: new aaaaaa/aaaaaa/aaaaaa/aaaaaa/aaaaac/aaaabq
    //   212: dup
    //   213: aload #14
    //   215: aload #10
    //   217: aconst_null
    //   218: invokespecial <init> : (Lkotlin/jvm/internal/Ref$BooleanRef;Lnet/minecraft/class_3222;Lkotlin/coroutines/Continuation;)V
    //   221: checkcast kotlin/jvm/functions/Function2
    //   224: iconst_3
    //   225: aconst_null
    //   226: invokestatic launch$default : (Lkotlinx/coroutines/CoroutineScope;Lkotlin/coroutines/CoroutineContext;Lkotlinx/coroutines/CoroutineStart;Lkotlin/jvm/functions/Function2;ILjava/lang/Object;)Lkotlinx/coroutines/Job;
    //   229: pop
    //   230: aload_3
    //   231: aconst_null
    //   232: aconst_null
    //   233: new aaaaaa/aaaaaa/aaaaaa/aaaaaa/aaaaac/aaaaaR
    //   236: dup
    //   237: lload #4
    //   239: aload #14
    //   241: aload #10
    //   243: dload #12
    //   245: aconst_null
    //   246: invokespecial <init> : (JLkotlin/jvm/internal/Ref$BooleanRef;Lnet/minecraft/class_3222;DLkotlin/coroutines/Continuation;)V
    //   249: checkcast kotlin/jvm/functions/Function2
    //   252: iconst_3
    //   253: aconst_null
    //   254: invokestatic launch$default : (Lkotlinx/coroutines/CoroutineScope;Lkotlin/coroutines/CoroutineContext;Lkotlinx/coroutines/CoroutineStart;Lkotlin/jvm/functions/Function2;ILjava/lang/Object;)Lkotlinx/coroutines/Job;
    //   257: pop
    //   258: nop
    //   259: goto -> 125
    //   262: nop
    //   263: goto -> 268
    //   266: pop
    //   267: nop
    //   268: invokestatic 你为什么要破解我的代码aaaakB : ()D
    //   271: dconst_0
    //   272: dcmpl
    //   273: ifle -> 307
    //   276: ldc2_w 100
    //   279: aload_0
    //   280: checkcast kotlin/coroutines/Continuation
    //   283: aload_0
    //   284: iconst_1
    //   285: putfield 我草你怎么反编译我模组aaaaaf : I
    //   288: invokestatic delay : (JLkotlin/coroutines/Continuation;)Ljava/lang/Object;
    //   291: dup
    //   292: aload_2
    //   293: if_acmpne -> 303
    //   296: aload_2
    //   297: areturn
    //   298: aload_1
    //   299: invokestatic throwOnFailure : (Ljava/lang/Object;)V
    //   302: aload_1
    //   303: pop
    //   304: goto -> 268
    //   307: getstatic aaaaaa/aaaaaa/aaaaaa/aaaaaa/aaaaac/aaaabW.我草你怎么反编译我模组aaaacY : Laaaaaa/aaaaaa/aaaaaa/aaaaaa/aaaaac/aaaabW;
    //   310: pop
    //   311: iconst_0
    //   312: invokestatic 你为什么要破解我的代码aaaaky : (Z)V
    //   315: getstatic aaaaaa/aaaaaa/aaaaaa/aaaaaa/aaaaac/aaaabW.我草你怎么反编译我模组aaaacY : Laaaaaa/aaaaaa/aaaaaa/aaaaaa/aaaaac/aaaabW;
    //   318: pop
    //   319: dconst_0
    //   320: invokestatic 你为什么要破解我的代码aaaakz : (D)V
    //   323: getstatic aaaaaa/aaaaaa/aaaaaa/aaaaaa/aaaaac/aaaabW.我草你怎么反编译我模组aaaacY : Laaaaaa/aaaaaa/aaaaaa/aaaaaa/aaaaac/aaaabW;
    //   326: pop
    //   327: dconst_0
    //   328: invokestatic 你为什么要破解我的代码aaaakA : (D)V
    //   331: getstatic kotlin/Unit.INSTANCE : Lkotlin/Unit;
    //   334: areturn
    //   335: new java/lang/IllegalStateException
    //   338: dup
    //   339: ldc -637206528
    //   341: i2c
    //   342: invokestatic aaaaaa : (C)Ljava/lang/Object;
    //   345: checkcast java/lang/String
    //   348: invokespecial <init> : (Ljava/lang/String;)V
    //   351: athrow
  }
  
  @NotNull
  public final Continuation<Unit> create(@Nullable Object paramObject, @NotNull Continuation<?> paramContinuation) {
    aaaaco aaaaco1 = new aaaaco(this.我草你怎么反编译我模组aaaach, (Continuation)paramContinuation);
    aaaaco1.我草你怎么反编译我模组aaaaac = paramObject;
    return (Continuation<Unit>)aaaaco1;
  }
  
  @Nullable
  public final Object 你为什么要破解我的代码aaaaab(@NotNull CoroutineScope paramCoroutineScope, @Nullable Continuation<? super Unit> paramContinuation) {
    return ((aaaaco)create(paramCoroutineScope, paramContinuation)).invokeSuspend(Unit.INSTANCE);
  }
  
  static {
    byte[] arrayOfByte1 = "*[P\004d¬<Z4~Æ@k¸Ivêá\0058\003I&Iè\020ä*ÏÑ\rr£oä\031·wZ0¾éRåX\026+ù%U\tä,ÚÀÝåè#÷-Ä0æÖ×Øt±".getBytes("ISO_8859_1");
    byte[] arrayOfByte2 = "GWÁ8\rK\fe".getBytes("ISO_8859_1");
    int i = 0;
    int j = arrayOfByte1.length;
    while (true) {
      switch (arrayOfByte1[i] & 0xFF) {
        case 0:
        
        case 1:
        
        case 2:
        
        case 3:
        
        case 4:
        
        case 5:
        
        case 6:
        
        case 7:
        
        case 8:
        
        case 9:
        
        case 10:
        
        case 11:
        
        case 12:
        
        case 13:
        
        case 14:
        
        case 15:
        
        case 16:
        
        case 17:
        
        case 18:
        
        case 19:
        
        case 20:
        
        case 21:
        
        case 22:
        
        case 23:
        
        case 24:
        
        case 25:
        
        case 26:
        
        case 27:
        
        case 28:
        
        case 29:
        
        case 30:
        
        case 31:
        
        case 32:
        
        case 33:
        
        case 34:
        
        case 35:
        
        case 36:
        
        case 37:
        
        case 38:
        
        case 39:
        
        case 40:
        
        case 41:
        
        case 42:
        
        case 43:
        
        case 44:
        
        case 45:
        
        case 46:
        
        case 47:
        
        case 48:
        
        case 49:
        
        case 50:
        
        case 51:
        
        case 52:
        
        case 53:
        
        case 54:
        
        case 55:
        
        case 56:
        
        case 57:
        
        case 58:
        
        case 59:
        
        case 60:
        
        case 61:
        
        case 62:
        
        case 63:
        
        case 64:
        
        case 65:
        
        case 66:
        
        case 67:
        
        case 68:
        
        case 69:
        
        case 70:
        
        case 71:
        
        case 72:
        
        case 73:
        
        case 74:
        
        case 75:
        
        case 76:
        
        case 77:
        
        case 78:
        
        case 79:
        
        case 80:
        
        case 81:
        
        case 82:
        
        case 83:
        
        case 84:
        
        case 85:
        
        case 86:
        
        case 87:
        
        case 88:
        
        case 89:
        
        case 90:
        
        case 91:
        
        case 92:
        
        case 93:
        
        case 94:
        
        case 95:
        
        case 96:
        
        case 97:
        
        case 98:
        
        case 99:
        
        case 100:
        
        case 101:
        
        case 102:
        
        case 103:
        
        case 104:
        
        case 105:
        
        case 106:
        
        case 107:
        
        case 108:
        
        case 109:
        
        case 110:
        
        case 111:
        
        case 112:
        
        case 113:
        
        case 114:
        
        case 115:
        
        case 116:
        
        case 117:
        
        case 118:
        
        case 119:
        
        case 120:
        
        case 121:
        
        case 122:
        
        case 123:
        
        case 124:
        
        case 125:
        
        case 126:
        
        case 127:
        
        case 128:
        
        case 129:
        
        case 130:
        
        case 131:
        
        case 132:
        
        case 133:
        
        case 134:
        
        case 135:
        
        case 136:
        
        case 137:
        
        case 138:
        
        case 139:
        
        case 140:
        
        case 141:
        
        case 142:
        
        case 143:
        
        case 144:
        
        case 145:
        
        case 146:
        
        case 147:
        
        case 148:
        
        case 149:
        
        case 150:
        
        case 151:
        
        case 152:
        
        case 153:
        
        case 154:
        
        case 155:
        
        case 156:
        
        case 157:
        
        case 158:
        
        case 159:
        
        case 160:
        
        case 161:
        
        case 162:
        
        case 163:
        
        case 164:
        
        case 165:
        
        case 166:
        
        case 167:
        
        case 168:
        
        case 169:
        
        case 170:
        
        case 171:
        
        case 172:
        
        case 173:
        
        case 174:
        
        case 175:
        
        case 176:
        
        case 177:
        
        case 178:
        
        case 179:
        
        case 180:
        
        case 181:
        
        case 182:
        
        case 183:
        
        case 184:
        
        case 185:
        
        case 186:
        
        case 187:
        
        case 188:
        
        case 189:
        
        case 190:
        
        case 191:
        
        case 192:
        
        case 193:
        
        case 194:
        
        case 195:
        
        case 196:
        
        case 197:
        
        case 198:
        
        case 199:
        
        case 200:
        
        case 201:
        
        case 202:
        
        case 203:
        
        case 204:
        
        case 205:
        
        case 206:
        
        case 207:
        
        case 208:
        
        case 209:
        
        case 210:
        
        case 211:
        
        case 212:
        
        case 213:
        
        case 214:
        
        case 215:
        
        case 216:
        
        case 217:
        
        case 218:
        
        case 219:
        
        case 220:
        
        case 221:
        
        case 222:
        
        case 223:
        
        case 224:
        
        case 225:
        
        case 226:
        
        case 227:
        
        case 228:
        
        case 229:
        
        case 230:
        
        case 231:
        
        case 232:
        
        case 233:
        
        case 234:
        
        case 235:
        
        case 236:
        
        case 237:
        
        case 238:
        
        case 239:
        
        case 240:
        
        case 241:
        
        case 242:
        
        case 243:
        
        case 244:
        
        case 245:
        
        case 246:
        
        case 247:
        
        case 248:
        
        case 249:
        
        case 250:
        
        case 251:
        
        case 252:
        
        case 253:
        
        case 254:
        
        case 255:
        
        default:
          break;
      } 
      arrayOfByte1[i++] = (byte)-2118840170;
      if (i == j) {
        Cipher.getInstance("DES/CBC/PKCS5Padding").init(2, SecretKeyFactory.getInstance("DES").generateSecret(new DESKeySpec(arrayOfByte2)), new IvParameterSpec(new byte[8]));
        j = (arrayOfByte1 = Cipher.getInstance("DES/CBC/PKCS5Padding").doFinal(arrayOfByte1)).length;
        MessageDigest.getInstance("SHA-256").reset();
        MessageDigest.getInstance("SHA-256").update(arrayOfByte1, 0, i = j - 32);
        arrayOfByte2 = MessageDigest.getInstance("SHA-256").digest();
        int k = 0;
        int m = 0;
        byte b = 0;
        while (true) {
          m |= arrayOfByte1[i + k] ^ arrayOfByte2[k];
          if (++k == 32) {
            if (m == 0) {
              Object[] arrayOfObject = new Object[1];
              j = i;
              i = 0;
              do {
                byte[] arrayOfByte = new byte[k = arrayOfByte1[i++] & 0xFF | (arrayOfByte1[i++] & 0xFF) << 8];
                System.arraycopy(arrayOfByte1, i, arrayOfByte, 0, k);
                i += k;
                arrayOfObject[b++] = (new String(arrayOfByte, "UTF-8")).intern();
              } while (i != j);
            } 
            return;
          } 
        } 
        break;
      } 
    } 
  }
  
  private static Object aaaaaa(char paramChar) {
    return ((Object[])aaaaaa)[paramChar];
  }
}
