package aaaaaa.aaaaaa.aaaaaa.aaaaaa.aaaaac;

import java.security.MessageDigest;
import java.util.List;
import java.util.Timer;
import java.util.TimerTask;
import javax.crypto.Cipher;
import javax.crypto.SecretKeyFactory;
import javax.crypto.spec.DESKeySpec;
import javax.crypto.spec.IvParameterSpec;
import kotlin.jvm.internal.Ref;
import kotlin.jvm.internal.SourceDebugExtension;
import net.minecraft.class_1299;
import net.minecraft.class_1308;
import net.minecraft.class_3218;

@SourceDebugExtension({"SMAP\nPeakChallengeStage.kt\nKotlin\n*S Kotlin\n*F\n+ 1 PeakChallengeStage.kt\ncn/pixellive/mc/game/stage/PeakChallengeStage$spawnEntities$createSpawnTimer$1\n+ 2 _Collections.kt\nkotlin/collections/CollectionsKt___CollectionsKt\n*L\n1#1,2800:1\n1963#2,14:2801\n*S KotlinDebug\n*F\n+ 1 PeakChallengeStage.kt\ncn/pixellive/mc/game/stage/PeakChallengeStage$spawnEntities$createSpawnTimer$1\n*L\n1318#1:2801,14\n*E\n"})
public final class aaaacd extends TimerTask {
  static Object aaaaax;
  
  aaaacd(Ref.IntRef paramIntRef, int paramInt, List<Timer> paramList, Timer paramTimer, class_1299<? extends class_1308> paramclass_1299, class_3218 paramclass_3218, String paramString) {}
  
  public void run() {
    // Byte code:
    //   0: aload_0
    //   1: getfield 我草你怎么反编译我模组aaaaas : Lkotlin/jvm/internal/Ref$IntRef;
    //   4: getfield element : I
    //   7: aload_0
    //   8: getfield 我草你怎么反编译我模组aaaaat : I
    //   11: if_icmplt -> 34
    //   14: aload_0
    //   15: invokevirtual cancel : ()Z
    //   18: pop
    //   19: aload_0
    //   20: getfield 我草你怎么反编译我模组aaaaao : Ljava/util/List;
    //   23: aload_0
    //   24: getfield 我草你怎么反编译我模组aaaaau : Ljava/util/Timer;
    //   27: invokeinterface remove : (Ljava/lang/Object;)Z
    //   32: pop
    //   33: return
    //   34: invokestatic 你为什么要破解我的代码aaaada : ()Lnet/minecraft/server/MinecraftServer;
    //   37: dup
    //   38: ifnull -> 77
    //   41: aload_0
    //   42: aload_0
    //   43: getfield 我草你怎么反编译我模组aaaaao : Ljava/util/List;
    //   46: aload_0
    //   47: getfield 我草你怎么反编译我模组aaaaau : Ljava/util/Timer;
    //   50: aload_0
    //   51: getfield 我草你怎么反编译我模组aaaaav : Lnet/minecraft/class_1299;
    //   54: aload_0
    //   55: getfield 我草你怎么反编译我模组aaaaaw : Lnet/minecraft/class_3218;
    //   58: aload_0
    //   59: getfield 我草你怎么反编译我模组aaaaaj : Ljava/lang/String;
    //   62: aload_0
    //   63: getfield 我草你怎么反编译我模组aaaaas : Lkotlin/jvm/internal/Ref$IntRef;
    //   66: <illegal opcode> run : (Laaaaaa/aaaaaa/aaaaaa/aaaaaa/aaaaac/aaaacd;Ljava/util/List;Ljava/util/Timer;Lnet/minecraft/class_1299;Lnet/minecraft/class_3218;Ljava/lang/String;Lkotlin/jvm/internal/Ref$IntRef;)Ljava/lang/Runnable;
    //   71: invokevirtual execute : (Ljava/lang/Runnable;)V
    //   74: goto -> 78
    //   77: pop
    //   78: return
  }
  
  private static final void 你为什么要破解我的代码aaaaal(aaaacd paramaaaacd, List paramList, Timer paramTimer, class_1299 paramclass_1299, class_3218 paramclass_3218, String paramString, Ref.IntRef paramIntRef) {
    // Byte code:
    //   0: aload_0
    //   1: ldc -1741488128
    //   3: i2c
    //   4: invokestatic aaaaam : (C)Ljava/lang/Object;
    //   7: checkcast java/lang/String
    //   10: invokestatic checkNotNullParameter : (Ljava/lang/Object;Ljava/lang/String;)V
    //   13: aload_1
    //   14: ldc 1713438721
    //   16: i2c
    //   17: invokestatic aaaaam : (C)Ljava/lang/Object;
    //   20: checkcast java/lang/String
    //   23: invokestatic checkNotNullParameter : (Ljava/lang/Object;Ljava/lang/String;)V
    //   26: aload_2
    //   27: ldc -841547774
    //   29: i2c
    //   30: invokestatic aaaaam : (C)Ljava/lang/Object;
    //   33: checkcast java/lang/String
    //   36: invokestatic checkNotNullParameter : (Ljava/lang/Object;Ljava/lang/String;)V
    //   39: aload_3
    //   40: ldc 159776771
    //   42: i2c
    //   43: invokestatic aaaaam : (C)Ljava/lang/Object;
    //   46: checkcast java/lang/String
    //   49: invokestatic checkNotNullParameter : (Ljava/lang/Object;Ljava/lang/String;)V
    //   52: aload #4
    //   54: ldc 673710084
    //   56: i2c
    //   57: invokestatic aaaaam : (C)Ljava/lang/Object;
    //   60: checkcast java/lang/String
    //   63: invokestatic checkNotNullParameter : (Ljava/lang/Object;Ljava/lang/String;)V
    //   66: aload #6
    //   68: ldc 816971781
    //   70: i2c
    //   71: invokestatic aaaaam : (C)Ljava/lang/Object;
    //   74: checkcast java/lang/String
    //   77: invokestatic checkNotNullParameter : (Ljava/lang/Object;Ljava/lang/String;)V
    //   80: invokestatic 你为什么要破解我的代码aaaada : ()Lnet/minecraft/server/MinecraftServer;
    //   83: dup
    //   84: invokestatic checkNotNull : (Ljava/lang/Object;)V
    //   87: invokevirtual method_3760 : ()Lnet/minecraft/class_3324;
    //   90: dup
    //   91: ifnull -> 235
    //   94: invokevirtual method_14571 : ()Ljava/util/List;
    //   97: dup
    //   98: ifnull -> 235
    //   101: checkcast java/lang/Iterable
    //   104: astore #7
    //   106: iconst_0
    //   107: istore #8
    //   109: aload #7
    //   111: invokeinterface iterator : ()Ljava/util/Iterator;
    //   116: astore #9
    //   118: aload #9
    //   120: invokeinterface hasNext : ()Z
    //   125: ifne -> 132
    //   128: aconst_null
    //   129: goto -> 229
    //   132: aload #9
    //   134: invokeinterface next : ()Ljava/lang/Object;
    //   139: astore #10
    //   141: aload #9
    //   143: invokeinterface hasNext : ()Z
    //   148: ifne -> 156
    //   151: aload #10
    //   153: goto -> 229
    //   156: aload #10
    //   158: checkcast net/minecraft/class_3222
    //   161: astore #11
    //   163: iconst_0
    //   164: istore #12
    //   166: aload #11
    //   168: invokevirtual method_23318 : ()D
    //   171: dstore #13
    //   173: aload #9
    //   175: invokeinterface next : ()Ljava/lang/Object;
    //   180: astore #12
    //   182: aload #12
    //   184: checkcast net/minecraft/class_3222
    //   187: astore #15
    //   189: iconst_0
    //   190: istore #16
    //   192: aload #15
    //   194: invokevirtual method_23318 : ()D
    //   197: dstore #17
    //   199: dload #13
    //   201: dload #17
    //   203: invokestatic compare : (DD)I
    //   206: ifge -> 217
    //   209: aload #12
    //   211: astore #10
    //   213: dload #17
    //   215: dstore #13
    //   217: aload #9
    //   219: invokeinterface hasNext : ()Z
    //   224: ifne -> 173
    //   227: aload #10
    //   229: checkcast net/minecraft/class_3222
    //   232: goto -> 237
    //   235: pop
    //   236: aconst_null
    //   237: astore #19
    //   239: aload #19
    //   241: ifnonnull -> 258
    //   244: aload_0
    //   245: invokevirtual cancel : ()Z
    //   248: pop
    //   249: aload_1
    //   250: aload_2
    //   251: invokeinterface remove : (Ljava/lang/Object;)Z
    //   256: pop
    //   257: return
    //   258: getstatic aaaaaa/aaaaaa/aaaaaa/aaaaaa/aaaaac/aaaaak.我草你怎么反编译我模组aaaaaa : Laaaaaa/aaaaaa/aaaaaa/aaaaaa/aaaaac/aaaaak;
    //   261: invokevirtual 你为什么要破解我的代码aaaaag : ()I
    //   264: invokestatic getSign : (I)I
    //   267: ifge -> 271
    //   270: return
    //   271: getstatic aaaaaa/aaaaaa/aaaaaa/aaaaaa/aaaaac/aaaaak.我草你怎么反编译我模组aaaaaa : Laaaaaa/aaaaaa/aaaaaa/aaaaaa/aaaaac/aaaaak;
    //   274: invokevirtual 你为什么要破解我的代码aaaaae : ()Z
    //   277: ifeq -> 289
    //   280: getstatic aaaaaa/aaaaaa/aaaaaa/aaaaaa/aaaaac/aaaaak.我草你怎么反编译我模组aaaaaa : Laaaaaa/aaaaaa/aaaaaa/aaaaaa/aaaaac/aaaaak;
    //   283: invokevirtual 你为什么要破解我的代码aaaaaa : ()I
    //   286: goto -> 296
    //   289: invokestatic 你为什么要破解我的代码aaaadb : ()D
    //   292: iconst_3
    //   293: i2d
    //   294: dsub
    //   295: d2i
    //   296: istore #20
    //   298: aload #19
    //   300: invokevirtual method_23318 : ()D
    //   303: iconst_3
    //   304: i2d
    //   305: dsub
    //   306: d2i
    //   307: istore #21
    //   309: iload #21
    //   311: bipush #30
    //   313: iadd
    //   314: iconst_1
    //   315: invokestatic 你为什么要破解我的代码aaaadb : ()D
    //   318: d2i
    //   319: invokestatic coerceIn : (III)I
    //   322: istore #7
    //   324: invokestatic 你为什么要破解我的代码aaaade : ()D
    //   327: dstore #22
    //   329: dload #22
    //   331: aload #19
    //   333: invokevirtual method_23321 : ()D
    //   336: dsub
    //   337: dconst_0
    //   338: invokestatic coerceAtLeast : (DD)D
    //   341: dstore #24
    //   343: aconst_null
    //   344: astore #12
    //   346: dload #24
    //   348: ldc2_w 30.0
    //   351: dcmpg
    //   352: ifge -> 415
    //   355: new net/minecraft/class_2338
    //   358: dup
    //   359: new kotlin/ranges/IntRange
    //   362: dup
    //   363: iconst_1
    //   364: bipush #13
    //   366: invokespecial <init> : (II)V
    //   369: getstatic kotlin/random/Random.Default : Lkotlin/random/Random$Default;
    //   372: checkcast kotlin/random/Random
    //   375: invokestatic random : (Lkotlin/ranges/IntRange;Lkotlin/random/Random;)I
    //   378: iconst_3
    //   379: iload #7
    //   381: iadd
    //   382: bipush #66
    //   384: iload #7
    //   386: isub
    //   387: new kotlin/ranges/IntRange
    //   390: dup
    //   391: iconst_5
    //   392: bipush #7
    //   394: invokespecial <init> : (II)V
    //   397: getstatic kotlin/random/Random.Default : Lkotlin/random/Random$Default;
    //   400: checkcast kotlin/random/Random
    //   403: invokestatic random : (Lkotlin/ranges/IntRange;Lkotlin/random/Random;)I
    //   406: iadd
    //   407: invokespecial <init> : (III)V
    //   410: astore #12
    //   412: goto -> 453
    //   415: iload #7
    //   417: iload #20
    //   419: invokestatic coerceAtMost : (II)I
    //   422: istore #15
    //   424: getstatic aaaaaa/aaaaaa/aaaaaa/aaaaaa/aaaaac/aaaaae.我草你怎么反编译我模组aaaaaE : Laaaaaa/aaaaaa/aaaaaa/aaaaaa/aaaaac/aaaaae;
    //   427: new kotlin/ranges/IntRange
    //   430: dup
    //   431: iconst_0
    //   432: bipush #12
    //   434: invokespecial <init> : (II)V
    //   437: getstatic kotlin/random/Random.Default : Lkotlin/random/Random$Default;
    //   440: checkcast kotlin/random/Random
    //   443: invokestatic random : (Lkotlin/ranges/IntRange;Lkotlin/random/Random;)I
    //   446: iload #15
    //   448: invokevirtual 你为什么要破解我的代码aaaacb : (II)Lnet/minecraft/class_2338;
    //   451: astore #12
    //   453: invokestatic 你为什么要破解我的代码aaaaaa : ()Lorg/slf4j/Logger;
    //   456: aload #19
    //   458: invokevirtual method_23318 : ()D
    //   461: aload #19
    //   463: invokevirtual method_23321 : ()D
    //   466: iload #7
    //   468: dload #24
    //   470: aload #12
    //   472: invokevirtual method_10263 : ()I
    //   475: aload #12
    //   477: invokevirtual method_10264 : ()I
    //   480: aload #12
    //   482: invokevirtual method_10260 : ()I
    //   485: <illegal opcode> makeConcatWithConstants : (DDIDIII)Ljava/lang/String;
    //   490: invokestatic trimIndent : (Ljava/lang/String;)Ljava/lang/String;
    //   493: invokeinterface info : (Ljava/lang/String;)V
    //   498: aload_3
    //   499: aload #4
    //   501: checkcast net/minecraft/class_1937
    //   504: invokevirtual method_5883 : (Lnet/minecraft/class_1937;)Lnet/minecraft/class_1297;
    //   507: dup
    //   508: ldc_w 1142292486
    //   511: i2c
    //   512: invokestatic aaaaam : (C)Ljava/lang/Object;
    //   515: checkcast java/lang/String
    //   518: invokestatic checkNotNull : (Ljava/lang/Object;Ljava/lang/String;)V
    //   521: checkcast net/minecraft/class_1308
    //   524: astore #15
    //   526: aload #15
    //   528: aload #12
    //   530: invokevirtual method_10263 : ()I
    //   533: i2d
    //   534: ldc2_w 0.5
    //   537: dadd
    //   538: aload #12
    //   540: invokevirtual method_10264 : ()I
    //   543: i2d
    //   544: aload #12
    //   546: invokevirtual method_10260 : ()I
    //   549: i2d
    //   550: ldc2_w 0.5
    //   553: dadd
    //   554: invokevirtual method_5814 : (DDD)V
    //   557: aload #15
    //   559: iconst_1
    //   560: putfield field_5960 : Z
    //   563: aload #5
    //   565: ifnull -> 592
    //   568: aload #15
    //   570: aload #5
    //   572: <illegal opcode> makeConcatWithConstants : (Ljava/lang/String;)Ljava/lang/String;
    //   577: invokestatic method_43470 : (Ljava/lang/String;)Lnet/minecraft/class_5250;
    //   580: checkcast net/minecraft/class_2561
    //   583: invokevirtual method_5665 : (Lnet/minecraft/class_2561;)V
    //   586: aload #15
    //   588: iconst_1
    //   589: invokevirtual method_5880 : (Z)V
    //   592: aload #15
    //   594: astore #16
    //   596: aload #16
    //   598: instanceof net/minecraft/class_1642
    //   601: ifeq -> 628
    //   604: aload #15
    //   606: getstatic net/minecraft/class_1304.field_6169 : Lnet/minecraft/class_1304;
    //   609: new net/minecraft/class_1799
    //   612: dup
    //   613: getstatic net/minecraft/class_1802.field_8805 : Lnet/minecraft/class_1792;
    //   616: checkcast net/minecraft/class_1935
    //   619: invokespecial <init> : (Lnet/minecraft/class_1935;)V
    //   622: invokevirtual method_5673 : (Lnet/minecraft/class_1304;Lnet/minecraft/class_1799;)V
    //   625: goto -> 731
    //   628: aload #16
    //   630: instanceof net/minecraft/class_1613
    //   633: ifeq -> 681
    //   636: aload #15
    //   638: getstatic net/minecraft/class_1304.field_6169 : Lnet/minecraft/class_1304;
    //   641: new net/minecraft/class_1799
    //   644: dup
    //   645: getstatic net/minecraft/class_1802.field_8805 : Lnet/minecraft/class_1792;
    //   648: checkcast net/minecraft/class_1935
    //   651: invokespecial <init> : (Lnet/minecraft/class_1935;)V
    //   654: invokevirtual method_5673 : (Lnet/minecraft/class_1304;Lnet/minecraft/class_1799;)V
    //   657: aload #15
    //   659: getstatic net/minecraft/class_1304.field_6173 : Lnet/minecraft/class_1304;
    //   662: new net/minecraft/class_1799
    //   665: dup
    //   666: getstatic net/minecraft/class_1802.field_8102 : Lnet/minecraft/class_1792;
    //   669: checkcast net/minecraft/class_1935
    //   672: invokespecial <init> : (Lnet/minecraft/class_1935;)V
    //   675: invokevirtual method_5673 : (Lnet/minecraft/class_1304;Lnet/minecraft/class_1799;)V
    //   678: goto -> 731
    //   681: aload #16
    //   683: instanceof net/minecraft/class_1639
    //   686: ifeq -> 731
    //   689: aload #15
    //   691: getstatic net/minecraft/class_1304.field_6169 : Lnet/minecraft/class_1304;
    //   694: new net/minecraft/class_1799
    //   697: dup
    //   698: getstatic net/minecraft/class_1802.field_8805 : Lnet/minecraft/class_1792;
    //   701: checkcast net/minecraft/class_1935
    //   704: invokespecial <init> : (Lnet/minecraft/class_1935;)V
    //   707: invokevirtual method_5673 : (Lnet/minecraft/class_1304;Lnet/minecraft/class_1799;)V
    //   710: aload #15
    //   712: getstatic net/minecraft/class_1304.field_6173 : Lnet/minecraft/class_1304;
    //   715: new net/minecraft/class_1799
    //   718: dup
    //   719: getstatic net/minecraft/class_1802.field_8528 : Lnet/minecraft/class_1792;
    //   722: checkcast net/minecraft/class_1935
    //   725: invokespecial <init> : (Lnet/minecraft/class_1935;)V
    //   728: invokevirtual method_5673 : (Lnet/minecraft/class_1304;Lnet/minecraft/class_1799;)V
    //   731: aload #4
    //   733: aload #15
    //   735: checkcast net/minecraft/class_1297
    //   738: invokevirtual method_8649 : (Lnet/minecraft/class_1297;)Z
    //   741: pop
    //   742: new net/minecraft/class_1695
    //   745: dup
    //   746: getstatic net/minecraft/class_1299.field_6096 : Lnet/minecraft/class_1299;
    //   749: aload #4
    //   751: checkcast net/minecraft/class_1937
    //   754: invokespecial <init> : (Lnet/minecraft/class_1299;Lnet/minecraft/class_1937;)V
    //   757: astore #16
    //   759: aload #16
    //   761: aload #12
    //   763: invokevirtual method_10263 : ()I
    //   766: i2d
    //   767: ldc2_w 0.5
    //   770: dadd
    //   771: aload #12
    //   773: invokevirtual method_10264 : ()I
    //   776: i2d
    //   777: aload #12
    //   779: invokevirtual method_10260 : ()I
    //   782: i2d
    //   783: ldc2_w 0.5
    //   786: dadd
    //   787: invokevirtual method_5814 : (DDD)V
    //   790: aload #16
    //   792: iconst_1
    //   793: putfield field_5960 : Z
    //   796: aload #4
    //   798: aload #16
    //   800: checkcast net/minecraft/class_1297
    //   803: invokevirtual method_8649 : (Lnet/minecraft/class_1297;)Z
    //   806: pop
    //   807: aload #15
    //   809: aload #16
    //   811: checkcast net/minecraft/class_1297
    //   814: invokevirtual method_5804 : (Lnet/minecraft/class_1297;)Z
    //   817: pop
    //   818: aload #6
    //   820: getfield element : I
    //   823: istore #26
    //   825: aload #6
    //   827: iload #26
    //   829: iconst_1
    //   830: iadd
    //   831: putfield element : I
    //   834: return
  }
  
  static {
    byte[] arrayOfByte1 = "Kóç,òË;þéãYv\006j\032ÛÊ«vì]çA\022ÏG\033(¿Ä\003ØD¦ªX\020µ|ç)¨Õ\034\000ÃÍ~\033KR\0177æ\030W0Z%7ñ×\\½;\024Q=*{Ýi\002 \004ÎÌ¹&VýHç~ä4¬·å&\004}â¢&Ã#ÏÂRq\001\021¢ÚêôP_x\022xfN\nXom+÷2\006þ %wôS \bÆg·\0249'êgî²º±y8)×4Ö".getBytes("ISO_8859_1");
    byte[] arrayOfByte2 = "!E2ÐK±F".getBytes("ISO_8859_1");
    int i = 0;
    int j = arrayOfByte1.length;
    while (true) {
      switch (arrayOfByte1[i] & 0xFF) {
        case 0:
        
        case 1:
        
        case 2:
        
        case 3:
        
        case 4:
        
        case 5:
        
        case 6:
        
        case 7:
        
        case 8:
        
        case 9:
        
        case 10:
        
        case 11:
        
        case 12:
        
        case 13:
        
        case 14:
        
        case 15:
        
        case 16:
        
        case 17:
        
        case 18:
        
        case 19:
        
        case 20:
        
        case 21:
        
        case 22:
        
        case 23:
        
        case 24:
        
        case 25:
        
        case 26:
        
        case 27:
        
        case 28:
        
        case 29:
        
        case 30:
        
        case 31:
        
        case 32:
        
        case 33:
        
        case 34:
        
        case 35:
        
        case 36:
        
        case 37:
        
        case 38:
        
        case 39:
        
        case 40:
        
        case 41:
        
        case 42:
        
        case 43:
        
        case 44:
        
        case 45:
        
        case 46:
        
        case 47:
        
        case 48:
        
        case 49:
        
        case 50:
        
        case 51:
        
        case 52:
        
        case 53:
        
        case 54:
        
        case 55:
        
        case 56:
        
        case 57:
        
        case 58:
        
        case 59:
        
        case 60:
        
        case 61:
        
        case 62:
        
        case 63:
        
        case 64:
        
        case 65:
        
        case 66:
        
        case 67:
        
        case 68:
        
        case 69:
        
        case 70:
        
        case 71:
        
        case 72:
        
        case 73:
        
        case 74:
        
        case 75:
        
        case 76:
        
        case 77:
        
        case 78:
        
        case 79:
        
        case 80:
        
        case 81:
        
        case 82:
        
        case 83:
        
        case 84:
        
        case 85:
        
        case 86:
        
        case 87:
        
        case 88:
        
        case 89:
        
        case 90:
        
        case 91:
        
        case 92:
        
        case 93:
        
        case 94:
        
        case 95:
        
        case 96:
        
        case 97:
        
        case 98:
        
        case 99:
        
        case 100:
        
        case 101:
        
        case 102:
        
        case 103:
        
        case 104:
        
        case 105:
        
        case 106:
        
        case 107:
        
        case 108:
        
        case 109:
        
        case 110:
        
        case 111:
        
        case 112:
        
        case 113:
        
        case 114:
        
        case 115:
        
        case 116:
        
        case 117:
        
        case 118:
        
        case 119:
        
        case 120:
        
        case 121:
        
        case 122:
        
        case 123:
        
        case 124:
        
        case 125:
        
        case 126:
        
        case 127:
        
        case 128:
        
        case 129:
        
        case 130:
        
        case 131:
        
        case 132:
        
        case 133:
        
        case 134:
        
        case 135:
        
        case 136:
        
        case 137:
        
        case 138:
        
        case 139:
        
        case 140:
        
        case 141:
        
        case 142:
        
        case 143:
        
        case 144:
        
        case 145:
        
        case 146:
        
        case 147:
        
        case 148:
        
        case 149:
        
        case 150:
        
        case 151:
        
        case 152:
        
        case 153:
        
        case 154:
        
        case 155:
        
        case 156:
        
        case 157:
        
        case 158:
        
        case 159:
        
        case 160:
        
        case 161:
        
        case 162:
        
        case 163:
        
        case 164:
        
        case 165:
        
        case 166:
        
        case 167:
        
        case 168:
        
        case 169:
        
        case 170:
        
        case 171:
        
        case 172:
        
        case 173:
        
        case 174:
        
        case 175:
        
        case 176:
        
        case 177:
        
        case 178:
        
        case 179:
        
        case 180:
        
        case 181:
        
        case 182:
        
        case 183:
        
        case 184:
        
        case 185:
        
        case 186:
        
        case 187:
        
        case 188:
        
        case 189:
        
        case 190:
        
        case 191:
        
        case 192:
        
        case 193:
        
        case 194:
        
        case 195:
        
        case 196:
        
        case 197:
        
        case 198:
        
        case 199:
        
        case 200:
        
        case 201:
        
        case 202:
        
        case 203:
        
        case 204:
        
        case 205:
        
        case 206:
        
        case 207:
        
        case 208:
        
        case 209:
        
        case 210:
        
        case 211:
        
        case 212:
        
        case 213:
        
        case 214:
        
        case 215:
        
        case 216:
        
        case 217:
        
        case 218:
        
        case 219:
        
        case 220:
        
        case 221:
        
        case 222:
        
        case 223:
        
        case 224:
        
        case 225:
        
        case 226:
        
        case 227:
        
        case 228:
        
        case 229:
        
        case 230:
        
        case 231:
        
        case 232:
        
        case 233:
        
        case 234:
        
        case 235:
        
        case 236:
        
        case 237:
        
        case 238:
        
        case 239:
        
        case 240:
        
        case 241:
        
        case 242:
        
        case 243:
        
        case 244:
        
        case 245:
        
        case 246:
        
        case 247:
        
        case 248:
        
        case 249:
        
        case 250:
        
        case 251:
        
        case 252:
        
        case 253:
        
        case 254:
        
        case 255:
        
        default:
          break;
      } 
      arrayOfByte1[i++] = (byte)79512198;
      if (i == j) {
        Cipher.getInstance("DES/CBC/PKCS5Padding").init(2, SecretKeyFactory.getInstance("DES").generateSecret(new DESKeySpec(arrayOfByte2)), new IvParameterSpec(new byte[8]));
        j = (arrayOfByte1 = Cipher.getInstance("DES/CBC/PKCS5Padding").doFinal(arrayOfByte1)).length;
        MessageDigest.getInstance("SHA-256").reset();
        MessageDigest.getInstance("SHA-256").update(arrayOfByte1, 0, i = j - 32);
        arrayOfByte2 = MessageDigest.getInstance("SHA-256").digest();
        int k = 0;
        int m = 0;
        byte b = 0;
        while (true) {
          m |= arrayOfByte1[i + k] ^ arrayOfByte2[k];
          if (++k == 32) {
            if (m == 0) {
              Object[] arrayOfObject = new Object[7];
              j = i;
              i = 0;
              do {
                byte[] arrayOfByte = new byte[k = arrayOfByte1[i++] & 0xFF | (arrayOfByte1[i++] & 0xFF) << 8];
                System.arraycopy(arrayOfByte1, i, arrayOfByte, 0, k);
                i += k;
                arrayOfObject[b++] = (new String(arrayOfByte, "UTF-8")).intern();
              } while (i != j);
            } 
            return;
          } 
        } 
        break;
      } 
    } 
  }
  
  private static Object aaaaam(char paramChar) {
    return ((Object[])aaaaax)[paramChar];
  }
}
