package aaaaaa.aaaaaa.aaaaaa.aaaaaa.aaaaac;

import aaaaaa.aaaaaa.aaaaaa.aaaaaa.aaaaah.aaaaaa.aaaaaa;
import aaaaaa.aaaaaa.aaaaaa.aaaaaa.aaaaah.aaaaac;
import java.security.MessageDigest;
import javax.crypto.Cipher;
import javax.crypto.SecretKeyFactory;
import javax.crypto.spec.DESKeySpec;
import javax.crypto.spec.IvParameterSpec;
import kotlin.Unit;
import kotlin.coroutines.Continuation;
import kotlin.coroutines.jvm.internal.SuspendLambda;
import kotlin.jvm.functions.Function2;
import kotlin.jvm.internal.Intrinsics;
import kotlinx.coroutines.CoroutineScope;
import net.minecraft.class_1299;
import org.jetbrains.annotations.NotNull;
import org.jetbrains.annotations.Nullable;

final class aaaabh extends SuspendLambda implements Function2<CoroutineScope, Continuation<? super Unit>, Object> {
  int 我草你怎么反编译我模组aaaaae;
  
  int 我草你怎么反编译我模组aaaaau;
  
  int 我草你怎么反编译我模组aaaaaJ;
  
  Object 我草你怎么反编译我模组aaaaac;
  
  Object 我草你怎么反编译我模组aaaaad;
  
  int 我草你怎么反编译我模组aaaaaf;
  
  static Object aaaabS;
  
  aaaabh(int paramInt1, int paramInt2, aaaabW paramaaaabW, String paramString, Continuation<? super aaaabh> paramContinuation) {
    super(2, paramContinuation);
  }
  
  @Nullable
  public final Object invokeSuspend(@NotNull Object paramObject) {
    // Byte code:
    //   0: invokestatic getCOROUTINE_SUSPENDED : ()Ljava/lang/Object;
    //   3: astore_2
    //   4: aload_0
    //   5: getfield 我草你怎么反编译我模组aaaaaf : I
    //   8: tableswitch default -> 313, 0 -> 32, 1 -> 259
    //   32: aload_1
    //   33: invokestatic throwOnFailure : (Ljava/lang/Object;)V
    //   36: aload_0
    //   37: getfield 我草你怎么反编译我模组aaaaaj : I
    //   40: istore_3
    //   41: aload_0
    //   42: getfield 我草你怎么反编译我模组aaaabR : I
    //   45: istore #4
    //   47: aload_0
    //   48: getfield 我草你怎么反编译我模组aaaaav : Laaaaaa/aaaaaa/aaaaaa/aaaaaa/aaaaac/aaaabW;
    //   51: astore #5
    //   53: aload_0
    //   54: getfield 我草你怎么反编译我模组aaaaah : Ljava/lang/String;
    //   57: astore #6
    //   59: iconst_0
    //   60: istore #7
    //   62: iload #7
    //   64: iload_3
    //   65: if_icmpge -> 309
    //   68: iconst_0
    //   69: istore #8
    //   71: getstatic aaaaaa/aaaaaa/aaaaaa/aaaaaa/aaaaac/aaaabW.我草你怎么反编译我模组aaaacY : Laaaaaa/aaaaaa/aaaaaa/aaaaaa/aaaaac/aaaabW;
    //   74: invokevirtual 你为什么要破解我的代码aaaakb : ()D
    //   77: d2i
    //   78: iconst_1
    //   79: iadd
    //   80: getstatic aaaaaa/aaaaaa/aaaaaa/aaaaaa/aaaaac/aaaabW.我草你怎么反编译我模组aaaacY : Laaaaaa/aaaaaa/aaaaaa/aaaaaa/aaaaac/aaaabW;
    //   83: invokevirtual 你为什么要破解我的代码aaaaiw : ()Lnet/minecraft/class_2338;
    //   86: invokevirtual method_10263 : ()I
    //   89: iconst_1
    //   90: isub
    //   91: invokestatic until : (II)Lkotlin/ranges/IntRange;
    //   94: checkcast java/lang/Iterable
    //   97: invokestatic toList : (Ljava/lang/Iterable;)Ljava/util/List;
    //   100: astore #9
    //   102: aload #9
    //   104: checkcast java/lang/Iterable
    //   107: invokestatic shuffled : (Ljava/lang/Iterable;)Ljava/util/List;
    //   110: checkcast java/lang/Iterable
    //   113: iload #4
    //   115: invokestatic take : (Ljava/lang/Iterable;I)Ljava/util/List;
    //   118: astore #10
    //   120: getstatic aaaaaa/aaaaaa/aaaaaa/aaaaaa/aaaaac/aaaabW.我草你怎么反编译我模组aaaacY : Laaaaaa/aaaaaa/aaaaaa/aaaaaa/aaaaac/aaaabW;
    //   123: invokevirtual 你为什么要破解我的代码aaaaeR : ()Lnet/minecraft/server/MinecraftServer;
    //   126: dup
    //   127: ifnull -> 145
    //   130: aload #5
    //   132: aload #6
    //   134: <illegal opcode> run : (Laaaaaa/aaaaaa/aaaaaa/aaaaaa/aaaaac/aaaabW;Ljava/lang/String;)Ljava/lang/Runnable;
    //   139: invokevirtual execute : (Ljava/lang/Runnable;)V
    //   142: goto -> 146
    //   145: pop
    //   146: aload #10
    //   148: invokeinterface iterator : ()Ljava/util/Iterator;
    //   153: astore #11
    //   155: aload #11
    //   157: invokeinterface hasNext : ()Z
    //   162: ifeq -> 211
    //   165: aload #11
    //   167: invokeinterface next : ()Ljava/lang/Object;
    //   172: checkcast java/lang/Number
    //   175: invokevirtual intValue : ()I
    //   178: istore #12
    //   180: getstatic aaaaaa/aaaaaa/aaaaaa/aaaaaa/aaaaac/aaaabW.我草你怎么反编译我模组aaaacY : Laaaaaa/aaaaaa/aaaaaa/aaaaaa/aaaaac/aaaabW;
    //   183: invokevirtual 你为什么要破解我的代码aaaaeR : ()Lnet/minecraft/server/MinecraftServer;
    //   186: dup
    //   187: ifnull -> 207
    //   190: iload #12
    //   192: aload #5
    //   194: aload #6
    //   196: <illegal opcode> run : (ILaaaaaa/aaaaaa/aaaaaa/aaaaaa/aaaaac/aaaabW;Ljava/lang/String;)Ljava/lang/Runnable;
    //   201: invokevirtual execute : (Ljava/lang/Runnable;)V
    //   204: goto -> 155
    //   207: pop
    //   208: goto -> 155
    //   211: ldc2_w 500
    //   214: aload_0
    //   215: aload_0
    //   216: aload #5
    //   218: putfield 我草你怎么反编译我模组aaaaac : Ljava/lang/Object;
    //   221: aload_0
    //   222: aload #6
    //   224: putfield 我草你怎么反编译我模组aaaaad : Ljava/lang/Object;
    //   227: aload_0
    //   228: iload_3
    //   229: putfield 我草你怎么反编译我模组aaaaae : I
    //   232: aload_0
    //   233: iload #4
    //   235: putfield 我草你怎么反编译我模组aaaaau : I
    //   238: aload_0
    //   239: iload #7
    //   241: putfield 我草你怎么反编译我模组aaaaaJ : I
    //   244: aload_0
    //   245: iconst_1
    //   246: putfield 我草你怎么反编译我模组aaaaaf : I
    //   249: invokestatic delay : (JLkotlin/coroutines/Continuation;)Ljava/lang/Object;
    //   252: dup
    //   253: aload_2
    //   254: if_acmpne -> 302
    //   257: aload_2
    //   258: areturn
    //   259: iconst_0
    //   260: istore #8
    //   262: aload_0
    //   263: getfield 我草你怎么反编译我模组aaaaaJ : I
    //   266: istore #7
    //   268: aload_0
    //   269: getfield 我草你怎么反编译我模组aaaaau : I
    //   272: istore #4
    //   274: aload_0
    //   275: getfield 我草你怎么反编译我模组aaaaae : I
    //   278: istore_3
    //   279: aload_0
    //   280: getfield 我草你怎么反编译我模组aaaaad : Ljava/lang/Object;
    //   283: checkcast java/lang/String
    //   286: astore #6
    //   288: aload_0
    //   289: getfield 我草你怎么反编译我模组aaaaac : Ljava/lang/Object;
    //   292: checkcast aaaaaa/aaaaaa/aaaaaa/aaaaaa/aaaaac/aaaabW
    //   295: astore #5
    //   297: aload_1
    //   298: invokestatic throwOnFailure : (Ljava/lang/Object;)V
    //   301: aload_1
    //   302: pop
    //   303: iinc #7, 1
    //   306: goto -> 62
    //   309: getstatic kotlin/Unit.INSTANCE : Lkotlin/Unit;
    //   312: areturn
    //   313: new java/lang/IllegalStateException
    //   316: dup
    //   317: ldc 1994915840
    //   319: i2c
    //   320: invokestatic aaaaaF : (C)Ljava/lang/Object;
    //   323: checkcast java/lang/String
    //   326: invokespecial <init> : (Ljava/lang/String;)V
    //   329: athrow
  }
  
  @NotNull
  public final Continuation<Unit> create(@Nullable Object paramObject, @NotNull Continuation<?> paramContinuation) {
    return (Continuation<Unit>)new aaaabh(this.我草你怎么反编译我模组aaaaaj, this.我草你怎么反编译我模组aaaabR, this.我草你怎么反编译我模组aaaaav, this.我草你怎么反编译我模组aaaaah, (Continuation)paramContinuation);
  }
  
  @Nullable
  public final Object 你为什么要破解我的代码aaaaab(@NotNull CoroutineScope paramCoroutineScope, @Nullable Continuation<? super Unit> paramContinuation) {
    return ((aaaabh)create(paramCoroutineScope, paramContinuation)).invokeSuspend(Unit.INSTANCE);
  }
  
  private static final void 你为什么要破解我的代码aaaaaD(aaaabW paramaaaabW, String paramString) {
    Intrinsics.checkNotNullExpressionValue(class_1299.field_6139, (String)aaaaaF((char)1961492481));
    aaaaac aaaaac = new aaaaac(class_1299.field_6139, aaaabW.我草你怎么反编译我模组aaaacY.你为什么要破解我的代码aaaaiw().method_10263() - true, 1, aaaaaa.我草你怎么反编译我模组aaaaao, false, paramaaaabW);
    aaaaac.你为什么要破解我的代码aaaaaa(paramString);
  }
  
  private static final void 你为什么要破解我的代码aaaaaE(int paramInt, aaaabW paramaaaabW, String paramString) {
    Intrinsics.checkNotNullExpressionValue(class_1299.field_6139, (String)aaaaaF((char)-1944453119));
    aaaaac aaaaac = new aaaaac(class_1299.field_6139, paramInt, 1, aaaaaa.我草你怎么反编译我模组aaaaao, false, paramaaaabW);
    aaaaac.你为什么要破解我的代码aaaaaa(paramString);
  }
  
  static {
    byte[] arrayOfByte1 = "µÈñfÊY\016É\016&\030¾Í0\004\033æÍ\036a1r«ÎÐÌw©Nk¢o÷ÇK^Òr@/%Yç°\017t£3ÿ3\02092î<ÇqË$qÔ_qøegGl)\t*ÞÕûì'öSçá\036ì".getBytes("ISO_8859_1");
    byte[] arrayOfByte2 = "66ÇQ\031Ç".getBytes("ISO_8859_1");
    int i = 0;
    int j = arrayOfByte1.length;
    while (true) {
      switch (arrayOfByte1[i] & 0xFF) {
        case 0:
        
        case 1:
        
        case 2:
        
        case 3:
        
        case 4:
        
        case 5:
        
        case 6:
        
        case 7:
        
        case 8:
        
        case 9:
        
        case 10:
        
        case 11:
        
        case 12:
        
        case 13:
        
        case 14:
        
        case 15:
        
        case 16:
        
        case 17:
        
        case 18:
        
        case 19:
        
        case 20:
        
        case 21:
        
        case 22:
        
        case 23:
        
        case 24:
        
        case 25:
        
        case 26:
        
        case 27:
        
        case 28:
        
        case 29:
        
        case 30:
        
        case 31:
        
        case 32:
        
        case 33:
        
        case 34:
        
        case 35:
        
        case 36:
        
        case 37:
        
        case 38:
        
        case 39:
        
        case 40:
        
        case 41:
        
        case 42:
        
        case 43:
        
        case 44:
        
        case 45:
        
        case 46:
        
        case 47:
        
        case 48:
        
        case 49:
        
        case 50:
        
        case 51:
        
        case 52:
        
        case 53:
        
        case 54:
        
        case 55:
        
        case 56:
        
        case 57:
        
        case 58:
        
        case 59:
        
        case 60:
        
        case 61:
        
        case 62:
        
        case 63:
        
        case 64:
        
        case 65:
        
        case 66:
        
        case 67:
        
        case 68:
        
        case 69:
        
        case 70:
        
        case 71:
        
        case 72:
        
        case 73:
        
        case 74:
        
        case 75:
        
        case 76:
        
        case 77:
        
        case 78:
        
        case 79:
        
        case 80:
        
        case 81:
        
        case 82:
        
        case 83:
        
        case 84:
        
        case 85:
        
        case 86:
        
        case 87:
        
        case 88:
        
        case 89:
        
        case 90:
        
        case 91:
        
        case 92:
        
        case 93:
        
        case 94:
        
        case 95:
        
        case 96:
        
        case 97:
        
        case 98:
        
        case 99:
        
        case 100:
        
        case 101:
        
        case 102:
        
        case 103:
        
        case 104:
        
        case 105:
        
        case 106:
        
        case 107:
        
        case 108:
        
        case 109:
        
        case 110:
        
        case 111:
        
        case 112:
        
        case 113:
        
        case 114:
        
        case 115:
        
        case 116:
        
        case 117:
        
        case 118:
        
        case 119:
        
        case 120:
        
        case 121:
        
        case 122:
        
        case 123:
        
        case 124:
        
        case 125:
        
        case 126:
        
        case 127:
        
        case 128:
        
        case 129:
        
        case 130:
        
        case 131:
        
        case 132:
        
        case 133:
        
        case 134:
        
        case 135:
        
        case 136:
        
        case 137:
        
        case 138:
        
        case 139:
        
        case 140:
        
        case 141:
        
        case 142:
        
        case 143:
        
        case 144:
        
        case 145:
        
        case 146:
        
        case 147:
        
        case 148:
        
        case 149:
        
        case 150:
        
        case 151:
        
        case 152:
        
        case 153:
        
        case 154:
        
        case 155:
        
        case 156:
        
        case 157:
        
        case 158:
        
        case 159:
        
        case 160:
        
        case 161:
        
        case 162:
        
        case 163:
        
        case 164:
        
        case 165:
        
        case 166:
        
        case 167:
        
        case 168:
        
        case 169:
        
        case 170:
        
        case 171:
        
        case 172:
        
        case 173:
        
        case 174:
        
        case 175:
        
        case 176:
        
        case 177:
        
        case 178:
        
        case 179:
        
        case 180:
        
        case 181:
        
        case 182:
        
        case 183:
        
        case 184:
        
        case 185:
        
        case 186:
        
        case 187:
        
        case 188:
        
        case 189:
        
        case 190:
        
        case 191:
        
        case 192:
        
        case 193:
        
        case 194:
        
        case 195:
        
        case 196:
        
        case 197:
        
        case 198:
        
        case 199:
        
        case 200:
        
        case 201:
        
        case 202:
        
        case 203:
        
        case 204:
        
        case 205:
        
        case 206:
        
        case 207:
        
        case 208:
        
        case 209:
        
        case 210:
        
        case 211:
        
        case 212:
        
        case 213:
        
        case 214:
        
        case 215:
        
        case 216:
        
        case 217:
        
        case 218:
        
        case 219:
        
        case 220:
        
        case 221:
        
        case 222:
        
        case 223:
        
        case 224:
        
        case 225:
        
        case 226:
        
        case 227:
        
        case 228:
        
        case 229:
        
        case 230:
        
        case 231:
        
        case 232:
        
        case 233:
        
        case 234:
        
        case 235:
        
        case 236:
        
        case 237:
        
        case 238:
        
        case 239:
        
        case 240:
        
        case 241:
        
        case 242:
        
        case 243:
        
        case 244:
        
        case 245:
        
        case 246:
        
        case 247:
        
        case 248:
        
        case 249:
        
        case 250:
        
        case 251:
        
        case 252:
        
        case 253:
        
        case 254:
        
        case 255:
        
        default:
          break;
      } 
      arrayOfByte1[i++] = (byte)-1728585538;
      if (i == j) {
        Cipher.getInstance("DES/CBC/PKCS5Padding").init(2, SecretKeyFactory.getInstance("DES").generateSecret(new DESKeySpec(arrayOfByte2)), new IvParameterSpec(new byte[8]));
        j = (arrayOfByte1 = Cipher.getInstance("DES/CBC/PKCS5Padding").doFinal(arrayOfByte1)).length;
        MessageDigest.getInstance("SHA-256").reset();
        MessageDigest.getInstance("SHA-256").update(arrayOfByte1, 0, i = j - 32);
        arrayOfByte2 = MessageDigest.getInstance("SHA-256").digest();
        int k = 0;
        int m = 0;
        byte b = 0;
        while (true) {
          m |= arrayOfByte1[i + k] ^ arrayOfByte2[k];
          if (++k == 32) {
            if (m == 0) {
              Object[] arrayOfObject = new Object[2];
              j = i;
              i = 0;
              do {
                byte[] arrayOfByte = new byte[k = arrayOfByte1[i++] & 0xFF | (arrayOfByte1[i++] & 0xFF) << 8];
                System.arraycopy(arrayOfByte1, i, arrayOfByte, 0, k);
                i += k;
                arrayOfObject[b++] = (new String(arrayOfByte, "UTF-8")).intern();
              } while (i != j);
            } 
            return;
          } 
        } 
        break;
      } 
    } 
  }
  
  private static Object aaaaaF(char paramChar) {
    return ((Object[])aaaabS)[paramChar];
  }
}
