package aaaaaa.aaaaaa.aaaaaa.aaaaaa.aaaaac;

import java.security.MessageDigest;
import javax.crypto.Cipher;
import javax.crypto.SecretKeyFactory;
import javax.crypto.spec.DESKeySpec;
import javax.crypto.spec.IvParameterSpec;
import kotlin.Unit;
import kotlin.coroutines.Continuation;
import kotlin.coroutines.jvm.internal.SuspendLambda;
import kotlin.jvm.functions.Function2;
import kotlinx.coroutines.CoroutineScope;
import net.minecraft.class_3222;
import org.jetbrains.annotations.NotNull;
import org.jetbrains.annotations.Nullable;

final class aaaaav extends SuspendLambda implements Function2<CoroutineScope, Continuation<? super Unit>, Object> {
  float 我草你怎么反编译我模组aaaaaG;
  
  long 我草你怎么反编译我模组aaaaaH;
  
  int 我草你怎么反编译我模组aaaaae;
  
  int 我草你怎么反编译我模组aaaaau;
  
  int 我草你怎么反编译我模组aaaaaf;
  
  static Object aaaaaI;
  
  aaaaav(class_3222 paramclass_3222, int paramInt, Continuation<? super aaaaav> paramContinuation) {
    super(2, paramContinuation);
  }
  
  @Nullable
  public final Object invokeSuspend(@NotNull Object paramObject) {
    // Byte code:
    //   0: invokestatic getCOROUTINE_SUSPENDED : ()Ljava/lang/Object;
    //   3: astore_2
    //   4: aload_0
    //   5: getfield 我草你怎么反编译我模组aaaaaf : I
    //   8: tableswitch default -> 443, 0 -> 32, 1 -> 380
    //   32: aload_1
    //   33: invokestatic throwOnFailure : (Ljava/lang/Object;)V
    //   36: aload_0
    //   37: getfield 我草你怎么反编译我模组aaaaak : Lnet/minecraft/class_3222;
    //   40: invokevirtual method_36454 : ()F
    //   43: fstore_3
    //   44: invokestatic currentTimeMillis : ()J
    //   47: lstore #4
    //   49: aload_0
    //   50: getfield 我草你怎么反编译我模组aaaaaj : I
    //   53: sipush #1000
    //   56: imul
    //   57: istore #6
    //   59: iconst_0
    //   60: istore #7
    //   62: nop
    //   63: invokestatic currentTimeMillis : ()J
    //   66: lstore #8
    //   68: lload #8
    //   70: lload #4
    //   72: lsub
    //   73: lstore #10
    //   75: lload #10
    //   77: iload #6
    //   79: i2l
    //   80: lcmp
    //   81: ifge -> 412
    //   84: lload #10
    //   86: l2f
    //   87: iload #6
    //   89: i2f
    //   90: fdiv
    //   91: fstore #12
    //   93: fload_3
    //   94: fload #12
    //   96: sipush #360
    //   99: i2f
    //   100: fmul
    //   101: aload_0
    //   102: getfield 我草你怎么反编译我模组aaaaaj : I
    //   105: i2f
    //   106: fmul
    //   107: fadd
    //   108: fstore #13
    //   110: fload #12
    //   112: aload_0
    //   113: getfield 我草你怎么反编译我模组aaaaaj : I
    //   116: i2f
    //   117: fmul
    //   118: f2i
    //   119: istore #14
    //   121: iload #14
    //   123: iload #7
    //   125: if_icmple -> 150
    //   128: iload #14
    //   130: istore #7
    //   132: getstatic aaaaaa/aaaaaa/aaaaaa/aaaaaa/aaaaag/aaaaaa/aaaaap.我草你怎么反编译我模组aaaaaa : Laaaaaa/aaaaaa/aaaaaa/aaaaaa/aaaaag/aaaaaa/aaaaaS;
    //   135: invokevirtual 你为什么要破解我的代码aaaaaa : ()Laaaaaa/aaaaaa/aaaaaa/aaaaaa/aaaaag/aaaaaa/aaaaap;
    //   138: ldc 663617536
    //   140: i2c
    //   141: invokestatic aaaaao : (C)Ljava/lang/Object;
    //   144: checkcast java/lang/String
    //   147: invokevirtual 你为什么要破解我的代码aaaaac : (Ljava/lang/String;)V
    //   150: iload #6
    //   152: i2l
    //   153: lload #10
    //   155: lsub
    //   156: l2d
    //   157: ldc2_w 1000.0
    //   160: ddiv
    //   161: dstore #15
    //   163: dload #15
    //   165: ldc2_w 0.2
    //   168: dcmpg
    //   169: ifge -> 175
    //   172: dconst_0
    //   173: dstore #15
    //   175: getstatic kotlin/jvm/internal/StringCompanionObject.INSTANCE : Lkotlin/jvm/internal/StringCompanionObject;
    //   178: pop
    //   179: ldc -2072707071
    //   181: i2c
    //   182: invokestatic aaaaao : (C)Ljava/lang/Object;
    //   185: checkcast java/lang/String
    //   188: astore #17
    //   190: iconst_1
    //   191: anewarray java/lang/Object
    //   194: astore #18
    //   196: aload #18
    //   198: iconst_0
    //   199: dload #15
    //   201: invokestatic boxDouble : (D)Ljava/lang/Double;
    //   204: aastore
    //   205: aload #18
    //   207: astore #18
    //   209: aload #17
    //   211: aload #18
    //   213: aload #18
    //   215: arraylength
    //   216: invokestatic copyOf : ([Ljava/lang/Object;I)[Ljava/lang/Object;
    //   219: invokestatic format : (Ljava/lang/String;[Ljava/lang/Object;)Ljava/lang/String;
    //   222: dup
    //   223: ldc -132055038
    //   225: i2c
    //   226: invokestatic aaaaao : (C)Ljava/lang/Object;
    //   229: checkcast java/lang/String
    //   232: invokestatic checkNotNullExpressionValue : (Ljava/lang/Object;Ljava/lang/String;)V
    //   235: astore #19
    //   237: aload_0
    //   238: getfield 我草你怎么反编译我模组aaaaak : Lnet/minecraft/class_3222;
    //   241: getfield field_13987 : Lnet/minecraft/class_3244;
    //   244: new net/minecraft/class_5894
    //   247: dup
    //   248: ldc 436928515
    //   250: i2c
    //   251: invokestatic aaaaao : (C)Ljava/lang/Object;
    //   254: checkcast java/lang/String
    //   257: iconst_2
    //   258: anewarray java/lang/Object
    //   261: astore #20
    //   263: aload #20
    //   265: iconst_0
    //   266: ldc -1562181628
    //   268: i2c
    //   269: invokestatic aaaaao : (C)Ljava/lang/Object;
    //   272: checkcast java/lang/String
    //   275: invokestatic method_43471 : (Ljava/lang/String;)Lnet/minecraft/class_5250;
    //   278: aastore
    //   279: aload #20
    //   281: iconst_1
    //   282: aload #19
    //   284: <illegal opcode> makeConcatWithConstants : (Ljava/lang/String;)Ljava/lang/String;
    //   289: aastore
    //   290: aload #20
    //   292: invokestatic method_43469 : (Ljava/lang/String;[Ljava/lang/Object;)Lnet/minecraft/class_5250;
    //   295: checkcast net/minecraft/class_2561
    //   298: invokespecial <init> : (Lnet/minecraft/class_2561;)V
    //   301: checkcast net/minecraft/class_2596
    //   304: invokevirtual method_14364 : (Lnet/minecraft/class_2596;)V
    //   307: getstatic aaaaaa/aaaaaa/aaaaaa/aaaaaa/aaaaac/aaaaaN.我草你怎么反编译我模组aaaack : Laaaaaa/aaaaaa/aaaaaa/aaaaaa/aaaaac/aaaaaN;
    //   310: invokevirtual 你为什么要破解我的代码aaaaeR : ()Lnet/minecraft/server/MinecraftServer;
    //   313: dup
    //   314: ifnull -> 334
    //   317: aload_0
    //   318: getfield 我草你怎么反编译我模组aaaaak : Lnet/minecraft/class_3222;
    //   321: fload #13
    //   323: <illegal opcode> run : (Lnet/minecraft/class_3222;F)Ljava/lang/Runnable;
    //   328: invokevirtual execute : (Ljava/lang/Runnable;)V
    //   331: goto -> 335
    //   334: pop
    //   335: ldc2_w 50
    //   338: aload_0
    //   339: checkcast kotlin/coroutines/Continuation
    //   342: aload_0
    //   343: fload_3
    //   344: putfield 我草你怎么反编译我模组aaaaaG : F
    //   347: aload_0
    //   348: lload #4
    //   350: putfield 我草你怎么反编译我模组aaaaaH : J
    //   353: aload_0
    //   354: iload #6
    //   356: putfield 我草你怎么反编译我模组aaaaae : I
    //   359: aload_0
    //   360: iload #7
    //   362: putfield 我草你怎么反编译我模组aaaaau : I
    //   365: aload_0
    //   366: iconst_1
    //   367: putfield 我草你怎么反编译我模组aaaaaf : I
    //   370: invokestatic delay : (JLkotlin/coroutines/Continuation;)Ljava/lang/Object;
    //   373: dup
    //   374: aload_2
    //   375: if_acmpne -> 408
    //   378: aload_2
    //   379: areturn
    //   380: aload_0
    //   381: getfield 我草你怎么反编译我模组aaaaau : I
    //   384: istore #7
    //   386: aload_0
    //   387: getfield 我草你怎么反编译我模组aaaaae : I
    //   390: istore #6
    //   392: aload_0
    //   393: getfield 我草你怎么反编译我模组aaaaaH : J
    //   396: lstore #4
    //   398: aload_0
    //   399: getfield 我草你怎么反编译我模组aaaaaG : F
    //   402: fstore_3
    //   403: aload_1
    //   404: invokestatic throwOnFailure : (Ljava/lang/Object;)V
    //   407: aload_1
    //   408: pop
    //   409: goto -> 62
    //   412: getstatic aaaaaa/aaaaaa/aaaaaa/aaaaaa/aaaaac/aaaaaN.我草你怎么反编译我模组aaaack : Laaaaaa/aaaaaa/aaaaaa/aaaaaa/aaaaac/aaaaaN;
    //   415: invokevirtual 你为什么要破解我的代码aaaaeR : ()Lnet/minecraft/server/MinecraftServer;
    //   418: dup
    //   419: ifnull -> 438
    //   422: aload_0
    //   423: getfield 我草你怎么反编译我模组aaaaak : Lnet/minecraft/class_3222;
    //   426: fload_3
    //   427: <illegal opcode> run : (Lnet/minecraft/class_3222;F)Ljava/lang/Runnable;
    //   432: invokevirtual execute : (Ljava/lang/Runnable;)V
    //   435: goto -> 439
    //   438: pop
    //   439: getstatic kotlin/Unit.INSTANCE : Lkotlin/Unit;
    //   442: areturn
    //   443: new java/lang/IllegalStateException
    //   446: dup
    //   447: ldc -1101987835
    //   449: i2c
    //   450: invokestatic aaaaao : (C)Ljava/lang/Object;
    //   453: checkcast java/lang/String
    //   456: invokespecial <init> : (Ljava/lang/String;)V
    //   459: athrow
  }
  
  @NotNull
  public final Continuation<Unit> create(@Nullable Object paramObject, @NotNull Continuation<?> paramContinuation) {
    return (Continuation<Unit>)new aaaaav(this.我草你怎么反编译我模组aaaaak, this.我草你怎么反编译我模组aaaaaj, (Continuation)paramContinuation);
  }
  
  @Nullable
  public final Object 你为什么要破解我的代码aaaaab(@NotNull CoroutineScope paramCoroutineScope, @Nullable Continuation<? super Unit> paramContinuation) {
    return ((aaaaav)create(paramCoroutineScope, paramContinuation)).invokeSuspend(Unit.INSTANCE);
  }
  
  private static final void 你为什么要破解我的代码aaaaam(class_3222 paramclass_3222, float paramFloat) {
    paramclass_3222.method_14251(paramclass_3222.method_51469(), paramclass_3222.method_23317(), paramclass_3222.method_23318(), paramclass_3222.method_23321(), paramFloat, paramclass_3222.method_36455());
    paramclass_3222.field_6037 = true;
  }
  
  private static final void 你为什么要破解我的代码aaaaan(class_3222 paramclass_3222, float paramFloat) {
    paramclass_3222.method_14251(paramclass_3222.method_51469(), paramclass_3222.method_23317(), paramclass_3222.method_23318(), paramclass_3222.method_23321(), paramFloat, paramclass_3222.method_36455());
    paramclass_3222.field_6037 = true;
  }
  
  static {
    byte[] arrayOfByte1 = "DtÉ_ý§A\022w\020å1\fâ[«úûÊ¯³<6éÜy·þyë\nY¹x\007xÈ¬ÀÌCDqÃ«ÛlZÚ¼T\016¶1¢EÝ\f5SÜ=\004µ¼ªê®U=¶Üò0¤|¿yâöeþk\n´,?®¯xü\005¹PútÌwAsÿt°rf\035æ\027b\001­þ\032\rwÒ\023ýE8hÀë8¢cÁpÐÜ\024¹\t¯Oµ\006.^W6£÷(hoø<4uá¢¨\0211\tÀ®Ë".getBytes("ISO_8859_1");
    byte[] arrayOfByte2 = "4¦úàu¾\bW".getBytes("ISO_8859_1");
    int i = 0;
    int j = arrayOfByte1.length;
    while (true) {
      switch (arrayOfByte1[i] & 0xFF) {
        case 0:
        
        case 1:
        
        case 2:
        
        case 3:
        
        case 4:
        
        case 5:
        
        case 6:
        
        case 7:
        
        case 8:
        
        case 9:
        
        case 10:
        
        case 11:
        
        case 12:
        
        case 13:
        
        case 14:
        
        case 15:
        
        case 16:
        
        case 17:
        
        case 18:
        
        case 19:
        
        case 20:
        
        case 21:
        
        case 22:
        
        case 23:
        
        case 24:
        
        case 25:
        
        case 26:
        
        case 27:
        
        case 28:
        
        case 29:
        
        case 30:
        
        case 31:
        
        case 32:
        
        case 33:
        
        case 34:
        
        case 35:
        
        case 36:
        
        case 37:
        
        case 38:
        
        case 39:
        
        case 40:
        
        case 41:
        
        case 42:
        
        case 43:
        
        case 44:
        
        case 45:
        
        case 46:
        
        case 47:
        
        case 48:
        
        case 49:
        
        case 50:
        
        case 51:
        
        case 52:
        
        case 53:
        
        case 54:
        
        case 55:
        
        case 56:
        
        case 57:
        
        case 58:
        
        case 59:
        
        case 60:
        
        case 61:
        
        case 62:
        
        case 63:
        
        case 64:
        
        case 65:
        
        case 66:
        
        case 67:
        
        case 68:
        
        case 69:
        
        case 70:
        
        case 71:
        
        case 72:
        
        case 73:
        
        case 74:
        
        case 75:
        
        case 76:
        
        case 77:
        
        case 78:
        
        case 79:
        
        case 80:
        
        case 81:
        
        case 82:
        
        case 83:
        
        case 84:
        
        case 85:
        
        case 86:
        
        case 87:
        
        case 88:
        
        case 89:
        
        case 90:
        
        case 91:
        
        case 92:
        
        case 93:
        
        case 94:
        
        case 95:
        
        case 96:
        
        case 97:
        
        case 98:
        
        case 99:
        
        case 100:
        
        case 101:
        
        case 102:
        
        case 103:
        
        case 104:
        
        case 105:
        
        case 106:
        
        case 107:
        
        case 108:
        
        case 109:
        
        case 110:
        
        case 111:
        
        case 112:
        
        case 113:
        
        case 114:
        
        case 115:
        
        case 116:
        
        case 117:
        
        case 118:
        
        case 119:
        
        case 120:
        
        case 121:
        
        case 122:
        
        case 123:
        
        case 124:
        
        case 125:
        
        case 126:
        
        case 127:
        
        case 128:
        
        case 129:
        
        case 130:
        
        case 131:
        
        case 132:
        
        case 133:
        
        case 134:
        
        case 135:
        
        case 136:
        
        case 137:
        
        case 138:
        
        case 139:
        
        case 140:
        
        case 141:
        
        case 142:
        
        case 143:
        
        case 144:
        
        case 145:
        
        case 146:
        
        case 147:
        
        case 148:
        
        case 149:
        
        case 150:
        
        case 151:
        
        case 152:
        
        case 153:
        
        case 154:
        
        case 155:
        
        case 156:
        
        case 157:
        
        case 158:
        
        case 159:
        
        case 160:
        
        case 161:
        
        case 162:
        
        case 163:
        
        case 164:
        
        case 165:
        
        case 166:
        
        case 167:
        
        case 168:
        
        case 169:
        
        case 170:
        
        case 171:
        
        case 172:
        
        case 173:
        
        case 174:
        
        case 175:
        
        case 176:
        
        case 177:
        
        case 178:
        
        case 179:
        
        case 180:
        
        case 181:
        
        case 182:
        
        case 183:
        
        case 184:
        
        case 185:
        
        case 186:
        
        case 187:
        
        case 188:
        
        case 189:
        
        case 190:
        
        case 191:
        
        case 192:
        
        case 193:
        
        case 194:
        
        case 195:
        
        case 196:
        
        case 197:
        
        case 198:
        
        case 199:
        
        case 200:
        
        case 201:
        
        case 202:
        
        case 203:
        
        case 204:
        
        case 205:
        
        case 206:
        
        case 207:
        
        case 208:
        
        case 209:
        
        case 210:
        
        case 211:
        
        case 212:
        
        case 213:
        
        case 214:
        
        case 215:
        
        case 216:
        
        case 217:
        
        case 218:
        
        case 219:
        
        case 220:
        
        case 221:
        
        case 222:
        
        case 223:
        
        case 224:
        
        case 225:
        
        case 226:
        
        case 227:
        
        case 228:
        
        case 229:
        
        case 230:
        
        case 231:
        
        case 232:
        
        case 233:
        
        case 234:
        
        case 235:
        
        case 236:
        
        case 237:
        
        case 238:
        
        case 239:
        
        case 240:
        
        case 241:
        
        case 242:
        
        case 243:
        
        case 244:
        
        case 245:
        
        case 246:
        
        case 247:
        
        case 248:
        
        case 249:
        
        case 250:
        
        case 251:
        
        case 252:
        
        case 253:
        
        case 254:
        
        case 255:
        
        default:
          break;
      } 
      arrayOfByte1[i++] = (byte)840323401;
      if (i == j) {
        Cipher.getInstance("DES/CBC/PKCS5Padding").init(2, SecretKeyFactory.getInstance("DES").generateSecret(new DESKeySpec(arrayOfByte2)), new IvParameterSpec(new byte[8]));
        j = (arrayOfByte1 = Cipher.getInstance("DES/CBC/PKCS5Padding").doFinal(arrayOfByte1)).length;
        MessageDigest.getInstance("SHA-256").reset();
        MessageDigest.getInstance("SHA-256").update(arrayOfByte1, 0, i = j - 32);
        arrayOfByte2 = MessageDigest.getInstance("SHA-256").digest();
        int k = 0;
        int m = 0;
        byte b = 0;
        while (true) {
          m |= arrayOfByte1[i + k] ^ arrayOfByte2[k];
          if (++k == 32) {
            if (m == 0) {
              Object[] arrayOfObject = new Object[6];
              j = i;
              i = 0;
              do {
                byte[] arrayOfByte = new byte[k = arrayOfByte1[i++] & 0xFF | (arrayOfByte1[i++] & 0xFF) << 8];
                System.arraycopy(arrayOfByte1, i, arrayOfByte, 0, k);
                i += k;
                arrayOfObject[b++] = (new String(arrayOfByte, "UTF-8")).intern();
              } while (i != j);
            } 
            return;
          } 
        } 
        break;
      } 
    } 
  }
  
  private static Object aaaaao(char paramChar) {
    return ((Object[])aaaaaI)[paramChar];
  }
}
