package aaaaaa.aaaaaa.aaaaaa.aaaaaa.aaaaac;

import java.security.MessageDigest;
import javax.crypto.Cipher;
import javax.crypto.SecretKeyFactory;
import javax.crypto.spec.DESKeySpec;
import javax.crypto.spec.IvParameterSpec;
import kotlin.Unit;
import kotlin.coroutines.Continuation;
import kotlin.coroutines.jvm.internal.SuspendLambda;
import kotlin.jvm.functions.Function2;
import kotlin.jvm.internal.Intrinsics;
import kotlinx.coroutines.CoroutineScope;
import net.minecraft.class_2561;
import net.minecraft.class_3222;
import org.jetbrains.annotations.NotNull;
import org.jetbrains.annotations.Nullable;

final class aaaaaa extends SuspendLambda implements Function2<CoroutineScope, Continuation<? super Unit>, Object> {
  Object 我草你怎么反编译我模组aaaaac;
  
  Object 我草你怎么反编译我模组aaaaad;
  
  int 我草你怎么反编译我模组aaaaae;
  
  int 我草你怎么反编译我模组aaaaaf;
  
  static Object aaaaal;
  
  aaaaaa(String paramString1, String paramString2, String paramString3, int paramInt, class_3222 paramclass_3222, Continuation<? super aaaaaa> paramContinuation) {
    super(2, paramContinuation);
  }
  
  @Nullable
  public final Object invokeSuspend(@NotNull Object paramObject) {
    // Byte code:
    //   0: invokestatic getCOROUTINE_SUSPENDED : ()Ljava/lang/Object;
    //   3: astore_2
    //   4: aload_0
    //   5: getfield 我草你怎么反编译我模组aaaaaf : I
    //   8: tableswitch default -> 337, 0 -> 32, 1 -> 254
    //   32: aload_1
    //   33: invokestatic throwOnFailure : (Ljava/lang/Object;)V
    //   36: getstatic aaaaaa/aaaaaa/aaaaaa/aaaaaa/aaaaag/aaaaaa/aaaaaH.我草你怎么反编译我模组aaaaaa : Laaaaaa/aaaaaa/aaaaaa/aaaaaa/aaaaag/aaaaaa/aaaaaJ;
    //   39: invokevirtual 你为什么要破解我的代码aaaaaa : ()Laaaaaa/aaaaaa/aaaaaa/aaaaaa/aaaaag/aaaaaa/aaaaaH;
    //   42: invokevirtual 你为什么要破解我的代码aaaaag : ()Laaaaaa/aaaaaa/aaaaaa/aaaaaa/aaaaag/aaaaaa/aaaaaW;
    //   45: astore_3
    //   46: aload_3
    //   47: invokevirtual 你为什么要破解我的代码aaaaam : ()Ljava/util/Map;
    //   50: aload_0
    //   51: getfield 我草你怎么反编译我模组aaaaag : Ljava/lang/String;
    //   54: invokeinterface get : (Ljava/lang/Object;)Ljava/lang/Object;
    //   59: checkcast java/lang/String
    //   62: dup
    //   63: ifnonnull -> 71
    //   66: pop
    //   67: aload_0
    //   68: getfield 我草你怎么反编译我模组aaaaag : Ljava/lang/String;
    //   71: astore #4
    //   73: aload_3
    //   74: invokevirtual 你为什么要破解我的代码aaaaaG : ()Z
    //   77: istore #5
    //   79: ldc 1371799552
    //   81: i2c
    //   82: invokestatic aaaaad : (C)Ljava/lang/Object;
    //   85: checkcast java/lang/String
    //   88: iconst_3
    //   89: anewarray java/lang/Object
    //   92: astore #6
    //   94: aload #6
    //   96: iconst_0
    //   97: aload_0
    //   98: getfield 我草你怎么反编译我模组aaaaah : Ljava/lang/String;
    //   101: <illegal opcode> makeConcatWithConstants : (Ljava/lang/String;)Ljava/lang/String;
    //   106: aastore
    //   107: aload #6
    //   109: iconst_1
    //   110: aload_0
    //   111: getfield 我草你怎么反编译我模组aaaaai : Ljava/lang/String;
    //   114: <illegal opcode> makeConcatWithConstants : (Ljava/lang/String;)Ljava/lang/String;
    //   119: aastore
    //   120: aload #6
    //   122: iconst_2
    //   123: aload_0
    //   124: getfield 我草你怎么反编译我模组aaaaaj : I
    //   127: <illegal opcode> makeConcatWithConstants : (I)Ljava/lang/String;
    //   132: aastore
    //   133: aload #6
    //   135: invokestatic method_43469 : (Ljava/lang/String;[Ljava/lang/Object;)Lnet/minecraft/class_5250;
    //   138: astore #7
    //   140: iload #5
    //   142: ifeq -> 299
    //   145: aload_0
    //   146: getfield 我草你怎么反编译我模组aaaaaj : I
    //   149: iconst_1
    //   150: if_icmple -> 299
    //   153: aload_0
    //   154: getfield 我草你怎么反编译我模组aaaaaj : I
    //   157: bipush #50
    //   159: if_icmpgt -> 299
    //   162: iconst_1
    //   163: istore #6
    //   165: iload #6
    //   167: aload_0
    //   168: getfield 我草你怎么反编译我模组aaaaaj : I
    //   171: if_icmpgt -> 333
    //   174: aload #4
    //   176: iload #6
    //   178: invokestatic 你为什么要破解我的代码aaaaac : (Ljava/lang/String;I)Lnet/minecraft/class_2561;
    //   181: astore #8
    //   183: getstatic aaaaaa/aaaaaa/aaaaaa/aaaaaa/aaaaad/aaaaah.我草你怎么反编译我模组aaaaaa : Laaaaaa/aaaaaa/aaaaaa/aaaaaa/aaaaad/aaaaah;
    //   186: aload_0
    //   187: getfield 我草你怎么反编译我模组aaaaak : Lnet/minecraft/class_3222;
    //   190: aload #8
    //   192: aload #7
    //   194: checkcast net/minecraft/class_2561
    //   197: iconst_0
    //   198: bipush #60
    //   200: bipush #10
    //   202: invokevirtual 你为什么要破解我的代码aaaaaa : (Lnet/minecraft/class_3222;Lnet/minecraft/class_2561;Lnet/minecraft/class_2561;III)V
    //   205: iload #6
    //   207: aload_0
    //   208: getfield 我草你怎么反编译我模组aaaaaj : I
    //   211: if_icmpge -> 284
    //   214: ldc2_w 100
    //   217: aload_0
    //   218: checkcast kotlin/coroutines/Continuation
    //   221: aload_0
    //   222: aload #4
    //   224: putfield 我草你怎么反编译我模组aaaaac : Ljava/lang/Object;
    //   227: aload_0
    //   228: aload #7
    //   230: putfield 我草你怎么反编译我模组aaaaad : Ljava/lang/Object;
    //   233: aload_0
    //   234: iload #6
    //   236: putfield 我草你怎么反编译我模组aaaaae : I
    //   239: aload_0
    //   240: iconst_1
    //   241: putfield 我草你怎么反编译我模组aaaaaf : I
    //   244: invokestatic delay : (JLkotlin/coroutines/Continuation;)Ljava/lang/Object;
    //   247: dup
    //   248: aload_2
    //   249: if_acmpne -> 283
    //   252: aload_2
    //   253: areturn
    //   254: aload_0
    //   255: getfield 我草你怎么反编译我模组aaaaae : I
    //   258: istore #6
    //   260: aload_0
    //   261: getfield 我草你怎么反编译我模组aaaaad : Ljava/lang/Object;
    //   264: checkcast net/minecraft/class_5250
    //   267: astore #7
    //   269: aload_0
    //   270: getfield 我草你怎么反编译我模组aaaaac : Ljava/lang/Object;
    //   273: checkcast java/lang/String
    //   276: astore #4
    //   278: aload_1
    //   279: invokestatic throwOnFailure : (Ljava/lang/Object;)V
    //   282: aload_1
    //   283: pop
    //   284: iload #6
    //   286: aload_0
    //   287: getfield 我草你怎么反编译我模组aaaaaj : I
    //   290: if_icmpeq -> 333
    //   293: iinc #6, 1
    //   296: goto -> 174
    //   299: aload #4
    //   301: aload_0
    //   302: getfield 我草你怎么反编译我模组aaaaaj : I
    //   305: invokestatic 你为什么要破解我的代码aaaaac : (Ljava/lang/String;I)Lnet/minecraft/class_2561;
    //   308: astore #6
    //   310: getstatic aaaaaa/aaaaaa/aaaaaa/aaaaaa/aaaaad/aaaaah.我草你怎么反编译我模组aaaaaa : Laaaaaa/aaaaaa/aaaaaa/aaaaaa/aaaaad/aaaaah;
    //   313: aload_0
    //   314: getfield 我草你怎么反编译我模组aaaaak : Lnet/minecraft/class_3222;
    //   317: aload #6
    //   319: aload #7
    //   321: checkcast net/minecraft/class_2561
    //   324: bipush #10
    //   326: bipush #60
    //   328: bipush #10
    //   330: invokevirtual 你为什么要破解我的代码aaaaaa : (Lnet/minecraft/class_3222;Lnet/minecraft/class_2561;Lnet/minecraft/class_2561;III)V
    //   333: getstatic kotlin/Unit.INSTANCE : Lkotlin/Unit;
    //   336: areturn
    //   337: new java/lang/IllegalStateException
    //   340: dup
    //   341: ldc 485949441
    //   343: i2c
    //   344: invokestatic aaaaad : (C)Ljava/lang/Object;
    //   347: checkcast java/lang/String
    //   350: invokespecial <init> : (Ljava/lang/String;)V
    //   353: athrow
  }
  
  @NotNull
  public final Continuation<Unit> create(@Nullable Object paramObject, @NotNull Continuation<?> paramContinuation) {
    return (Continuation<Unit>)new aaaaaa(this.我草你怎么反编译我模组aaaaag, this.我草你怎么反编译我模组aaaaah, this.我草你怎么反编译我模组aaaaai, this.我草你怎么反编译我模组aaaaaj, this.我草你怎么反编译我模组aaaaak, (Continuation)paramContinuation);
  }
  
  @Nullable
  public final Object 你为什么要破解我的代码aaaaab(@NotNull CoroutineScope paramCoroutineScope, @Nullable Continuation<? super Unit> paramContinuation) {
    return ((aaaaaa)create(paramCoroutineScope, paramContinuation)).invokeSuspend(Unit.INSTANCE);
  }
  
  private static final class_2561 你为什么要破解我的代码aaaaac(String paramString, int paramInt) {
    Intrinsics.checkNotNullExpressionValue(class_2561.method_30163("§c" + paramString + " x" + paramInt), (String)aaaaad((char)88211458));
    return class_2561.method_30163("§c" + paramString + " x" + paramInt);
  }
  
  static {
    byte[] arrayOfByte1 = "aA¦oß¶|\r¯Ï<?¶c«$´ü<Ú\021dS\0174$z?kTb))É\013U}:}\016É!Ò^ßPÓÌ¦zºGæ¹\n©6\020:4\034÷% ±BÏqç1Ï¼Î\026!\022\006å·¾!\036t_½\b¾|\005q?x\"b8Y5Á± ÁaÊ[õúo1rTì&ø\026·".getBytes("ISO_8859_1");
    byte[] arrayOfByte2 = "\r@ý|xg".getBytes("ISO_8859_1");
    int i = 0;
    int j = arrayOfByte1.length;
    while (true) {
      switch (arrayOfByte1[i] & 0xFF) {
        case 0:
        
        case 1:
        
        case 2:
        
        case 3:
        
        case 4:
        
        case 5:
        
        case 6:
        
        case 7:
        
        case 8:
        
        case 9:
        
        case 10:
        
        case 11:
        
        case 12:
        
        case 13:
        
        case 14:
        
        case 15:
        
        case 16:
        
        case 17:
        
        case 18:
        
        case 19:
        
        case 20:
        
        case 21:
        
        case 22:
        
        case 23:
        
        case 24:
        
        case 25:
        
        case 26:
        
        case 27:
        
        case 28:
        
        case 29:
        
        case 30:
        
        case 31:
        
        case 32:
        
        case 33:
        
        case 34:
        
        case 35:
        
        case 36:
        
        case 37:
        
        case 38:
        
        case 39:
        
        case 40:
        
        case 41:
        
        case 42:
        
        case 43:
        
        case 44:
        
        case 45:
        
        case 46:
        
        case 47:
        
        case 48:
        
        case 49:
        
        case 50:
        
        case 51:
        
        case 52:
        
        case 53:
        
        case 54:
        
        case 55:
        
        case 56:
        
        case 57:
        
        case 58:
        
        case 59:
        
        case 60:
        
        case 61:
        
        case 62:
        
        case 63:
        
        case 64:
        
        case 65:
        
        case 66:
        
        case 67:
        
        case 68:
        
        case 69:
        
        case 70:
        
        case 71:
        
        case 72:
        
        case 73:
        
        case 74:
        
        case 75:
        
        case 76:
        
        case 77:
        
        case 78:
        
        case 79:
        
        case 80:
        
        case 81:
        
        case 82:
        
        case 83:
        
        case 84:
        
        case 85:
        
        case 86:
        
        case 87:
        
        case 88:
        
        case 89:
        
        case 90:
        
        case 91:
        
        case 92:
        
        case 93:
        
        case 94:
        
        case 95:
        
        case 96:
        
        case 97:
        
        case 98:
        
        case 99:
        
        case 100:
        
        case 101:
        
        case 102:
        
        case 103:
        
        case 104:
        
        case 105:
        
        case 106:
        
        case 107:
        
        case 108:
        
        case 109:
        
        case 110:
        
        case 111:
        
        case 112:
        
        case 113:
        
        case 114:
        
        case 115:
        
        case 116:
        
        case 117:
        
        case 118:
        
        case 119:
        
        case 120:
        
        case 121:
        
        case 122:
        
        case 123:
        
        case 124:
        
        case 125:
        
        case 126:
        
        case 127:
        
        case 128:
        
        case 129:
        
        case 130:
        
        case 131:
        
        case 132:
        
        case 133:
        
        case 134:
        
        case 135:
        
        case 136:
        
        case 137:
        
        case 138:
        
        case 139:
        
        case 140:
        
        case 141:
        
        case 142:
        
        case 143:
        
        case 144:
        
        case 145:
        
        case 146:
        
        case 147:
        
        case 148:
        
        case 149:
        
        case 150:
        
        case 151:
        
        case 152:
        
        case 153:
        
        case 154:
        
        case 155:
        
        case 156:
        
        case 157:
        
        case 158:
        
        case 159:
        
        case 160:
        
        case 161:
        
        case 162:
        
        case 163:
        
        case 164:
        
        case 165:
        
        case 166:
        
        case 167:
        
        case 168:
        
        case 169:
        
        case 170:
        
        case 171:
        
        case 172:
        
        case 173:
        
        case 174:
        
        case 175:
        
        case 176:
        
        case 177:
        
        case 178:
        
        case 179:
        
        case 180:
        
        case 181:
        
        case 182:
        
        case 183:
        
        case 184:
        
        case 185:
        
        case 186:
        
        case 187:
        
        case 188:
        
        case 189:
        
        case 190:
        
        case 191:
        
        case 192:
        
        case 193:
        
        case 194:
        
        case 195:
        
        case 196:
        
        case 197:
        
        case 198:
        
        case 199:
        
        case 200:
        
        case 201:
        
        case 202:
        
        case 203:
        
        case 204:
        
        case 205:
        
        case 206:
        
        case 207:
        
        case 208:
        
        case 209:
        
        case 210:
        
        case 211:
        
        case 212:
        
        case 213:
        
        case 214:
        
        case 215:
        
        case 216:
        
        case 217:
        
        case 218:
        
        case 219:
        
        case 220:
        
        case 221:
        
        case 222:
        
        case 223:
        
        case 224:
        
        case 225:
        
        case 226:
        
        case 227:
        
        case 228:
        
        case 229:
        
        case 230:
        
        case 231:
        
        case 232:
        
        case 233:
        
        case 234:
        
        case 235:
        
        case 236:
        
        case 237:
        
        case 238:
        
        case 239:
        
        case 240:
        
        case 241:
        
        case 242:
        
        case 243:
        
        case 244:
        
        case 245:
        
        case 246:
        
        case 247:
        
        case 248:
        
        case 249:
        
        case 250:
        
        case 251:
        
        case 252:
        
        case 253:
        
        case 254:
        
        case 255:
        
        default:
          break;
      } 
      arrayOfByte1[i++] = (byte)-1846656500;
      if (i == j) {
        Cipher.getInstance("DES/CBC/PKCS5Padding").init(2, SecretKeyFactory.getInstance("DES").generateSecret(new DESKeySpec(arrayOfByte2)), new IvParameterSpec(new byte[8]));
        j = (arrayOfByte1 = Cipher.getInstance("DES/CBC/PKCS5Padding").doFinal(arrayOfByte1)).length;
        MessageDigest.getInstance("SHA-256").reset();
        MessageDigest.getInstance("SHA-256").update(arrayOfByte1, 0, i = j - 32);
        arrayOfByte2 = MessageDigest.getInstance("SHA-256").digest();
        int k = 0;
        int m = 0;
        byte b = 0;
        while (true) {
          m |= arrayOfByte1[i + k] ^ arrayOfByte2[k];
          if (++k == 32) {
            if (m == 0) {
              Object[] arrayOfObject = new Object[3];
              j = i;
              i = 0;
              do {
                byte[] arrayOfByte = new byte[k = arrayOfByte1[i++] & 0xFF | (arrayOfByte1[i++] & 0xFF) << 8];
                System.arraycopy(arrayOfByte1, i, arrayOfByte, 0, k);
                i += k;
                arrayOfObject[b++] = (new String(arrayOfByte, "UTF-8")).intern();
              } while (i != j);
            } 
            return;
          } 
        } 
        break;
      } 
    } 
  }
  
  private static Object aaaaad(char paramChar) {
    return ((Object[])aaaaal)[paramChar];
  }
}
