package aaaaaa.aaaaaa.aaaaaa.aaaaaa.aaaaac;

import aaaaaa.aaaaaa.aaaaaa.aaaaaa.aaaaag.aaaaaa.aaaaaV;
import cn.pixellive.mc.game.event.live.LiveGiftEvent;
import java.security.MessageDigest;
import java.util.List;
import javax.crypto.Cipher;
import javax.crypto.SecretKeyFactory;
import javax.crypto.spec.DESKeySpec;
import javax.crypto.spec.IvParameterSpec;
import kotlin.Unit;
import kotlin.coroutines.Continuation;
import kotlin.coroutines.jvm.internal.SuspendLambda;
import kotlin.jvm.functions.Function2;
import kotlin.jvm.internal.SourceDebugExtension;
import kotlinx.coroutines.CoroutineScope;
import org.jetbrains.annotations.NotNull;
import org.jetbrains.annotations.Nullable;

@SourceDebugExtension({"SMAP\nFillBoxStage.kt\nKotlin\n*S Kotlin\n*F\n+ 1 FillBoxStage.kt\ncn/pixellive/mc/game/stage/FillBoxStage$startOpeningBlindBox$1$run$1\n+ 2 _Collections.kt\nkotlin/collections/CollectionsKt___CollectionsKt\n*L\n1#1,2939:1\n1855#2,2:2940\n*S KotlinDebug\n*F\n+ 1 FillBoxStage.kt\ncn/pixellive/mc/game/stage/FillBoxStage$startOpeningBlindBox$1$run$1\n*L\n1423#1:2940,2\n*E\n"})
final class aaaabg extends SuspendLambda implements Function2<CoroutineScope, Continuation<? super Unit>, Object> {
  Object 我草你怎么反编译我模组aaaaac;
  
  Object 我草你怎么反编译我模组aaaaad;
  
  Object 我草你怎么反编译我模组aaaaar;
  
  Object 我草你怎么反编译我模组aaaabK;
  
  Object 我草你怎么反编译我模组aaaabL;
  
  Object 我草你怎么反编译我模组aaaabM;
  
  int 我草你怎么反编译我模组aaaaae;
  
  int 我草你怎么反编译我模组aaaaau;
  
  int 我草你怎么反编译我模组aaaaaf;
  
  static Object aaaabR;
  
  aaaabg(aaaaaV paramaaaaaV, LiveGiftEvent paramLiveGiftEvent, String paramString, int paramInt, List<aaaaaV> paramList, Continuation<? super aaaabg> paramContinuation) {
    super(2, paramContinuation);
  }
  
  @Nullable
  public final Object invokeSuspend(@NotNull Object paramObject) {
    // Byte code:
    //   0: invokestatic getCOROUTINE_SUSPENDED : ()Ljava/lang/Object;
    //   3: astore_2
    //   4: aload_0
    //   5: getfield 我草你怎么反编译我模组aaaaaf : I
    //   8: tableswitch default -> 2138, 0 -> 32, 1 -> 356
    //   32: aload_1
    //   33: invokestatic throwOnFailure : (Ljava/lang/Object;)V
    //   36: getstatic aaaaaa/aaaaaa/aaaaaa/aaaaaa/aaaaac/aaaaaN.我草你怎么反编译我模组aaaack : Laaaaaa/aaaaaa/aaaaaa/aaaaaa/aaaaac/aaaaaN;
    //   39: invokevirtual 你为什么要破解我的代码aaaaeR : ()Lnet/minecraft/server/MinecraftServer;
    //   42: dup
    //   43: ifnull -> 740
    //   46: invokevirtual method_3760 : ()Lnet/minecraft/class_3324;
    //   49: dup
    //   50: ifnull -> 740
    //   53: invokevirtual method_14571 : ()Ljava/util/List;
    //   56: dup
    //   57: ifnull -> 740
    //   60: checkcast java/lang/Iterable
    //   63: astore_3
    //   64: aload_0
    //   65: getfield 我草你怎么反编译我模组aaaabN : Laaaaaa/aaaaaa/aaaaaa/aaaaaa/aaaaag/aaaaaa/aaaaaV;
    //   68: astore #4
    //   70: aload_0
    //   71: getfield 我草你怎么反编译我模组aaaaah : Ljava/lang/String;
    //   74: astore #5
    //   76: aload_0
    //   77: getfield 我草你怎么反编译我模组aaaabQ : Ljava/util/List;
    //   80: astore #6
    //   82: aload_0
    //   83: getfield 我草你怎么反编译我模组aaaabO : Lcn/pixellive/mc/game/event/live/LiveGiftEvent;
    //   86: astore #7
    //   88: iconst_0
    //   89: istore #8
    //   91: aload_3
    //   92: invokeinterface iterator : ()Ljava/util/Iterator;
    //   97: astore #9
    //   99: aload #9
    //   101: invokeinterface hasNext : ()Z
    //   106: ifeq -> 736
    //   109: aload #9
    //   111: invokeinterface next : ()Ljava/lang/Object;
    //   116: astore #10
    //   118: aload #10
    //   120: checkcast net/minecraft/class_3222
    //   123: astore #11
    //   125: iconst_0
    //   126: istore #12
    //   128: getstatic aaaaaa/aaaaaa/aaaaaa/aaaaaa/aaaaag/aaaaaa/aaaaap.我草你怎么反编译我模组aaaaaa : Laaaaaa/aaaaaa/aaaaaa/aaaaaa/aaaaag/aaaaaa/aaaaaS;
    //   131: invokevirtual 你为什么要破解我的代码aaaaaa : ()Laaaaaa/aaaaaa/aaaaaa/aaaaaa/aaaaag/aaaaaa/aaaaap;
    //   134: ldc -461897728
    //   136: i2c
    //   137: invokestatic aaaaaa : (C)Ljava/lang/Object;
    //   140: checkcast java/lang/String
    //   143: invokevirtual 你为什么要破解我的代码aaaaac : (Ljava/lang/String;)V
    //   146: bipush #10
    //   148: istore #13
    //   150: iconst_0
    //   151: istore #14
    //   153: iload #14
    //   155: iload #13
    //   157: if_icmpge -> 443
    //   160: iconst_0
    //   161: istore #15
    //   163: aload #6
    //   165: checkcast java/util/Collection
    //   168: getstatic kotlin/random/Random.Default : Lkotlin/random/Random$Default;
    //   171: checkcast kotlin/random/Random
    //   174: invokestatic random : (Ljava/util/Collection;Lkotlin/random/Random;)Ljava/lang/Object;
    //   177: checkcast aaaaaa/aaaaaa/aaaaaa/aaaaaa/aaaaag/aaaaaa/aaaaaV
    //   180: astore #16
    //   182: getstatic aaaaaa/aaaaaa/aaaaaa/aaaaaa/aaaaad/aaaaah.我草你怎么反编译我模组aaaaaa : Laaaaaa/aaaaaa/aaaaaa/aaaaaa/aaaaad/aaaaah;
    //   185: aload #11
    //   187: invokestatic checkNotNull : (Ljava/lang/Object;)V
    //   190: aload #11
    //   192: ldc 1282146305
    //   194: i2c
    //   195: invokestatic aaaaaa : (C)Ljava/lang/Object;
    //   198: checkcast java/lang/String
    //   201: iconst_1
    //   202: anewarray java/lang/Object
    //   205: astore #17
    //   207: aload #17
    //   209: iconst_0
    //   210: aload #16
    //   212: invokevirtual 你为什么要破解我的代码aaaaaa : ()Ljava/lang/String;
    //   215: <illegal opcode> makeConcatWithConstants : (Ljava/lang/String;)Ljava/lang/String;
    //   220: aastore
    //   221: aload #17
    //   223: invokestatic method_43469 : (Ljava/lang/String;[Ljava/lang/Object;)Lnet/minecraft/class_5250;
    //   226: checkcast net/minecraft/class_2561
    //   229: ldc -721485822
    //   231: i2c
    //   232: invokestatic aaaaaa : (C)Ljava/lang/Object;
    //   235: checkcast java/lang/String
    //   238: iconst_2
    //   239: anewarray java/lang/Object
    //   242: astore #17
    //   244: aload #17
    //   246: iconst_0
    //   247: aload #5
    //   249: <illegal opcode> makeConcatWithConstants : (Ljava/lang/String;)Ljava/lang/String;
    //   254: aastore
    //   255: aload #17
    //   257: iconst_1
    //   258: aload #7
    //   260: invokevirtual getGiftName : ()Ljava/lang/String;
    //   263: aload #7
    //   265: invokevirtual getGiftCount : ()I
    //   268: <illegal opcode> makeConcatWithConstants : (Ljava/lang/String;I)Ljava/lang/String;
    //   273: aastore
    //   274: aload #17
    //   276: invokestatic method_43469 : (Ljava/lang/String;[Ljava/lang/Object;)Lnet/minecraft/class_5250;
    //   279: checkcast net/minecraft/class_2561
    //   282: iconst_0
    //   283: bipush #20
    //   285: iconst_0
    //   286: invokevirtual 你为什么要破解我的代码aaaaaa : (Lnet/minecraft/class_3222;Lnet/minecraft/class_2561;Lnet/minecraft/class_2561;III)V
    //   289: ldc2_w 250
    //   292: aload_0
    //   293: aload_0
    //   294: aload #4
    //   296: putfield 我草你怎么反编译我模组aaaaac : Ljava/lang/Object;
    //   299: aload_0
    //   300: aload #5
    //   302: putfield 我草你怎么反编译我模组aaaaad : Ljava/lang/Object;
    //   305: aload_0
    //   306: aload #6
    //   308: putfield 我草你怎么反编译我模组aaaaar : Ljava/lang/Object;
    //   311: aload_0
    //   312: aload #7
    //   314: putfield 我草你怎么反编译我模组aaaabK : Ljava/lang/Object;
    //   317: aload_0
    //   318: aload #9
    //   320: putfield 我草你怎么反编译我模组aaaabL : Ljava/lang/Object;
    //   323: aload_0
    //   324: aload #11
    //   326: putfield 我草你怎么反编译我模组aaaabM : Ljava/lang/Object;
    //   329: aload_0
    //   330: iload #13
    //   332: putfield 我草你怎么反编译我模组aaaaae : I
    //   335: aload_0
    //   336: iload #14
    //   338: putfield 我草你怎么反编译我模组aaaaau : I
    //   341: aload_0
    //   342: iconst_1
    //   343: putfield 我草你怎么反编译我模组aaaaaf : I
    //   346: invokestatic delay : (JLkotlin/coroutines/Continuation;)Ljava/lang/Object;
    //   349: dup
    //   350: aload_2
    //   351: if_acmpne -> 436
    //   354: aload_2
    //   355: areturn
    //   356: iconst_0
    //   357: istore #8
    //   359: iconst_0
    //   360: istore #12
    //   362: iconst_0
    //   363: istore #15
    //   365: aload_0
    //   366: getfield 我草你怎么反编译我模组aaaaau : I
    //   369: istore #14
    //   371: aload_0
    //   372: getfield 我草你怎么反编译我模组aaaaae : I
    //   375: istore #13
    //   377: aload_0
    //   378: getfield 我草你怎么反编译我模组aaaabM : Ljava/lang/Object;
    //   381: checkcast net/minecraft/class_3222
    //   384: astore #11
    //   386: aload_0
    //   387: getfield 我草你怎么反编译我模组aaaabL : Ljava/lang/Object;
    //   390: checkcast java/util/Iterator
    //   393: astore #9
    //   395: aload_0
    //   396: getfield 我草你怎么反编译我模组aaaabK : Ljava/lang/Object;
    //   399: checkcast cn/pixellive/mc/game/event/live/LiveGiftEvent
    //   402: astore #7
    //   404: aload_0
    //   405: getfield 我草你怎么反编译我模组aaaaar : Ljava/lang/Object;
    //   408: checkcast java/util/List
    //   411: astore #6
    //   413: aload_0
    //   414: getfield 我草你怎么反编译我模组aaaaad : Ljava/lang/Object;
    //   417: checkcast java/lang/String
    //   420: astore #5
    //   422: aload_0
    //   423: getfield 我草你怎么反编译我模组aaaaac : Ljava/lang/Object;
    //   426: checkcast aaaaaa/aaaaaa/aaaaaa/aaaaaa/aaaaag/aaaaaa/aaaaaV
    //   429: astore #4
    //   431: aload_1
    //   432: invokestatic throwOnFailure : (Ljava/lang/Object;)V
    //   435: aload_1
    //   436: pop
    //   437: iinc #14, 1
    //   440: goto -> 153
    //   443: ldc -1378811903
    //   445: i2c
    //   446: invokestatic aaaaaa : (C)Ljava/lang/Object;
    //   449: checkcast java/lang/String
    //   452: iconst_1
    //   453: anewarray java/lang/Object
    //   456: astore #14
    //   458: aload #14
    //   460: iconst_0
    //   461: aload #4
    //   463: invokevirtual 你为什么要破解我的代码aaaaaa : ()Ljava/lang/String;
    //   466: <illegal opcode> makeConcatWithConstants : (Ljava/lang/String;)Ljava/lang/String;
    //   471: aastore
    //   472: aload #14
    //   474: invokestatic method_43469 : (Ljava/lang/String;[Ljava/lang/Object;)Lnet/minecraft/class_5250;
    //   477: astore #13
    //   479: getstatic aaaaaa/aaaaaa/aaaaaa/aaaaaa/aaaaad/aaaaah.我草你怎么反编译我模组aaaaaa : Laaaaaa/aaaaaa/aaaaaa/aaaaaa/aaaaad/aaaaah;
    //   482: aload #11
    //   484: invokestatic checkNotNull : (Ljava/lang/Object;)V
    //   487: aload #11
    //   489: aload #13
    //   491: checkcast net/minecraft/class_2561
    //   494: ldc_w -1694826493
    //   497: i2c
    //   498: invokestatic aaaaaa : (C)Ljava/lang/Object;
    //   501: checkcast java/lang/String
    //   504: iconst_2
    //   505: anewarray java/lang/Object
    //   508: astore #14
    //   510: aload #14
    //   512: iconst_0
    //   513: aload #5
    //   515: <illegal opcode> makeConcatWithConstants : (Ljava/lang/String;)Ljava/lang/String;
    //   520: aastore
    //   521: aload #14
    //   523: iconst_1
    //   524: aload #4
    //   526: invokevirtual 你为什么要破解我的代码aaaaaa : ()Ljava/lang/String;
    //   529: <illegal opcode> makeConcatWithConstants : (Ljava/lang/String;)Ljava/lang/String;
    //   534: aastore
    //   535: aload #14
    //   537: invokestatic method_43469 : (Ljava/lang/String;[Ljava/lang/Object;)Lnet/minecraft/class_5250;
    //   540: checkcast net/minecraft/class_2561
    //   543: iconst_2
    //   544: bipush #40
    //   546: iconst_5
    //   547: invokevirtual 你为什么要破解我的代码aaaaaa : (Lnet/minecraft/class_3222;Lnet/minecraft/class_2561;Lnet/minecraft/class_2561;III)V
    //   550: getstatic aaaaaa/aaaaaa/aaaaaa/aaaaaa/aaaaag/aaaaab.Companion : Laaaaaa/aaaaaa/aaaaaa/aaaaaa/aaaaag/aaaaaa;
    //   553: invokevirtual 你为什么要破解我的代码aaaaaa : ()Laaaaaa/aaaaaa/aaaaaa/aaaaaa/aaaaag/aaaaab;
    //   556: invokevirtual 你为什么要破解我的代码aaaaam : ()Z
    //   559: ifeq -> 732
    //   562: aload #4
    //   564: invokevirtual 你为什么要破解我的代码aaaaaa : ()Ljava/lang/String;
    //   567: ldc_w 1735983108
    //   570: i2c
    //   571: invokestatic aaaaaa : (C)Ljava/lang/Object;
    //   574: checkcast java/lang/String
    //   577: invokestatic areEqual : (Ljava/lang/Object;Ljava/lang/Object;)Z
    //   580: ifeq -> 674
    //   583: aload #4
    //   585: invokevirtual 你为什么要破解我的代码aaaaab : ()Laaaaaa/aaaaaa/aaaaaa/aaaaaa/aaaaag/aaaaaa/aaaabA;
    //   588: invokevirtual 你为什么要破解我的代码aaaaab : ()I
    //   591: ifle -> 610
    //   594: aload #4
    //   596: invokevirtual 你为什么要破解我的代码aaaaab : ()Laaaaaa/aaaaaa/aaaaaa/aaaaaa/aaaaag/aaaaaa/aaaabA;
    //   599: invokevirtual 你为什么要破解我的代码aaaaab : ()I
    //   602: <illegal opcode> makeConcatWithConstants : (I)Ljava/lang/String;
    //   607: goto -> 621
    //   610: aload #4
    //   612: invokevirtual 你为什么要破解我的代码aaaaab : ()Laaaaaa/aaaaaa/aaaaaa/aaaaaa/aaaaag/aaaaaa/aaaabA;
    //   615: invokevirtual 你为什么要破解我的代码aaaaab : ()I
    //   618: invokestatic valueOf : (I)Ljava/lang/String;
    //   621: astore #18
    //   623: ldc_w 232587269
    //   626: i2c
    //   627: invokestatic aaaaaa : (C)Ljava/lang/Object;
    //   630: checkcast java/lang/String
    //   633: iconst_2
    //   634: anewarray java/lang/Object
    //   637: astore #15
    //   639: aload #15
    //   641: iconst_0
    //   642: aload #5
    //   644: <illegal opcode> makeConcatWithConstants : (Ljava/lang/String;)Ljava/lang/String;
    //   649: aastore
    //   650: aload #15
    //   652: iconst_1
    //   653: aload #4
    //   655: invokevirtual 你为什么要破解我的代码aaaaaa : ()Ljava/lang/String;
    //   658: aload #18
    //   660: <illegal opcode> makeConcatWithConstants : (Ljava/lang/String;Ljava/lang/String;)Ljava/lang/String;
    //   665: aastore
    //   666: aload #15
    //   668: invokestatic method_43469 : (Ljava/lang/String;[Ljava/lang/Object;)Lnet/minecraft/class_5250;
    //   671: goto -> 720
    //   674: ldc_w -1791426555
    //   677: i2c
    //   678: invokestatic aaaaaa : (C)Ljava/lang/Object;
    //   681: checkcast java/lang/String
    //   684: iconst_2
    //   685: anewarray java/lang/Object
    //   688: astore #18
    //   690: aload #18
    //   692: iconst_0
    //   693: aload #5
    //   695: <illegal opcode> makeConcatWithConstants : (Ljava/lang/String;)Ljava/lang/String;
    //   700: aastore
    //   701: aload #18
    //   703: iconst_1
    //   704: aload #4
    //   706: invokevirtual 你为什么要破解我的代码aaaaaa : ()Ljava/lang/String;
    //   709: <illegal opcode> makeConcatWithConstants : (Ljava/lang/String;)Ljava/lang/String;
    //   714: aastore
    //   715: aload #18
    //   717: invokestatic method_43469 : (Ljava/lang/String;[Ljava/lang/Object;)Lnet/minecraft/class_5250;
    //   720: astore #14
    //   722: aload #11
    //   724: aload #14
    //   726: checkcast net/minecraft/class_2561
    //   729: invokevirtual method_43496 : (Lnet/minecraft/class_2561;)V
    //   732: nop
    //   733: goto -> 99
    //   736: nop
    //   737: goto -> 742
    //   740: pop
    //   741: nop
    //   742: getstatic aaaaaa/aaaaaa/aaaaaa/aaaaaa/aaaaac/aaaaaN.我草你怎么反编译我模组aaaack : Laaaaaa/aaaaaa/aaaaaa/aaaaaa/aaaaac/aaaaaN;
    //   745: astore #19
    //   747: aload #19
    //   749: aload #19
    //   751: invokevirtual 你为什么要破解我的代码aaaaeT : ()I
    //   754: aload_0
    //   755: getfield 我草你怎么反编译我模组aaaabN : Laaaaaa/aaaaaa/aaaaaa/aaaaaa/aaaaag/aaaaaa/aaaaaV;
    //   758: invokevirtual 你为什么要破解我的代码aaaaab : ()Laaaaaa/aaaaaa/aaaaaa/aaaaaa/aaaaag/aaaaaa/aaaabA;
    //   761: invokevirtual 你为什么要破解我的代码aaaaab : ()I
    //   764: iadd
    //   765: invokevirtual 你为什么要破解我的代码aaaabU : (I)V
    //   768: aload_0
    //   769: getfield 我草你怎么反编译我模组aaaabO : Lcn/pixellive/mc/game/event/live/LiveGiftEvent;
    //   772: iconst_1
    //   773: invokevirtual setGiftCount : (I)V
    //   776: aload_0
    //   777: getfield 我草你怎么反编译我模组aaaabN : Laaaaaa/aaaaaa/aaaaaa/aaaaaa/aaaaag/aaaaaa/aaaaaV;
    //   780: invokevirtual 你为什么要破解我的代码aaaaaa : ()Ljava/lang/String;
    //   783: astore #19
    //   785: aload #19
    //   787: invokevirtual hashCode : ()I
    //   790: lookupswitch default -> 2123, -487099157 -> 1425, -63279477 -> 1278, 657119 -> 1299, 918913 -> 1215, 930529 -> 1236, 943424 -> 1173, 24851761 -> 1131, 31924721 -> 1320, 35997036 -> 1089, 655752639 -> 1110, 659869171 -> 1005, 687872247 -> 1341, 688653065 -> 984, 700312307 -> 1194, 848080797 -> 1257, 907554274 -> 1362, 936430092 -> 1383, 936447161 -> 1047, 982028416 -> 1026, 1174435196 -> 1404, 1174452265 -> 1068, 2047640262 -> 1152, 2054713222 -> 1446
    //   984: aload #19
    //   986: ldc_w -575340538
    //   989: i2c
    //   990: invokestatic aaaaaa : (C)Ljava/lang/Object;
    //   993: checkcast java/lang/String
    //   996: invokevirtual equals : (Ljava/lang/Object;)Z
    //   999: ifne -> 1605
    //   1002: goto -> 2123
    //   1005: aload #19
    //   1007: ldc_w 1778712583
    //   1010: i2c
    //   1011: invokestatic aaaaaa : (C)Ljava/lang/Object;
    //   1014: checkcast java/lang/String
    //   1017: invokevirtual equals : (Ljava/lang/Object;)Z
    //   1020: ifne -> 1529
    //   1023: goto -> 2123
    //   1026: aload #19
    //   1028: ldc_w -245104632
    //   1031: i2c
    //   1032: invokestatic aaaaaa : (C)Ljava/lang/Object;
    //   1035: checkcast java/lang/String
    //   1038: invokevirtual equals : (Ljava/lang/Object;)Z
    //   1041: ifne -> 1699
    //   1044: goto -> 2123
    //   1047: aload #19
    //   1049: ldc_w 1251278857
    //   1052: i2c
    //   1053: invokestatic aaaaaa : (C)Ljava/lang/Object;
    //   1056: checkcast java/lang/String
    //   1059: invokevirtual equals : (Ljava/lang/Object;)Z
    //   1062: ifne -> 1768
    //   1065: goto -> 2123
    //   1068: aload #19
    //   1070: ldc_w -1320091638
    //   1073: i2c
    //   1074: invokestatic aaaaaa : (C)Ljava/lang/Object;
    //   1077: checkcast java/lang/String
    //   1080: invokevirtual equals : (Ljava/lang/Object;)Z
    //   1083: ifne -> 1827
    //   1086: goto -> 2123
    //   1089: aload #19
    //   1091: ldc_w -813105141
    //   1094: i2c
    //   1095: invokestatic aaaaaa : (C)Ljava/lang/Object;
    //   1098: checkcast java/lang/String
    //   1101: invokevirtual equals : (Ljava/lang/Object;)Z
    //   1104: ifne -> 2091
    //   1107: goto -> 2123
    //   1110: aload #19
    //   1112: ldc_w 848494604
    //   1115: i2c
    //   1116: invokestatic aaaaaa : (C)Ljava/lang/Object;
    //   1119: checkcast java/lang/String
    //   1122: invokevirtual equals : (Ljava/lang/Object;)Z
    //   1125: ifne -> 1553
    //   1128: goto -> 2123
    //   1131: aload #19
    //   1133: ldc_w 971440141
    //   1136: i2c
    //   1137: invokestatic aaaaaa : (C)Ljava/lang/Object;
    //   1140: checkcast java/lang/String
    //   1143: invokevirtual equals : (Ljava/lang/Object;)Z
    //   1146: ifne -> 1921
    //   1149: goto -> 2123
    //   1152: aload #19
    //   1154: ldc_w 1715339278
    //   1157: i2c
    //   1158: invokestatic aaaaaa : (C)Ljava/lang/Object;
    //   1161: checkcast java/lang/String
    //   1164: invokevirtual equals : (Ljava/lang/Object;)Z
    //   1167: ifne -> 1991
    //   1170: goto -> 2123
    //   1173: aload #19
    //   1175: ldc_w 1856110607
    //   1178: i2c
    //   1179: invokestatic aaaaaa : (C)Ljava/lang/Object;
    //   1182: checkcast java/lang/String
    //   1185: invokevirtual equals : (Ljava/lang/Object;)Z
    //   1188: ifne -> 1629
    //   1191: goto -> 2123
    //   1194: aload #19
    //   1196: ldc_w 1341915152
    //   1199: i2c
    //   1200: invokestatic aaaaaa : (C)Ljava/lang/Object;
    //   1203: checkcast java/lang/String
    //   1206: invokevirtual equals : (Ljava/lang/Object;)Z
    //   1209: ifne -> 1716
    //   1212: goto -> 2123
    //   1215: aload #19
    //   1217: ldc_w -596901871
    //   1220: i2c
    //   1221: invokestatic aaaaaa : (C)Ljava/lang/Object;
    //   1224: checkcast java/lang/String
    //   1227: invokevirtual equals : (Ljava/lang/Object;)Z
    //   1230: ifne -> 1502
    //   1233: goto -> 2123
    //   1236: aload #19
    //   1238: ldc_w 1142423570
    //   1241: i2c
    //   1242: invokestatic aaaaaa : (C)Ljava/lang/Object;
    //   1245: checkcast java/lang/String
    //   1248: invokevirtual equals : (Ljava/lang/Object;)Z
    //   1251: ifne -> 1664
    //   1254: goto -> 2123
    //   1257: aload #19
    //   1259: ldc_w 187564036
    //   1262: i2c
    //   1263: invokestatic aaaaaa : (C)Ljava/lang/Object;
    //   1266: checkcast java/lang/String
    //   1269: invokevirtual equals : (Ljava/lang/Object;)Z
    //   1272: ifne -> 1467
    //   1275: goto -> 2123
    //   1278: aload #19
    //   1280: ldc_w -117637101
    //   1283: i2c
    //   1284: invokestatic aaaaaa : (C)Ljava/lang/Object;
    //   1287: checkcast java/lang/String
    //   1290: invokevirtual equals : (Ljava/lang/Object;)Z
    //   1293: ifne -> 1851
    //   1296: goto -> 2123
    //   1299: aload #19
    //   1301: ldc_w -788398060
    //   1304: i2c
    //   1305: invokestatic aaaaaa : (C)Ljava/lang/Object;
    //   1308: checkcast java/lang/String
    //   1311: invokevirtual equals : (Ljava/lang/Object;)Z
    //   1314: ifne -> 1570
    //   1317: goto -> 2123
    //   1320: aload #19
    //   1322: ldc_w -1166671851
    //   1325: i2c
    //   1326: invokestatic aaaaaa : (C)Ljava/lang/Object;
    //   1329: checkcast java/lang/String
    //   1332: invokevirtual equals : (Ljava/lang/Object;)Z
    //   1335: ifne -> 1956
    //   1338: goto -> 2123
    //   1341: aload #19
    //   1343: ldc_w 1768488982
    //   1346: i2c
    //   1347: invokestatic aaaaaa : (C)Ljava/lang/Object;
    //   1350: checkcast java/lang/String
    //   1353: invokevirtual equals : (Ljava/lang/Object;)Z
    //   1356: ifne -> 2074
    //   1359: goto -> 2123
    //   1362: aload #19
    //   1364: ldc_w -1954086889
    //   1367: i2c
    //   1368: invokestatic aaaaaa : (C)Ljava/lang/Object;
    //   1371: checkcast java/lang/String
    //   1374: invokevirtual equals : (Ljava/lang/Object;)Z
    //   1377: ifne -> 2039
    //   1380: goto -> 2123
    //   1383: aload #19
    //   1385: ldc_w -1610219496
    //   1388: i2c
    //   1389: invokestatic aaaaaa : (C)Ljava/lang/Object;
    //   1392: checkcast java/lang/String
    //   1395: invokevirtual equals : (Ljava/lang/Object;)Z
    //   1398: ifne -> 1733
    //   1401: goto -> 2123
    //   1404: aload #19
    //   1406: ldc_w -895877095
    //   1409: i2c
    //   1410: invokestatic aaaaaa : (C)Ljava/lang/Object;
    //   1413: checkcast java/lang/String
    //   1416: invokevirtual equals : (Ljava/lang/Object;)Z
    //   1419: ifne -> 1803
    //   1422: goto -> 2123
    //   1425: aload #19
    //   1427: ldc_w 1307639834
    //   1430: i2c
    //   1431: invokestatic aaaaaa : (C)Ljava/lang/Object;
    //   1434: checkcast java/lang/String
    //   1437: invokevirtual equals : (Ljava/lang/Object;)Z
    //   1440: ifne -> 1886
    //   1443: goto -> 2123
    //   1446: aload #19
    //   1448: ldc_w -714145765
    //   1451: i2c
    //   1452: invokestatic aaaaaa : (C)Ljava/lang/Object;
    //   1455: checkcast java/lang/String
    //   1458: invokevirtual equals : (Ljava/lang/Object;)Z
    //   1461: ifne -> 2015
    //   1464: goto -> 2123
    //   1467: getstatic aaaaaa/aaaaaa/aaaaaa/aaaaaa/aaaaac/aaaaaN.我草你怎么反编译我模组aaaack : Laaaaaa/aaaaaa/aaaaaa/aaaaaa/aaaaac/aaaaaN;
    //   1470: aload_0
    //   1471: getfield 我草你怎么反编译我模组aaaabO : Lcn/pixellive/mc/game/event/live/LiveGiftEvent;
    //   1474: aload_0
    //   1475: getfield 我草你怎么反编译我模组aaaaah : Ljava/lang/String;
    //   1478: aload_0
    //   1479: getfield 我草你怎么反编译我模组aaaabN : Laaaaaa/aaaaaa/aaaaaa/aaaaaa/aaaaag/aaaaaa/aaaaaV;
    //   1482: invokevirtual 你为什么要破解我的代码aaaaab : ()Laaaaaa/aaaaaa/aaaaaa/aaaaaa/aaaaag/aaaaaa/aaaabA;
    //   1485: invokevirtual 你为什么要破解我的代码aaaaab : ()I
    //   1488: aload_0
    //   1489: getfield 我草你怎么反编译我模组aaaabO : Lcn/pixellive/mc/game/event/live/LiveGiftEvent;
    //   1492: invokevirtual getGiftCount : ()I
    //   1495: imul
    //   1496: invokestatic 你为什么要破解我的代码aaaahn : (Laaaaaa/aaaaaa/aaaaaa/aaaaaa/aaaaac/aaaaaN;Lcn/pixellive/mc/game/event/live/LiveGiftEvent;Ljava/lang/String;I)V
    //   1499: goto -> 2123
    //   1502: getstatic aaaaaa/aaaaaa/aaaaaa/aaaaaa/aaaaac/aaaaaN.我草你怎么反编译我模组aaaack : Laaaaaa/aaaaaa/aaaaaa/aaaaaa/aaaaac/aaaaaN;
    //   1505: aload_0
    //   1506: getfield 我草你怎么反编译我模组aaaabO : Lcn/pixellive/mc/game/event/live/LiveGiftEvent;
    //   1509: aload_0
    //   1510: getfield 我草你怎么反编译我模组aaaaah : Ljava/lang/String;
    //   1513: aload_0
    //   1514: getfield 我草你怎么反编译我模组aaaabN : Laaaaaa/aaaaaa/aaaaaa/aaaaaa/aaaaag/aaaaaa/aaaaaV;
    //   1517: invokevirtual 你为什么要破解我的代码aaaaab : ()Laaaaaa/aaaaaa/aaaaaa/aaaaaa/aaaaag/aaaaaa/aaaabA;
    //   1520: invokevirtual 你为什么要破解我的代码aaaaaa : ()I
    //   1523: invokestatic 你为什么要破解我的代码aaaaho : (Laaaaaa/aaaaaa/aaaaaa/aaaaaa/aaaaac/aaaaaN;Lcn/pixellive/mc/game/event/live/LiveGiftEvent;Ljava/lang/String;I)V
    //   1526: goto -> 2123
    //   1529: getstatic aaaaaa/aaaaaa/aaaaaa/aaaaaa/aaaaac/aaaaaN.我草你怎么反编译我模组aaaack : Laaaaaa/aaaaaa/aaaaaa/aaaaaa/aaaaac/aaaaaN;
    //   1532: aload_0
    //   1533: getfield 我草你怎么反编译我模组aaaabO : Lcn/pixellive/mc/game/event/live/LiveGiftEvent;
    //   1536: aload_0
    //   1537: getfield 我草你怎么反编译我模组aaaaah : Ljava/lang/String;
    //   1540: aload_0
    //   1541: getfield 我草你怎么反编译我模组aaaabO : Lcn/pixellive/mc/game/event/live/LiveGiftEvent;
    //   1544: invokevirtual getGiftCount : ()I
    //   1547: invokestatic 你为什么要破解我的代码aaaahp : (Laaaaaa/aaaaaa/aaaaaa/aaaaaa/aaaaac/aaaaaN;Lcn/pixellive/mc/game/event/live/LiveGiftEvent;Ljava/lang/String;I)V
    //   1550: goto -> 2123
    //   1553: getstatic aaaaaa/aaaaaa/aaaaaa/aaaaaa/aaaaac/aaaaaN.我草你怎么反编译我模组aaaack : Laaaaaa/aaaaaa/aaaaaa/aaaaaa/aaaaac/aaaaaN;
    //   1556: aload_0
    //   1557: getfield 我草你怎么反编译我模组aaaabO : Lcn/pixellive/mc/game/event/live/LiveGiftEvent;
    //   1560: aload_0
    //   1561: getfield 我草你怎么反编译我模组aaaaah : Ljava/lang/String;
    //   1564: invokestatic 你为什么要破解我的代码aaaahq : (Laaaaaa/aaaaaa/aaaaaa/aaaaaa/aaaaac/aaaaaN;Lcn/pixellive/mc/game/event/live/LiveGiftEvent;Ljava/lang/String;)V
    //   1567: goto -> 2123
    //   1570: getstatic aaaaaa/aaaaaa/aaaaaa/aaaaaa/aaaaac/aaaaaN.我草你怎么反编译我模组aaaack : Laaaaaa/aaaaaa/aaaaaa/aaaaaa/aaaaac/aaaaaN;
    //   1573: aload_0
    //   1574: getfield 我草你怎么反编译我模组aaaabO : Lcn/pixellive/mc/game/event/live/LiveGiftEvent;
    //   1577: aload_0
    //   1578: getfield 我草你怎么反编译我模组aaaaah : Ljava/lang/String;
    //   1581: aload_0
    //   1582: getfield 我草你怎么反编译我模组aaaabN : Laaaaaa/aaaaaa/aaaaaa/aaaaaa/aaaaag/aaaaaa/aaaaaV;
    //   1585: invokevirtual 你为什么要破解我的代码aaaaab : ()Laaaaaa/aaaaaa/aaaaaa/aaaaaa/aaaaag/aaaaaa/aaaabA;
    //   1588: invokevirtual 你为什么要破解我的代码aaaaaa : ()I
    //   1591: aload_0
    //   1592: getfield 我草你怎么反编译我模组aaaabO : Lcn/pixellive/mc/game/event/live/LiveGiftEvent;
    //   1595: invokevirtual getGiftCount : ()I
    //   1598: imul
    //   1599: invokestatic 你为什么要破解我的代码aaaahr : (Laaaaaa/aaaaaa/aaaaaa/aaaaaa/aaaaac/aaaaaN;Lcn/pixellive/mc/game/event/live/LiveGiftEvent;Ljava/lang/String;I)V
    //   1602: goto -> 2123
    //   1605: getstatic aaaaaa/aaaaaa/aaaaaa/aaaaaa/aaaaac/aaaaaN.我草你怎么反编译我模组aaaack : Laaaaaa/aaaaaa/aaaaaa/aaaaaa/aaaaac/aaaaaN;
    //   1608: aload_0
    //   1609: getfield 我草你怎么反编译我模组aaaabO : Lcn/pixellive/mc/game/event/live/LiveGiftEvent;
    //   1612: aload_0
    //   1613: getfield 我草你怎么反编译我模组aaaaah : Ljava/lang/String;
    //   1616: aload_0
    //   1617: getfield 我草你怎么反编译我模组aaaabO : Lcn/pixellive/mc/game/event/live/LiveGiftEvent;
    //   1620: invokevirtual getGiftCount : ()I
    //   1623: invokestatic 你为什么要破解我的代码aaaahs : (Laaaaaa/aaaaaa/aaaaaa/aaaaaa/aaaaac/aaaaaN;Lcn/pixellive/mc/game/event/live/LiveGiftEvent;Ljava/lang/String;I)V
    //   1626: goto -> 2123
    //   1629: getstatic aaaaaa/aaaaaa/aaaaaa/aaaaaa/aaaaac/aaaaaN.我草你怎么反编译我模组aaaack : Laaaaaa/aaaaaa/aaaaaa/aaaaaa/aaaaac/aaaaaN;
    //   1632: aload_0
    //   1633: getfield 我草你怎么反编译我模组aaaabO : Lcn/pixellive/mc/game/event/live/LiveGiftEvent;
    //   1636: aload_0
    //   1637: getfield 我草你怎么反编译我模组aaaaah : Ljava/lang/String;
    //   1640: aload_0
    //   1641: getfield 我草你怎么反编译我模组aaaabN : Laaaaaa/aaaaaa/aaaaaa/aaaaaa/aaaaag/aaaaaa/aaaaaV;
    //   1644: invokevirtual 你为什么要破解我的代码aaaaab : ()Laaaaaa/aaaaaa/aaaaaa/aaaaaa/aaaaag/aaaaaa/aaaabA;
    //   1647: invokevirtual 你为什么要破解我的代码aaaaaa : ()I
    //   1650: aload_0
    //   1651: getfield 我草你怎么反编译我模组aaaabO : Lcn/pixellive/mc/game/event/live/LiveGiftEvent;
    //   1654: invokevirtual getGiftCount : ()I
    //   1657: imul
    //   1658: invokestatic 你为什么要破解我的代码aaaaht : (Laaaaaa/aaaaaa/aaaaaa/aaaaaa/aaaaac/aaaaaN;Lcn/pixellive/mc/game/event/live/LiveGiftEvent;Ljava/lang/String;I)V
    //   1661: goto -> 2123
    //   1664: getstatic aaaaaa/aaaaaa/aaaaaa/aaaaaa/aaaaac/aaaaaN.我草你怎么反编译我模组aaaack : Laaaaaa/aaaaaa/aaaaaa/aaaaaa/aaaaac/aaaaaN;
    //   1667: aload_0
    //   1668: getfield 我草你怎么反编译我模组aaaabO : Lcn/pixellive/mc/game/event/live/LiveGiftEvent;
    //   1671: aload_0
    //   1672: getfield 我草你怎么反编译我模组aaaaah : Ljava/lang/String;
    //   1675: aload_0
    //   1676: getfield 我草你怎么反编译我模组aaaabN : Laaaaaa/aaaaaa/aaaaaa/aaaaaa/aaaaag/aaaaaa/aaaaaV;
    //   1679: invokevirtual 你为什么要破解我的代码aaaaab : ()Laaaaaa/aaaaaa/aaaaaa/aaaaaa/aaaaag/aaaaaa/aaaabA;
    //   1682: invokevirtual 你为什么要破解我的代码aaaaaa : ()I
    //   1685: aload_0
    //   1686: getfield 我草你怎么反编译我模组aaaabO : Lcn/pixellive/mc/game/event/live/LiveGiftEvent;
    //   1689: invokevirtual getGiftCount : ()I
    //   1692: imul
    //   1693: invokestatic 你为什么要破解我的代码aaaahu : (Laaaaaa/aaaaaa/aaaaaa/aaaaaa/aaaaac/aaaaaN;Lcn/pixellive/mc/game/event/live/LiveGiftEvent;Ljava/lang/String;I)V
    //   1696: goto -> 2123
    //   1699: getstatic aaaaaa/aaaaaa/aaaaaa/aaaaaa/aaaaac/aaaaaN.我草你怎么反编译我模组aaaack : Laaaaaa/aaaaaa/aaaaaa/aaaaaa/aaaaac/aaaaaN;
    //   1702: aload_0
    //   1703: getfield 我草你怎么反编译我模组aaaabO : Lcn/pixellive/mc/game/event/live/LiveGiftEvent;
    //   1706: aload_0
    //   1707: getfield 我草你怎么反编译我模组aaaaah : Ljava/lang/String;
    //   1710: invokestatic 你为什么要破解我的代码aaaahv : (Laaaaaa/aaaaaa/aaaaaa/aaaaaa/aaaaac/aaaaaN;Lcn/pixellive/mc/game/event/live/LiveGiftEvent;Ljava/lang/String;)V
    //   1713: goto -> 2123
    //   1716: getstatic aaaaaa/aaaaaa/aaaaaa/aaaaaa/aaaaac/aaaaaN.我草你怎么反编译我模组aaaack : Laaaaaa/aaaaaa/aaaaaa/aaaaaa/aaaaac/aaaaaN;
    //   1719: aload_0
    //   1720: getfield 我草你怎么反编译我模组aaaabO : Lcn/pixellive/mc/game/event/live/LiveGiftEvent;
    //   1723: aload_0
    //   1724: getfield 我草你怎么反编译我模组aaaaah : Ljava/lang/String;
    //   1727: invokestatic 你为什么要破解我的代码aaaahw : (Laaaaaa/aaaaaa/aaaaaa/aaaaaa/aaaaac/aaaaaN;Lcn/pixellive/mc/game/event/live/LiveGiftEvent;Ljava/lang/String;)V
    //   1730: goto -> 2123
    //   1733: getstatic aaaaaa/aaaaaa/aaaaaa/aaaaaa/aaaaac/aaaaaN.我草你怎么反编译我模组aaaack : Laaaaaa/aaaaaa/aaaaaa/aaaaaa/aaaaac/aaaaaN;
    //   1736: aload_0
    //   1737: getfield 我草你怎么反编译我模组aaaabO : Lcn/pixellive/mc/game/event/live/LiveGiftEvent;
    //   1740: aload_0
    //   1741: getfield 我草你怎么反编译我模组aaaabN : Laaaaaa/aaaaaa/aaaaaa/aaaaaa/aaaaag/aaaaaa/aaaaaV;
    //   1744: invokevirtual 你为什么要破解我的代码aaaaab : ()Laaaaaa/aaaaaa/aaaaaa/aaaaaa/aaaaag/aaaaaa/aaaabA;
    //   1747: invokevirtual 你为什么要破解我的代码aaaaaa : ()I
    //   1750: aload_0
    //   1751: getfield 我草你怎么反编译我模组aaaabO : Lcn/pixellive/mc/game/event/live/LiveGiftEvent;
    //   1754: invokevirtual getGiftCount : ()I
    //   1757: imul
    //   1758: aload_0
    //   1759: getfield 我草你怎么反编译我模组aaaaah : Ljava/lang/String;
    //   1762: invokestatic 你为什么要破解我的代码aaaahx : (Laaaaaa/aaaaaa/aaaaaa/aaaaaa/aaaaac/aaaaaN;Lcn/pixellive/mc/game/event/live/LiveGiftEvent;ILjava/lang/String;)V
    //   1765: goto -> 2123
    //   1768: getstatic aaaaaa/aaaaaa/aaaaaa/aaaaaa/aaaaac/aaaaaN.我草你怎么反编译我模组aaaack : Laaaaaa/aaaaaa/aaaaaa/aaaaaa/aaaaac/aaaaaN;
    //   1771: aload_0
    //   1772: getfield 我草你怎么反编译我模组aaaabO : Lcn/pixellive/mc/game/event/live/LiveGiftEvent;
    //   1775: aload_0
    //   1776: getfield 我草你怎么反编译我模组aaaabN : Laaaaaa/aaaaaa/aaaaaa/aaaaaa/aaaaag/aaaaaa/aaaaaV;
    //   1779: invokevirtual 你为什么要破解我的代码aaaaab : ()Laaaaaa/aaaaaa/aaaaaa/aaaaaa/aaaaag/aaaaaa/aaaabA;
    //   1782: invokevirtual 你为什么要破解我的代码aaaaaa : ()I
    //   1785: aload_0
    //   1786: getfield 我草你怎么反编译我模组aaaabO : Lcn/pixellive/mc/game/event/live/LiveGiftEvent;
    //   1789: invokevirtual getGiftCount : ()I
    //   1792: imul
    //   1793: aload_0
    //   1794: getfield 我草你怎么反编译我模组aaaaah : Ljava/lang/String;
    //   1797: invokestatic 你为什么要破解我的代码aaaahy : (Laaaaaa/aaaaaa/aaaaaa/aaaaaa/aaaaac/aaaaaN;Lcn/pixellive/mc/game/event/live/LiveGiftEvent;ILjava/lang/String;)V
    //   1800: goto -> 2123
    //   1803: getstatic aaaaaa/aaaaaa/aaaaaa/aaaaaa/aaaaac/aaaaaN.我草你怎么反编译我模组aaaack : Laaaaaa/aaaaaa/aaaaaa/aaaaaa/aaaaac/aaaaaN;
    //   1806: aload_0
    //   1807: getfield 我草你怎么反编译我模组aaaabO : Lcn/pixellive/mc/game/event/live/LiveGiftEvent;
    //   1810: aload_0
    //   1811: getfield 我草你怎么反编译我模组aaaabO : Lcn/pixellive/mc/game/event/live/LiveGiftEvent;
    //   1814: invokevirtual getGiftCount : ()I
    //   1817: aload_0
    //   1818: getfield 我草你怎么反编译我模组aaaaah : Ljava/lang/String;
    //   1821: invokestatic 你为什么要破解我的代码aaaahz : (Laaaaaa/aaaaaa/aaaaaa/aaaaaa/aaaaac/aaaaaN;Lcn/pixellive/mc/game/event/live/LiveGiftEvent;ILjava/lang/String;)V
    //   1824: goto -> 2123
    //   1827: getstatic aaaaaa/aaaaaa/aaaaaa/aaaaaa/aaaaac/aaaaaN.我草你怎么反编译我模组aaaack : Laaaaaa/aaaaaa/aaaaaa/aaaaaa/aaaaac/aaaaaN;
    //   1830: aload_0
    //   1831: getfield 我草你怎么反编译我模组aaaabO : Lcn/pixellive/mc/game/event/live/LiveGiftEvent;
    //   1834: aload_0
    //   1835: getfield 我草你怎么反编译我模组aaaabO : Lcn/pixellive/mc/game/event/live/LiveGiftEvent;
    //   1838: invokevirtual getGiftCount : ()I
    //   1841: aload_0
    //   1842: getfield 我草你怎么反编译我模组aaaaah : Ljava/lang/String;
    //   1845: invokestatic 你为什么要破解我的代码aaaahA : (Laaaaaa/aaaaaa/aaaaaa/aaaaaa/aaaaac/aaaaaN;Lcn/pixellive/mc/game/event/live/LiveGiftEvent;ILjava/lang/String;)V
    //   1848: goto -> 2123
    //   1851: getstatic aaaaaa/aaaaaa/aaaaaa/aaaaaa/aaaaac/aaaaaN.我草你怎么反编译我模组aaaack : Laaaaaa/aaaaaa/aaaaaa/aaaaaa/aaaaac/aaaaaN;
    //   1854: aload_0
    //   1855: getfield 我草你怎么反编译我模组aaaabO : Lcn/pixellive/mc/game/event/live/LiveGiftEvent;
    //   1858: aload_0
    //   1859: getfield 我草你怎么反编译我模组aaaabN : Laaaaaa/aaaaaa/aaaaaa/aaaaaa/aaaaag/aaaaaa/aaaaaV;
    //   1862: invokevirtual 你为什么要破解我的代码aaaaab : ()Laaaaaa/aaaaaa/aaaaaa/aaaaaa/aaaaag/aaaaaa/aaaabA;
    //   1865: invokevirtual 你为什么要破解我的代码aaaaaa : ()I
    //   1868: aload_0
    //   1869: getfield 我草你怎么反编译我模组aaaabO : Lcn/pixellive/mc/game/event/live/LiveGiftEvent;
    //   1872: invokevirtual getGiftCount : ()I
    //   1875: imul
    //   1876: aload_0
    //   1877: getfield 我草你怎么反编译我模组aaaaah : Ljava/lang/String;
    //   1880: invokevirtual 你为什么要破解我的代码aaaagx : (Lcn/pixellive/mc/game/event/live/LiveGiftEvent;ILjava/lang/String;)V
    //   1883: goto -> 2123
    //   1886: getstatic aaaaaa/aaaaaa/aaaaaa/aaaaaa/aaaaac/aaaaaN.我草你怎么反编译我模组aaaack : Laaaaaa/aaaaaa/aaaaaa/aaaaaa/aaaaac/aaaaaN;
    //   1889: aload_0
    //   1890: getfield 我草你怎么反编译我模组aaaabO : Lcn/pixellive/mc/game/event/live/LiveGiftEvent;
    //   1893: aload_0
    //   1894: getfield 我草你怎么反编译我模组aaaabN : Laaaaaa/aaaaaa/aaaaaa/aaaaaa/aaaaag/aaaaaa/aaaaaV;
    //   1897: invokevirtual 你为什么要破解我的代码aaaaab : ()Laaaaaa/aaaaaa/aaaaaa/aaaaaa/aaaaag/aaaaaa/aaaabA;
    //   1900: invokevirtual 你为什么要破解我的代码aaaaaa : ()I
    //   1903: aload_0
    //   1904: getfield 我草你怎么反编译我模组aaaabO : Lcn/pixellive/mc/game/event/live/LiveGiftEvent;
    //   1907: invokevirtual getGiftCount : ()I
    //   1910: imul
    //   1911: aload_0
    //   1912: getfield 我草你怎么反编译我模组aaaaah : Ljava/lang/String;
    //   1915: invokevirtual 你为什么要破解我的代码aaaagy : (Lcn/pixellive/mc/game/event/live/LiveGiftEvent;ILjava/lang/String;)V
    //   1918: goto -> 2123
    //   1921: getstatic aaaaaa/aaaaaa/aaaaaa/aaaaaa/aaaaac/aaaaaN.我草你怎么反编译我模组aaaack : Laaaaaa/aaaaaa/aaaaaa/aaaaaa/aaaaac/aaaaaN;
    //   1924: aload_0
    //   1925: getfield 我草你怎么反编译我模组aaaabO : Lcn/pixellive/mc/game/event/live/LiveGiftEvent;
    //   1928: aload_0
    //   1929: getfield 我草你怎么反编译我模组aaaabN : Laaaaaa/aaaaaa/aaaaaa/aaaaaa/aaaaag/aaaaaa/aaaaaV;
    //   1932: invokevirtual 你为什么要破解我的代码aaaaab : ()Laaaaaa/aaaaaa/aaaaaa/aaaaaa/aaaaag/aaaaaa/aaaabA;
    //   1935: invokevirtual 你为什么要破解我的代码aaaaaa : ()I
    //   1938: aload_0
    //   1939: getfield 我草你怎么反编译我模组aaaabO : Lcn/pixellive/mc/game/event/live/LiveGiftEvent;
    //   1942: invokevirtual getGiftCount : ()I
    //   1945: imul
    //   1946: aload_0
    //   1947: getfield 我草你怎么反编译我模组aaaaah : Ljava/lang/String;
    //   1950: invokestatic 你为什么要破解我的代码aaaahB : (Laaaaaa/aaaaaa/aaaaaa/aaaaaa/aaaaac/aaaaaN;Lcn/pixellive/mc/game/event/live/LiveGiftEvent;ILjava/lang/String;)V
    //   1953: goto -> 2123
    //   1956: getstatic aaaaaa/aaaaaa/aaaaaa/aaaaaa/aaaaac/aaaaaN.我草你怎么反编译我模组aaaack : Laaaaaa/aaaaaa/aaaaaa/aaaaaa/aaaaac/aaaaaN;
    //   1959: aload_0
    //   1960: getfield 我草你怎么反编译我模组aaaabO : Lcn/pixellive/mc/game/event/live/LiveGiftEvent;
    //   1963: aload_0
    //   1964: getfield 我草你怎么反编译我模组aaaabN : Laaaaaa/aaaaaa/aaaaaa/aaaaaa/aaaaag/aaaaaa/aaaaaV;
    //   1967: invokevirtual 你为什么要破解我的代码aaaaab : ()Laaaaaa/aaaaaa/aaaaaa/aaaaaa/aaaaag/aaaaaa/aaaabA;
    //   1970: invokevirtual 你为什么要破解我的代码aaaaaa : ()I
    //   1973: aload_0
    //   1974: getfield 我草你怎么反编译我模组aaaabO : Lcn/pixellive/mc/game/event/live/LiveGiftEvent;
    //   1977: invokevirtual getGiftCount : ()I
    //   1980: imul
    //   1981: aload_0
    //   1982: getfield 我草你怎么反编译我模组aaaaah : Ljava/lang/String;
    //   1985: invokestatic 你为什么要破解我的代码aaaahC : (Laaaaaa/aaaaaa/aaaaaa/aaaaaa/aaaaac/aaaaaN;Lcn/pixellive/mc/game/event/live/LiveGiftEvent;ILjava/lang/String;)V
    //   1988: goto -> 2123
    //   1991: getstatic aaaaaa/aaaaaa/aaaaaa/aaaaaa/aaaaac/aaaaaN.我草你怎么反编译我模组aaaack : Laaaaaa/aaaaaa/aaaaaa/aaaaaa/aaaaac/aaaaaN;
    //   1994: aload_0
    //   1995: getfield 我草你怎么反编译我模组aaaabO : Lcn/pixellive/mc/game/event/live/LiveGiftEvent;
    //   1998: aload_0
    //   1999: getfield 我草你怎么反编译我模组aaaabO : Lcn/pixellive/mc/game/event/live/LiveGiftEvent;
    //   2002: invokevirtual getGiftCount : ()I
    //   2005: aload_0
    //   2006: getfield 我草你怎么反编译我模组aaaaah : Ljava/lang/String;
    //   2009: invokestatic 你为什么要破解我的代码aaaahD : (Laaaaaa/aaaaaa/aaaaaa/aaaaaa/aaaaac/aaaaaN;Lcn/pixellive/mc/game/event/live/LiveGiftEvent;ILjava/lang/String;)V
    //   2012: goto -> 2123
    //   2015: getstatic aaaaaa/aaaaaa/aaaaaa/aaaaaa/aaaaac/aaaaaN.我草你怎么反编译我模组aaaack : Laaaaaa/aaaaaa/aaaaaa/aaaaaa/aaaaac/aaaaaN;
    //   2018: aload_0
    //   2019: getfield 我草你怎么反编译我模组aaaabO : Lcn/pixellive/mc/game/event/live/LiveGiftEvent;
    //   2022: aload_0
    //   2023: getfield 我草你怎么反编译我模组aaaabO : Lcn/pixellive/mc/game/event/live/LiveGiftEvent;
    //   2026: invokevirtual getGiftCount : ()I
    //   2029: aload_0
    //   2030: getfield 我草你怎么反编译我模组aaaaah : Ljava/lang/String;
    //   2033: invokestatic 你为什么要破解我的代码aaaahE : (Laaaaaa/aaaaaa/aaaaaa/aaaaaa/aaaaac/aaaaaN;Lcn/pixellive/mc/game/event/live/LiveGiftEvent;ILjava/lang/String;)V
    //   2036: goto -> 2123
    //   2039: getstatic aaaaaa/aaaaaa/aaaaaa/aaaaaa/aaaaac/aaaaaN.我草你怎么反编译我模组aaaack : Laaaaaa/aaaaaa/aaaaaa/aaaaaa/aaaaac/aaaaaN;
    //   2042: aload_0
    //   2043: getfield 我草你怎么反编译我模组aaaabO : Lcn/pixellive/mc/game/event/live/LiveGiftEvent;
    //   2046: aload_0
    //   2047: getfield 我草你怎么反编译我模组aaaaah : Ljava/lang/String;
    //   2050: aload_0
    //   2051: getfield 我草你怎么反编译我模组aaaabN : Laaaaaa/aaaaaa/aaaaaa/aaaaaa/aaaaag/aaaaaa/aaaaaV;
    //   2054: invokevirtual 你为什么要破解我的代码aaaaab : ()Laaaaaa/aaaaaa/aaaaaa/aaaaaa/aaaaag/aaaaaa/aaaabA;
    //   2057: invokevirtual 你为什么要破解我的代码aaaaaa : ()I
    //   2060: aload_0
    //   2061: getfield 我草你怎么反编译我模组aaaabO : Lcn/pixellive/mc/game/event/live/LiveGiftEvent;
    //   2064: invokevirtual getGiftCount : ()I
    //   2067: imul
    //   2068: invokestatic 你为什么要破解我的代码aaaahF : (Laaaaaa/aaaaaa/aaaaaa/aaaaaa/aaaaac/aaaaaN;Lcn/pixellive/mc/game/event/live/LiveGiftEvent;Ljava/lang/String;I)V
    //   2071: goto -> 2123
    //   2074: getstatic aaaaaa/aaaaaa/aaaaaa/aaaaaa/aaaaac/aaaaaN.我草你怎么反编译我模组aaaack : Laaaaaa/aaaaaa/aaaaaa/aaaaaa/aaaaac/aaaaaN;
    //   2077: aload_0
    //   2078: getfield 我草你怎么反编译我模组aaaabO : Lcn/pixellive/mc/game/event/live/LiveGiftEvent;
    //   2081: aload_0
    //   2082: getfield 我草你怎么反编译我模组aaaaah : Ljava/lang/String;
    //   2085: invokestatic 你为什么要破解我的代码aaaahG : (Laaaaaa/aaaaaa/aaaaaa/aaaaaa/aaaaac/aaaaaN;Lcn/pixellive/mc/game/event/live/LiveGiftEvent;Ljava/lang/String;)V
    //   2088: goto -> 2123
    //   2091: getstatic aaaaaa/aaaaaa/aaaaaa/aaaaaa/aaaaac/aaaaaN.我草你怎么反编译我模组aaaack : Laaaaaa/aaaaaa/aaaaaa/aaaaaa/aaaaac/aaaaaN;
    //   2094: aload_0
    //   2095: getfield 我草你怎么反编译我模组aaaabO : Lcn/pixellive/mc/game/event/live/LiveGiftEvent;
    //   2098: aload_0
    //   2099: getfield 我草你怎么反编译我模组aaaaah : Ljava/lang/String;
    //   2102: aload_0
    //   2103: getfield 我草你怎么反编译我模组aaaabN : Laaaaaa/aaaaaa/aaaaaa/aaaaaa/aaaaag/aaaaaa/aaaaaV;
    //   2106: invokevirtual 你为什么要破解我的代码aaaaab : ()Laaaaaa/aaaaaa/aaaaaa/aaaaaa/aaaaag/aaaaaa/aaaabA;
    //   2109: invokevirtual 你为什么要破解我的代码aaaaaa : ()I
    //   2112: aload_0
    //   2113: getfield 我草你怎么反编译我模组aaaabO : Lcn/pixellive/mc/game/event/live/LiveGiftEvent;
    //   2116: invokevirtual getGiftCount : ()I
    //   2119: imul
    //   2120: invokestatic 你为什么要破解我的代码aaaahH : (Laaaaaa/aaaaaa/aaaaaa/aaaaaa/aaaaac/aaaaaN;Lcn/pixellive/mc/game/event/live/LiveGiftEvent;Ljava/lang/String;I)V
    //   2123: aload_0
    //   2124: getfield 我草你怎么反编译我模组aaaabO : Lcn/pixellive/mc/game/event/live/LiveGiftEvent;
    //   2127: aload_0
    //   2128: getfield 我草你怎么反编译我模组aaaabP : I
    //   2131: invokevirtual setGiftCount : (I)V
    //   2134: getstatic kotlin/Unit.INSTANCE : Lkotlin/Unit;
    //   2137: areturn
    //   2138: new java/lang/IllegalStateException
    //   2141: dup
    //   2142: ldc_w -547749860
    //   2145: i2c
    //   2146: invokestatic aaaaaa : (C)Ljava/lang/Object;
    //   2149: checkcast java/lang/String
    //   2152: invokespecial <init> : (Ljava/lang/String;)V
    //   2155: athrow
  }
  
  @NotNull
  public final Continuation<Unit> create(@Nullable Object paramObject, @NotNull Continuation<?> paramContinuation) {
    return (Continuation<Unit>)new aaaabg(this.我草你怎么反编译我模组aaaabN, this.我草你怎么反编译我模组aaaabO, this.我草你怎么反编译我模组aaaaah, this.我草你怎么反编译我模组aaaabP, this.我草你怎么反编译我模组aaaabQ, (Continuation)paramContinuation);
  }
  
  @Nullable
  public final Object 你为什么要破解我的代码aaaaab(@NotNull CoroutineScope paramCoroutineScope, @Nullable Continuation<? super Unit> paramContinuation) {
    return ((aaaabg)create(paramCoroutineScope, paramContinuation)).invokeSuspend(Unit.INSTANCE);
  }
  
  static {
    byte[] arrayOfByte1 = "ªè\013ea\000a\027 \0316¼¸A²½iY|^\\@byù>YW|2TF´ùóy¡­À\000ÅÌ_\024\023oè\032ì\026\bm\016å¿+xrC>õ¥0.GýQ\036HÆ\002=îaA·\017ÍVÖ'Ñ¨2X3\034×\016ñtó?pz{\023ô\013b<D¶;Ogä-pðT·Í\016LÉ\024·ñ\035¥Ð\025L\022éZD3¶F:]5Á³ö|)ÎèG4Û\024\036@%â`³¯?§\017+d|W\000\030±ÿ£r÷|öX ¢yõæ Oðk±!Ð7Å0|¿\007ø%\006òR»h¬iÔÌ¦çº7ão²\000 ùÂ`êaaWÍ]Â«>´»i\004A\031ì¹Iÿù/\020óx\013Ì0Ñ\tS\005Ìëã¯Ç§5N©¢\002\0137!ý÷ÿ5à\bI\tÛã§{®FÀîÉ=DÚ¹³I¤\034Í>OB\031[ÍçíØYæ°ì´41¹Ù~\033u\nØ\031bµRQÙ&Ç÷ &hû\032Ù±1PÝéT!Xòd\"H~Ï\0041àÿ{è[%@\034öÁ#\002Vè\032s¯ÿ¾Ñ\000Õ£d\006<X)ÿ\r6ìUºÞÀ\035=£îîÔQÜB\037¬ lÎI\006dÐ\b³²çO|bîÖ\034fEÇ\ngÞÞ@¾öäKàoË;së\bÑv\\-¤\000$à/­|Zgç#ý%`rú\035\"åh7#ê7(Ý<fXäâ^ª¯eÎÚ³Èß\000ÑU\007)hvä1=]SÊM?\006¬ÙúnlÿN".getBytes("ISO_8859_1");
    byte[] arrayOfByte2 = "\027\016WPÕÖÜ".getBytes("ISO_8859_1");
    int i = 0;
    int j = arrayOfByte1.length;
    while (true) {
      switch (arrayOfByte1[i] & 0xFF) {
        case 0:
        
        case 1:
        
        case 2:
        
        case 3:
        
        case 4:
        
        case 5:
        
        case 6:
        
        case 7:
        
        case 8:
        
        case 9:
        
        case 10:
        
        case 11:
        
        case 12:
        
        case 13:
        
        case 14:
        
        case 15:
        
        case 16:
        
        case 17:
        
        case 18:
        
        case 19:
        
        case 20:
        
        case 21:
        
        case 22:
        
        case 23:
        
        case 24:
        
        case 25:
        
        case 26:
        
        case 27:
        
        case 28:
        
        case 29:
        
        case 30:
        
        case 31:
        
        case 32:
        
        case 33:
        
        case 34:
        
        case 35:
        
        case 36:
        
        case 37:
        
        case 38:
        
        case 39:
        
        case 40:
        
        case 41:
        
        case 42:
        
        case 43:
        
        case 44:
        
        case 45:
        
        case 46:
        
        case 47:
        
        case 48:
        
        case 49:
        
        case 50:
        
        case 51:
        
        case 52:
        
        case 53:
        
        case 54:
        
        case 55:
        
        case 56:
        
        case 57:
        
        case 58:
        
        case 59:
        
        case 60:
        
        case 61:
        
        case 62:
        
        case 63:
        
        case 64:
        
        case 65:
        
        case 66:
        
        case 67:
        
        case 68:
        
        case 69:
        
        case 70:
        
        case 71:
        
        case 72:
        
        case 73:
        
        case 74:
        
        case 75:
        
        case 76:
        
        case 77:
        
        case 78:
        
        case 79:
        
        case 80:
        
        case 81:
        
        case 82:
        
        case 83:
        
        case 84:
        
        case 85:
        
        case 86:
        
        case 87:
        
        case 88:
        
        case 89:
        
        case 90:
        
        case 91:
        
        case 92:
        
        case 93:
        
        case 94:
        
        case 95:
        
        case 96:
        
        case 97:
        
        case 98:
        
        case 99:
        
        case 100:
        
        case 101:
        
        case 102:
        
        case 103:
        
        case 104:
        
        case 105:
        
        case 106:
        
        case 107:
        
        case 108:
        
        case 109:
        
        case 110:
        
        case 111:
        
        case 112:
        
        case 113:
        
        case 114:
        
        case 115:
        
        case 116:
        
        case 117:
        
        case 118:
        
        case 119:
        
        case 120:
        
        case 121:
        
        case 122:
        
        case 123:
        
        case 124:
        
        case 125:
        
        case 126:
        
        case 127:
        
        case 128:
        
        case 129:
        
        case 130:
        
        case 131:
        
        case 132:
        
        case 133:
        
        case 134:
        
        case 135:
        
        case 136:
        
        case 137:
        
        case 138:
        
        case 139:
        
        case 140:
        
        case 141:
        
        case 142:
        
        case 143:
        
        case 144:
        
        case 145:
        
        case 146:
        
        case 147:
        
        case 148:
        
        case 149:
        
        case 150:
        
        case 151:
        
        case 152:
        
        case 153:
        
        case 154:
        
        case 155:
        
        case 156:
        
        case 157:
        
        case 158:
        
        case 159:
        
        case 160:
        
        case 161:
        
        case 162:
        
        case 163:
        
        case 164:
        
        case 165:
        
        case 166:
        
        case 167:
        
        case 168:
        
        case 169:
        
        case 170:
        
        case 171:
        
        case 172:
        
        case 173:
        
        case 174:
        
        case 175:
        
        case 176:
        
        case 177:
        
        case 178:
        
        case 179:
        
        case 180:
        
        case 181:
        
        case 182:
        
        case 183:
        
        case 184:
        
        case 185:
        
        case 186:
        
        case 187:
        
        case 188:
        
        case 189:
        
        case 190:
        
        case 191:
        
        case 192:
        
        case 193:
        
        case 194:
        
        case 195:
        
        case 196:
        
        case 197:
        
        case 198:
        
        case 199:
        
        case 200:
        
        case 201:
        
        case 202:
        
        case 203:
        
        case 204:
        
        case 205:
        
        case 206:
        
        case 207:
        
        case 208:
        
        case 209:
        
        case 210:
        
        case 211:
        
        case 212:
        
        case 213:
        
        case 214:
        
        case 215:
        
        case 216:
        
        case 217:
        
        case 218:
        
        case 219:
        
        case 220:
        
        case 221:
        
        case 222:
        
        case 223:
        
        case 224:
        
        case 225:
        
        case 226:
        
        case 227:
        
        case 228:
        
        case 229:
        
        case 230:
        
        case 231:
        
        case 232:
        
        case 233:
        
        case 234:
        
        case 235:
        
        case 236:
        
        case 237:
        
        case 238:
        
        case 239:
        
        case 240:
        
        case 241:
        
        case 242:
        
        case 243:
        
        case 244:
        
        case 245:
        
        case 246:
        
        case 247:
        
        case 248:
        
        case 249:
        
        case 250:
        
        case 251:
        
        case 252:
        
        case 253:
        
        case 254:
        
        case 255:
        
        default:
          break;
      } 
      arrayOfByte1[i++] = (byte)-395590037;
      if (i == j) {
        Cipher.getInstance("DES/CBC/PKCS5Padding").init(2, SecretKeyFactory.getInstance("DES").generateSecret(new DESKeySpec(arrayOfByte2)), new IvParameterSpec(new byte[8]));
        j = (arrayOfByte1 = Cipher.getInstance("DES/CBC/PKCS5Padding").doFinal(arrayOfByte1)).length;
        MessageDigest.getInstance("SHA-256").reset();
        MessageDigest.getInstance("SHA-256").update(arrayOfByte1, 0, i = j - 32);
        arrayOfByte2 = MessageDigest.getInstance("SHA-256").digest();
        int k = 0;
        int m = 0;
        byte b = 0;
        while (true) {
          m |= arrayOfByte1[i + k] ^ arrayOfByte2[k];
          if (++k == 32) {
            if (m == 0) {
              Object[] arrayOfObject = new Object[29];
              j = i;
              i = 0;
              do {
                byte[] arrayOfByte = new byte[k = arrayOfByte1[i++] & 0xFF | (arrayOfByte1[i++] & 0xFF) << 8];
                System.arraycopy(arrayOfByte1, i, arrayOfByte, 0, k);
                i += k;
                arrayOfObject[b++] = (new String(arrayOfByte, "UTF-8")).intern();
              } while (i != j);
            } 
            return;
          } 
        } 
        break;
      } 
    } 
  }
  
  private static Object aaaaaa(char paramChar) {
    return ((Object[])aaaabR)[paramChar];
  }
}
