package aaaaaa.aaaaaa.aaaaaa.aaaaaa.aaaaac;

import java.security.MessageDigest;
import java.util.Timer;
import java.util.TimerTask;
import javax.crypto.Cipher;
import javax.crypto.SecretKeyFactory;
import javax.crypto.spec.DESKeySpec;
import javax.crypto.spec.IvParameterSpec;
import kotlin.jvm.internal.Ref;
import kotlin.jvm.internal.SourceDebugExtension;
import net.minecraft.class_243;
import net.minecraft.class_3218;
import net.minecraft.class_3222;

@SourceDebugExtension({"SMAP\nBreakOutStage.kt\nKotlin\n*S Kotlin\n*F\n+ 1 BreakOutStage.kt\ncn/pixellive/mc/game/stage/BreakOutStage$spawnEntity$1\n+ 2 _Collections.kt\nkotlin/collections/CollectionsKt___CollectionsKt\n*L\n1#1,2063:1\n518#2,7:2064\n*S KotlinDebug\n*F\n+ 1 BreakOutStage.kt\ncn/pixellive/mc/game/stage/BreakOutStage$spawnEntity$1\n*L\n1420#1:2064,7\n*E\n"})
public final class aaaach extends TimerTask {
  static Object aaaaaG;
  
  aaaach(Ref.IntRef paramIntRef, int paramInt, Timer paramTimer, aaaaax.aaaaaa/aaaaaa/aaaaaa/aaaaaa/aaaaac/aaaaal paramaaaaaa/aaaaaa/aaaaaa/aaaaaa/aaaaac/aaaaal, class_3222 paramclass_3222, double paramDouble1, double paramDouble2, class_243 paramclass_243, class_3218 paramclass_3218, String paramString) {}
  
  public void run() {
    // Byte code:
    //   0: aload_0
    //   1: getfield 我草你怎么反编译我模组aaaaas : Lkotlin/jvm/internal/Ref$IntRef;
    //   4: getfield element : I
    //   7: aload_0
    //   8: getfield 我草你怎么反编译我模组aaaaaA : I
    //   11: if_icmplt -> 27
    //   14: aload_0
    //   15: invokevirtual cancel : ()Z
    //   18: pop
    //   19: aload_0
    //   20: getfield 我草你怎么反编译我模组aaaaau : Ljava/util/Timer;
    //   23: invokevirtual cancel : ()V
    //   26: return
    //   27: invokestatic 你为什么要破解我的代码aaaada : ()Lnet/minecraft/server/MinecraftServer;
    //   30: dup
    //   31: ifnull -> 81
    //   34: aload_0
    //   35: getfield 我草你怎么反编译我模组aaaaaB : Laaaaaa/aaaaaa/aaaaaa/aaaaaa/aaaaac/aaaaal;
    //   38: aload_0
    //   39: getfield 我草你怎么反编译我模组aaaaaa : Lnet/minecraft/class_3222;
    //   42: aload_0
    //   43: getfield 我草你怎么反编译我模组aaaaaC : D
    //   46: aload_0
    //   47: getfield 我草你怎么反编译我模组aaaaaD : D
    //   50: aload_0
    //   51: getfield 我草你怎么反编译我模组aaaaas : Lkotlin/jvm/internal/Ref$IntRef;
    //   54: aload_0
    //   55: getfield 我草你怎么反编译我模组aaaaaA : I
    //   58: aload_0
    //   59: getfield 我草你怎么反编译我模组aaaaaE : Lnet/minecraft/class_243;
    //   62: aload_0
    //   63: getfield 我草你怎么反编译我模组aaaaaw : Lnet/minecraft/class_3218;
    //   66: aload_0
    //   67: getfield 我草你怎么反编译我模组aaaaaF : Ljava/lang/String;
    //   70: <illegal opcode> run : (Laaaaaa/aaaaaa/aaaaaa/aaaaaa/aaaaac/aaaaal;Lnet/minecraft/class_3222;DDLkotlin/jvm/internal/Ref$IntRef;ILnet/minecraft/class_243;Lnet/minecraft/class_3218;Ljava/lang/String;)Ljava/lang/Runnable;
    //   75: invokevirtual execute : (Ljava/lang/Runnable;)V
    //   78: goto -> 82
    //   81: pop
    //   82: return
  }
  
  private static final void 你为什么要破解我的代码aaaaan(aaaaax.aaaaaa/aaaaaa/aaaaaa/aaaaaa/aaaaac/aaaaal paramaaaaaa/aaaaaa/aaaaaa/aaaaaa/aaaaac/aaaaal, class_3222 paramclass_3222, double paramDouble1, double paramDouble2, Ref.IntRef paramIntRef, int paramInt, class_243 paramclass_243, class_3218 paramclass_3218, String paramString) {
    // Byte code:
    //   0: aload_0
    //   1: ldc 1471545344
    //   3: i2c
    //   4: invokestatic aaaaao : (C)Ljava/lang/Object;
    //   7: checkcast java/lang/String
    //   10: invokestatic checkNotNullParameter : (Ljava/lang/Object;Ljava/lang/String;)V
    //   13: aload_1
    //   14: ldc -851378175
    //   16: i2c
    //   17: invokestatic aaaaao : (C)Ljava/lang/Object;
    //   20: checkcast java/lang/String
    //   23: invokestatic checkNotNullParameter : (Ljava/lang/Object;Ljava/lang/String;)V
    //   26: aload #6
    //   28: ldc 1520173058
    //   30: i2c
    //   31: invokestatic aaaaao : (C)Ljava/lang/Object;
    //   34: checkcast java/lang/String
    //   37: invokestatic checkNotNullParameter : (Ljava/lang/Object;Ljava/lang/String;)V
    //   40: aload #8
    //   42: ldc -244449277
    //   44: i2c
    //   45: invokestatic aaaaao : (C)Ljava/lang/Object;
    //   48: checkcast java/lang/String
    //   51: invokestatic checkNotNullParameter : (Ljava/lang/Object;Ljava/lang/String;)V
    //   54: aload #9
    //   56: ldc -1107558396
    //   58: i2c
    //   59: invokestatic aaaaao : (C)Ljava/lang/Object;
    //   62: checkcast java/lang/String
    //   65: invokestatic checkNotNullParameter : (Ljava/lang/Object;Ljava/lang/String;)V
    //   68: aload #10
    //   70: ldc 1217593349
    //   72: i2c
    //   73: invokestatic aaaaao : (C)Ljava/lang/Object;
    //   76: checkcast java/lang/String
    //   79: invokestatic checkNotNullParameter : (Ljava/lang/Object;Ljava/lang/String;)V
    //   82: aload_0
    //   83: invokevirtual 你为什么要破解我的代码aaaaaa : ()Ljava/lang/String;
    //   86: astore #11
    //   88: aload #11
    //   90: invokevirtual hashCode : ()I
    //   93: lookupswitch default -> 266, 666083 -> 184, 687755 -> 144, 1267438 -> 204, 32883264 -> 164, 955568538 -> 224
    //   144: aload #11
    //   146: ldc -1525547002
    //   148: i2c
    //   149: invokestatic aaaaao : (C)Ljava/lang/Object;
    //   152: checkcast java/lang/String
    //   155: invokevirtual equals : (Ljava/lang/Object;)Z
    //   158: ifne -> 241
    //   161: goto -> 266
    //   164: aload #11
    //   166: ldc 1703870471
    //   168: i2c
    //   169: invokestatic aaaaao : (C)Ljava/lang/Object;
    //   172: checkcast java/lang/String
    //   175: invokevirtual equals : (Ljava/lang/Object;)Z
    //   178: ifne -> 241
    //   181: goto -> 266
    //   184: aload #11
    //   186: ldc 712310792
    //   188: i2c
    //   189: invokestatic aaaaao : (C)Ljava/lang/Object;
    //   192: checkcast java/lang/String
    //   195: invokevirtual equals : (Ljava/lang/Object;)Z
    //   198: ifne -> 241
    //   201: goto -> 266
    //   204: aload #11
    //   206: ldc -658112503
    //   208: i2c
    //   209: invokestatic aaaaao : (C)Ljava/lang/Object;
    //   212: checkcast java/lang/String
    //   215: invokevirtual equals : (Ljava/lang/Object;)Z
    //   218: ifne -> 241
    //   221: goto -> 266
    //   224: aload #11
    //   226: ldc -2044854262
    //   228: i2c
    //   229: invokestatic aaaaao : (C)Ljava/lang/Object;
    //   232: checkcast java/lang/String
    //   235: invokevirtual equals : (Ljava/lang/Object;)Z
    //   238: ifeq -> 266
    //   241: new net/minecraft/class_243
    //   244: dup
    //   245: aload_1
    //   246: invokevirtual method_23317 : ()D
    //   249: dload_2
    //   250: dsub
    //   251: aload_1
    //   252: invokevirtual method_23318 : ()D
    //   255: iconst_3
    //   256: i2d
    //   257: dadd
    //   258: dload #4
    //   260: invokespecial <init> : (DDD)V
    //   263: goto -> 384
    //   266: aload #6
    //   268: getfield element : I
    //   271: iconst_2
    //   272: irem
    //   273: ifne -> 282
    //   276: ldc2_w 2.0
    //   279: goto -> 285
    //   282: ldc2_w -2.0
    //   285: dstore #12
    //   287: aload #6
    //   289: getfield element : I
    //   292: iload #7
    //   294: iconst_2
    //   295: idiv
    //   296: if_icmpge -> 305
    //   299: ldc2_w -2.0
    //   302: goto -> 308
    //   305: ldc2_w 2.0
    //   308: dstore #14
    //   310: aload_1
    //   311: invokevirtual method_19538 : ()Lnet/minecraft/class_243;
    //   314: aload #8
    //   316: new net/minecraft/class_243
    //   319: dup
    //   320: dconst_0
    //   321: dconst_1
    //   322: dconst_0
    //   323: invokespecial <init> : (DDD)V
    //   326: invokevirtual method_1036 : (Lnet/minecraft/class_243;)Lnet/minecraft/class_243;
    //   329: dload #12
    //   331: invokevirtual method_1021 : (D)Lnet/minecraft/class_243;
    //   334: aload #8
    //   336: dload #14
    //   338: invokevirtual method_1021 : (D)Lnet/minecraft/class_243;
    //   341: invokevirtual method_1019 : (Lnet/minecraft/class_243;)Lnet/minecraft/class_243;
    //   344: invokevirtual method_1019 : (Lnet/minecraft/class_243;)Lnet/minecraft/class_243;
    //   347: astore #16
    //   349: aload #16
    //   351: getfield field_1350 : D
    //   354: ldc2_w 25.0
    //   357: ldc2_w 33.0
    //   360: invokestatic coerceIn : (DDD)D
    //   363: dstore #17
    //   365: new net/minecraft/class_243
    //   368: dup
    //   369: aload #16
    //   371: getfield field_1352 : D
    //   374: aload #16
    //   376: getfield field_1351 : D
    //   379: dload #17
    //   381: invokespecial <init> : (DDD)V
    //   384: astore #19
    //   386: nop
    //   387: aload_0
    //   388: invokevirtual 你为什么要破解我的代码aaaaae : ()Lkotlin/jvm/functions/Function3;
    //   391: ifnull -> 504
    //   394: nop
    //   395: invokestatic 你为什么要破解我的代码aaaaaa : ()Lorg/slf4j/Logger;
    //   398: aload_0
    //   399: invokevirtual 你为什么要破解我的代码aaaaaa : ()Ljava/lang/String;
    //   402: <illegal opcode> makeConcatWithConstants : (Ljava/lang/String;)Ljava/lang/String;
    //   407: invokeinterface info : (Ljava/lang/String;)V
    //   412: aload_0
    //   413: invokevirtual 你为什么要破解我的代码aaaaae : ()Lkotlin/jvm/functions/Function3;
    //   416: aload #9
    //   418: aload #19
    //   420: aload #10
    //   422: invokeinterface invoke : (Ljava/lang/Object;Ljava/lang/Object;Ljava/lang/Object;)Ljava/lang/Object;
    //   427: checkcast net/minecraft/class_1308
    //   430: astore #11
    //   432: aload #11
    //   434: ifnull -> 457
    //   437: invokestatic 你为什么要破解我的代码aaaaaa : ()Lorg/slf4j/Logger;
    //   440: aload_0
    //   441: invokevirtual 你为什么要破解我的代码aaaaaa : ()Ljava/lang/String;
    //   444: <illegal opcode> makeConcatWithConstants : (Ljava/lang/String;)Ljava/lang/String;
    //   449: invokeinterface info : (Ljava/lang/String;)V
    //   454: goto -> 819
    //   457: invokestatic 你为什么要破解我的代码aaaaaa : ()Lorg/slf4j/Logger;
    //   460: aload_0
    //   461: invokevirtual 你为什么要破解我的代码aaaaaa : ()Ljava/lang/String;
    //   464: <illegal opcode> makeConcatWithConstants : (Ljava/lang/String;)Ljava/lang/String;
    //   469: invokeinterface warn : (Ljava/lang/String;)V
    //   474: goto -> 819
    //   477: astore #11
    //   479: invokestatic 你为什么要破解我的代码aaaaaa : ()Lorg/slf4j/Logger;
    //   482: aload_0
    //   483: invokevirtual 你为什么要破解我的代码aaaaaa : ()Ljava/lang/String;
    //   486: <illegal opcode> makeConcatWithConstants : (Ljava/lang/String;)Ljava/lang/String;
    //   491: aload #11
    //   493: checkcast java/lang/Throwable
    //   496: invokeinterface error : (Ljava/lang/String;Ljava/lang/Throwable;)V
    //   501: goto -> 819
    //   504: aload_0
    //   505: invokevirtual 你为什么要破解我的代码aaaaad : ()Ljava/lang/String;
    //   508: ifnull -> 736
    //   511: nop
    //   512: aload_0
    //   513: invokevirtual 你为什么要破解我的代码aaaaad : ()Ljava/lang/String;
    //   516: aload #19
    //   518: getfield field_1352 : D
    //   521: aload #19
    //   523: getfield field_1351 : D
    //   526: aload #19
    //   528: getfield field_1350 : D
    //   531: aload #10
    //   533: <illegal opcode> makeConcatWithConstants : (Ljava/lang/String;DDDLjava/lang/String;)Ljava/lang/String;
    //   538: astore #11
    //   540: aload #9
    //   542: invokevirtual method_8503 : ()Lnet/minecraft/server/MinecraftServer;
    //   545: invokevirtual method_3734 : ()Lnet/minecraft/class_2170;
    //   548: aload #9
    //   550: invokevirtual method_8503 : ()Lnet/minecraft/server/MinecraftServer;
    //   553: invokevirtual method_3739 : ()Lnet/minecraft/class_2168;
    //   556: aload #11
    //   558: invokevirtual method_44252 : (Lnet/minecraft/class_2168;Ljava/lang/String;)V
    //   561: aload #9
    //   563: invokevirtual method_27909 : ()Ljava/lang/Iterable;
    //   566: dup
    //   567: ldc_w 1992753163
    //   570: i2c
    //   571: invokestatic aaaaao : (C)Ljava/lang/Object;
    //   574: checkcast java/lang/String
    //   577: invokestatic checkNotNullExpressionValue : (Ljava/lang/Object;Ljava/lang/String;)V
    //   580: astore #20
    //   582: iconst_0
    //   583: istore #21
    //   585: aconst_null
    //   586: astore #22
    //   588: aload #20
    //   590: invokeinterface iterator : ()Ljava/util/Iterator;
    //   595: astore #16
    //   597: aload #16
    //   599: invokeinterface hasNext : ()Z
    //   604: ifeq -> 682
    //   607: aload #16
    //   609: invokeinterface next : ()Ljava/lang/Object;
    //   614: astore #23
    //   616: aload #23
    //   618: checkcast net/minecraft/class_1297
    //   621: astore #24
    //   623: iconst_0
    //   624: istore #25
    //   626: aload #24
    //   628: invokevirtual method_5797 : ()Lnet/minecraft/class_2561;
    //   631: dup
    //   632: ifnull -> 643
    //   635: invokeinterface getString : ()Ljava/lang/String;
    //   640: goto -> 645
    //   643: pop
    //   644: aconst_null
    //   645: aload #10
    //   647: <illegal opcode> makeConcatWithConstants : (Ljava/lang/String;)Ljava/lang/String;
    //   652: invokestatic areEqual : (Ljava/lang/Object;Ljava/lang/Object;)Z
    //   655: ifeq -> 670
    //   658: aload #24
    //   660: instanceof net/minecraft/class_1308
    //   663: ifeq -> 670
    //   666: iconst_1
    //   667: goto -> 671
    //   670: iconst_0
    //   671: nop
    //   672: ifeq -> 597
    //   675: aload #23
    //   677: astore #22
    //   679: goto -> 597
    //   682: aload #22
    //   684: checkcast net/minecraft/class_1297
    //   687: astore #26
    //   689: aload #26
    //   691: ifnull -> 705
    //   694: aload #26
    //   696: astore #21
    //   698: iconst_0
    //   699: istore #22
    //   701: nop
    //   702: goto -> 819
    //   705: nop
    //   706: goto -> 819
    //   709: astore #11
    //   711: invokestatic 你为什么要破解我的代码aaaaaa : ()Lorg/slf4j/Logger;
    //   714: aload_0
    //   715: invokevirtual 你为什么要破解我的代码aaaaad : ()Ljava/lang/String;
    //   718: <illegal opcode> makeConcatWithConstants : (Ljava/lang/String;)Ljava/lang/String;
    //   723: aload #11
    //   725: checkcast java/lang/Throwable
    //   728: invokeinterface error : (Ljava/lang/String;Ljava/lang/Throwable;)V
    //   733: goto -> 819
    //   736: aload_0
    //   737: invokevirtual 你为什么要破解我的代码aaaaac : ()Lnet/minecraft/class_1299;
    //   740: ifnull -> 819
    //   743: aload_0
    //   744: invokevirtual 你为什么要破解我的代码aaaaac : ()Lnet/minecraft/class_1299;
    //   747: aload #9
    //   749: aload #19
    //   751: checkcast net/minecraft/class_2374
    //   754: invokestatic method_49638 : (Lnet/minecraft/class_2374;)Lnet/minecraft/class_2338;
    //   757: getstatic net/minecraft/class_3730.field_16462 : Lnet/minecraft/class_3730;
    //   760: invokevirtual method_47821 : (Lnet/minecraft/class_3218;Lnet/minecraft/class_2338;Lnet/minecraft/class_3730;)Lnet/minecraft/class_1297;
    //   763: checkcast net/minecraft/class_1308
    //   766: astore #11
    //   768: aload #11
    //   770: ifnull -> 819
    //   773: aload #11
    //   775: aload #19
    //   777: getfield field_1352 : D
    //   780: aload #19
    //   782: getfield field_1351 : D
    //   785: aload #19
    //   787: getfield field_1350 : D
    //   790: fconst_0
    //   791: fconst_0
    //   792: invokevirtual method_5808 : (DDDFF)V
    //   795: aload #11
    //   797: aload #10
    //   799: <illegal opcode> makeConcatWithConstants : (Ljava/lang/String;)Ljava/lang/String;
    //   804: invokestatic method_43470 : (Ljava/lang/String;)Lnet/minecraft/class_5250;
    //   807: checkcast net/minecraft/class_2561
    //   810: invokevirtual method_5665 : (Lnet/minecraft/class_2561;)V
    //   813: aload #11
    //   815: iconst_1
    //   816: invokevirtual method_5880 : (Z)V
    //   819: aload #6
    //   821: getfield element : I
    //   824: istore #11
    //   826: aload #6
    //   828: iload #11
    //   830: iconst_1
    //   831: iadd
    //   832: putfield element : I
    //   835: return
    // Exception table:
    //   from	to	target	type
    //   394	474	477	java/lang/Exception
    //   511	706	709	java/lang/Exception
  }
  
  static {
    byte[] arrayOfByte1 = "Í|ÜüuþË9Ú)cÞ\\ñáüu¶.¼¾½\000í ~Û²\021\f®SÖÃöãã)\baø¨ö\"akuôû\027\023\bpÅÃ\026£}âs£V?èÏ¢êÁÚøQ\013¿;\000¦H\036ó\001%ñ¢\022>gûKÃÄÉ\025íG¾âCY\n«\002B§`©?Ã)§w\006p\016S}¶\f¾_\034á_H\001î\003\f\bzÈè{\0062=\033 fóoA)X\036¯\034\025g§\037Xºæ4\033".getBytes("ISO_8859_1");
    byte[] arrayOfByte2 = "Çx\034Áb¹[p".getBytes("ISO_8859_1");
    int i = 0;
    int j = arrayOfByte1.length;
    while (true) {
      switch (arrayOfByte1[i] & 0xFF) {
        case 0:
        
        case 1:
        
        case 2:
        
        case 3:
        
        case 4:
        
        case 5:
        
        case 6:
        
        case 7:
        
        case 8:
        
        case 9:
        
        case 10:
        
        case 11:
        
        case 12:
        
        case 13:
        
        case 14:
        
        case 15:
        
        case 16:
        
        case 17:
        
        case 18:
        
        case 19:
        
        case 20:
        
        case 21:
        
        case 22:
        
        case 23:
        
        case 24:
        
        case 25:
        
        case 26:
        
        case 27:
        
        case 28:
        
        case 29:
        
        case 30:
        
        case 31:
        
        case 32:
        
        case 33:
        
        case 34:
        
        case 35:
        
        case 36:
        
        case 37:
        
        case 38:
        
        case 39:
        
        case 40:
        
        case 41:
        
        case 42:
        
        case 43:
        
        case 44:
        
        case 45:
        
        case 46:
        
        case 47:
        
        case 48:
        
        case 49:
        
        case 50:
        
        case 51:
        
        case 52:
        
        case 53:
        
        case 54:
        
        case 55:
        
        case 56:
        
        case 57:
        
        case 58:
        
        case 59:
        
        case 60:
        
        case 61:
        
        case 62:
        
        case 63:
        
        case 64:
        
        case 65:
        
        case 66:
        
        case 67:
        
        case 68:
        
        case 69:
        
        case 70:
        
        case 71:
        
        case 72:
        
        case 73:
        
        case 74:
        
        case 75:
        
        case 76:
        
        case 77:
        
        case 78:
        
        case 79:
        
        case 80:
        
        case 81:
        
        case 82:
        
        case 83:
        
        case 84:
        
        case 85:
        
        case 86:
        
        case 87:
        
        case 88:
        
        case 89:
        
        case 90:
        
        case 91:
        
        case 92:
        
        case 93:
        
        case 94:
        
        case 95:
        
        case 96:
        
        case 97:
        
        case 98:
        
        case 99:
        
        case 100:
        
        case 101:
        
        case 102:
        
        case 103:
        
        case 104:
        
        case 105:
        
        case 106:
        
        case 107:
        
        case 108:
        
        case 109:
        
        case 110:
        
        case 111:
        
        case 112:
        
        case 113:
        
        case 114:
        
        case 115:
        
        case 116:
        
        case 117:
        
        case 118:
        
        case 119:
        
        case 120:
        
        case 121:
        
        case 122:
        
        case 123:
        
        case 124:
        
        case 125:
        
        case 126:
        
        case 127:
        
        case 128:
        
        case 129:
        
        case 130:
        
        case 131:
        
        case 132:
        
        case 133:
        
        case 134:
        
        case 135:
        
        case 136:
        
        case 137:
        
        case 138:
        
        case 139:
        
        case 140:
        
        case 141:
        
        case 142:
        
        case 143:
        
        case 144:
        
        case 145:
        
        case 146:
        
        case 147:
        
        case 148:
        
        case 149:
        
        case 150:
        
        case 151:
        
        case 152:
        
        case 153:
        
        case 154:
        
        case 155:
        
        case 156:
        
        case 157:
        
        case 158:
        
        case 159:
        
        case 160:
        
        case 161:
        
        case 162:
        
        case 163:
        
        case 164:
        
        case 165:
        
        case 166:
        
        case 167:
        
        case 168:
        
        case 169:
        
        case 170:
        
        case 171:
        
        case 172:
        
        case 173:
        
        case 174:
        
        case 175:
        
        case 176:
        
        case 177:
        
        case 178:
        
        case 179:
        
        case 180:
        
        case 181:
        
        case 182:
        
        case 183:
        
        case 184:
        
        case 185:
        
        case 186:
        
        case 187:
        
        case 188:
        
        case 189:
        
        case 190:
        
        case 191:
        
        case 192:
        
        case 193:
        
        case 194:
        
        case 195:
        
        case 196:
        
        case 197:
        
        case 198:
        
        case 199:
        
        case 200:
        
        case 201:
        
        case 202:
        
        case 203:
        
        case 204:
        
        case 205:
        
        case 206:
        
        case 207:
        
        case 208:
        
        case 209:
        
        case 210:
        
        case 211:
        
        case 212:
        
        case 213:
        
        case 214:
        
        case 215:
        
        case 216:
        
        case 217:
        
        case 218:
        
        case 219:
        
        case 220:
        
        case 221:
        
        case 222:
        
        case 223:
        
        case 224:
        
        case 225:
        
        case 226:
        
        case 227:
        
        case 228:
        
        case 229:
        
        case 230:
        
        case 231:
        
        case 232:
        
        case 233:
        
        case 234:
        
        case 235:
        
        case 236:
        
        case 237:
        
        case 238:
        
        case 239:
        
        case 240:
        
        case 241:
        
        case 242:
        
        case 243:
        
        case 244:
        
        case 245:
        
        case 246:
        
        case 247:
        
        case 248:
        
        case 249:
        
        case 250:
        
        case 251:
        
        case 252:
        
        case 253:
        
        case 254:
        
        case 255:
        
        default:
          break;
      } 
      arrayOfByte1[i++] = (byte)290513058;
      if (i == j) {
        Cipher.getInstance("DES/CBC/PKCS5Padding").init(2, SecretKeyFactory.getInstance("DES").generateSecret(new DESKeySpec(arrayOfByte2)), new IvParameterSpec(new byte[8]));
        j = (arrayOfByte1 = Cipher.getInstance("DES/CBC/PKCS5Padding").doFinal(arrayOfByte1)).length;
        MessageDigest.getInstance("SHA-256").reset();
        MessageDigest.getInstance("SHA-256").update(arrayOfByte1, 0, i = j - 32);
        arrayOfByte2 = MessageDigest.getInstance("SHA-256").digest();
        int k = 0;
        int m = 0;
        byte b = 0;
        while (true) {
          m |= arrayOfByte1[i + k] ^ arrayOfByte2[k];
          if (++k == 32) {
            if (m == 0) {
              Object[] arrayOfObject = new Object[12];
              j = i;
              i = 0;
              do {
                byte[] arrayOfByte = new byte[k = arrayOfByte1[i++] & 0xFF | (arrayOfByte1[i++] & 0xFF) << 8];
                System.arraycopy(arrayOfByte1, i, arrayOfByte, 0, k);
                i += k;
                arrayOfObject[b++] = (new String(arrayOfByte, "UTF-8")).intern();
              } while (i != j);
            } 
            return;
          } 
        } 
        break;
      } 
    } 
  }
  
  private static Object aaaaao(char paramChar) {
    return ((Object[])aaaaaG)[paramChar];
  }
}
