package aaaaaa.aaaaaa.aaaaaa.aaaaaa.aaaaaa.aaaaaa;

import kotlin.jvm.internal.SourceDebugExtension;
import net.minecraft.class_2561;
import net.minecraft.class_310;
import net.minecraft.class_332;
import net.minecraft.class_350;
import net.minecraft.class_4280;
import net.minecraft.class_6382;
import org.jetbrains.annotations.NotNull;
import org.jetbrains.annotations.Nullable;
import org.openjdk.nashorn.tools.resources.JhjbM.___;
import org.openjdk.nashorn.tools.resources.JhjbM.___.____;

@SourceDebugExtension({"SMAP\nMusicVolumeScreen.kt\nKotlin\n*S Kotlin\n*F\n+ 1 MusicVolumeScreen.kt\ncn/pixellive/mc/game/client/screen/MusicVolumeScreen$EffectListWidget\n+ 2 _Maps.kt\nkotlin/collections/MapsKt___MapsKt\n+ 3 fake.kt\nkotlin/jvm/internal/FakeKt\n*L\n1#1,285:1\n215#2,2:286\n1#3:288\n*S KotlinDebug\n*F\n+ 1 MusicVolumeScreen.kt\ncn/pixellive/mc/game/client/screen/MusicVolumeScreen$EffectListWidget\n*L\n145#1:286,2\n*E\n"})
final class aaaaaa/aaaaaa/aaaaaa/aaaaaa/aaaaaa/aaaaaa/aaaaam extends class_4280<aaaaan.aaaaaa/aaaaaa/aaaaaa/aaaaaa/aaaaaa/aaaaaa/aaaaam.aaaaaa/aaaaaa/aaaaaa/aaaaaa/aaaaaa/aaaaaa/aaaaaA> {
  public static boolean $skidonion$230027024;
  
  public aaaaaa/aaaaaa/aaaaaa/aaaaaa/aaaaaa/aaaaaa/aaaaam(@NotNull aaaaan paramaaaaan, class_310 paramclass_310, int paramInt1, int paramInt2, int paramInt3, int paramInt4) {
    // Byte code:
    //   0: aload_2
    //   1: ldc 614662144
    //   3: i2c
    //   4: invokestatic aaaace : (C)Ljava/lang/Object;
    //   7: checkcast java/lang/String
    //   10: invokestatic checkNotNullParameter : (Ljava/lang/Object;Ljava/lang/String;)V
    //   13: aload_0
    //   14: aload_1
    //   15: putfield 我草你怎么反编译我模组aaaaaY : Laaaaaa/aaaaaa/aaaaaa/aaaaaa/aaaaaa/aaaaaa/aaaaan;
    //   18: aload_0
    //   19: aload_2
    //   20: iload_3
    //   21: iload #4
    //   23: iload #5
    //   25: iload #6
    //   27: invokespecial <init> : (Lnet/minecraft/class_310;IIII)V
    //   30: nop
    //   31: aload_0
    //   32: getfield 我草你怎么反编译我模组aaaaaY : Laaaaaa/aaaaaa/aaaaaa/aaaaaa/aaaaaa/aaaaaa/aaaaan;
    //   35: invokestatic 你为什么要破解我的代码aaaach : (Laaaaaa/aaaaaa/aaaaaa/aaaaaa/aaaaaa/aaaaaa/aaaaan;)Ljava/util/Map;
    //   38: astore #7
    //   40: iconst_0
    //   41: istore #8
    //   43: aload #7
    //   45: invokeinterface entrySet : ()Ljava/util/Set;
    //   50: invokeinterface iterator : ()Ljava/util/Iterator;
    //   55: astore #9
    //   57: aload #9
    //   59: invokeinterface hasNext : ()Z
    //   64: ifeq -> 138
    //   67: aload #9
    //   69: invokeinterface next : ()Ljava/lang/Object;
    //   74: checkcast java/util/Map$Entry
    //   77: astore #10
    //   79: aload #10
    //   81: astore #11
    //   83: iconst_0
    //   84: istore #12
    //   86: aload #11
    //   88: invokeinterface getKey : ()Ljava/lang/Object;
    //   93: checkcast java/lang/String
    //   96: astore #13
    //   98: aload #11
    //   100: invokeinterface getValue : ()Ljava/lang/Object;
    //   105: checkcast java/lang/Number
    //   108: invokevirtual doubleValue : ()D
    //   111: dstore #14
    //   113: aload_0
    //   114: new aaaaaa/aaaaaa/aaaaaa/aaaaaa/aaaaaa/aaaaaa/aaaaaA
    //   117: dup
    //   118: aload_0
    //   119: aload #13
    //   121: dload #14
    //   123: invokespecial <init> : (Laaaaaa/aaaaaa/aaaaaa/aaaaaa/aaaaaa/aaaaaa/aaaaam;Ljava/lang/String;D)V
    //   126: checkcast net/minecraft/class_350$class_351
    //   129: invokevirtual method_25321 : (Lnet/minecraft/class_350$class_351;)I
    //   132: pop
    //   133: nop
    //   134: nop
    //   135: goto -> 57
    //   138: nop
    //   139: aload_0
    //   140: invokevirtual method_25396 : ()Ljava/util/List;
    //   143: dup
    //   144: ldc -287834111
    //   146: i2c
    //   147: invokestatic aaaace : (C)Ljava/lang/Object;
    //   150: checkcast java/lang/String
    //   153: invokestatic checkNotNullExpressionValue : (Ljava/lang/Object;Ljava/lang/String;)V
    //   156: checkcast java/util/Collection
    //   159: invokeinterface isEmpty : ()Z
    //   164: ifne -> 171
    //   167: iconst_1
    //   168: goto -> 172
    //   171: iconst_0
    //   172: ifeq -> 202
    //   175: aload_0
    //   176: aload_0
    //   177: invokevirtual method_25396 : ()Ljava/util/List;
    //   180: dup
    //   181: ldc -945291263
    //   183: i2c
    //   184: invokestatic aaaace : (C)Ljava/lang/Object;
    //   187: checkcast java/lang/String
    //   190: invokestatic checkNotNullExpressionValue : (Ljava/lang/Object;Ljava/lang/String;)V
    //   193: invokestatic first : (Ljava/util/List;)Ljava/lang/Object;
    //   196: checkcast net/minecraft/class_350$class_351
    //   199: invokevirtual method_25313 : (Lnet/minecraft/class_350$class_351;)V
    //   202: nop
    //   203: return
  }
  
  protected native void 你为什么要破解我的代码aaaacd(@Nullable class_6382 paramclass_6382, @Nullable aaaaaa/aaaaaa/aaaaaa/aaaaaa/aaaaaa/aaaaaa/aaaaaA paramaaaaaa/aaaaaa/aaaaaa/aaaaaa/aaaaaa/aaaaaa/aaaaaA);
  
  static {
    ___.___(72, aaaaaa/aaaaaa/aaaaaa/aaaaaa/aaaaaa/aaaaaa/aaaaam.class);
    ____.___72_30(aaaaaa/aaaaaa/aaaaaa/aaaaaa/aaaaaa/aaaaaa/aaaaam.class);
  }
  
  private static native Object aaaace(char paramChar);
  
  public final class aaaaaa/aaaaaa/aaaaaa/aaaaaa/aaaaaa/aaaaaa/aaaaaA extends class_4280.class_4281<aaaaaa/aaaaaa/aaaaaa/aaaaaa/aaaaaa/aaaaaa/aaaaaA> {
    @NotNull
    private final String 我草你怎么反编译我模组aaaabC;
    
    private final double 我草你怎么反编译我模组aaaabD;
    
    public static boolean $skidonion$2021704589;
    
    public aaaaaa/aaaaaa/aaaaaa/aaaaaa/aaaaaa/aaaaaa/aaaaaA(@NotNull aaaaan.aaaaaa/aaaaaa/aaaaaa/aaaaaa/aaaaaa/aaaaaa/aaaaam this$0, String param2String, double param2Double) {
      this.我草你怎么反编译我模组aaaabC = param2String;
      this.我草你怎么反编译我模组aaaabD = param2Double;
    }
    
    @NotNull
    public final native String 你为什么要破解我的代码aaaadE();
    
    public native void method_25343(@NotNull class_332 param2class_332, int param2Int1, int param2Int2, int param2Int3, int param2Int4, int param2Int5, int param2Int6, int param2Int7, boolean param2Boolean, float param2Float);
    
    public native boolean method_25402(double param2Double1, double param2Double2, int param2Int);
    
    @NotNull
    public native class_2561 method_37006();
    
    static {
      ___.___(172, aaaaaa/aaaaaa/aaaaaa/aaaaaa/aaaaaa/aaaaaa/aaaaaA.class);
      ____.___172_50(aaaaaa/aaaaaa/aaaaaa/aaaaaa/aaaaaa/aaaaaa/aaaaaA.class);
    }
    
    private static native Object aaaadF(char param2Char);
  }
}
