package aaaaaa.aaaaaa.aaaaaa.aaaaaa.aaaaaa.aaaaaa;

import aaaaaa.aaaaaa.aaaaaa.aaaaaa.aaaaac.aaaabG;
import java.io.File;
import kotlin.Unit;
import kotlin.jvm.functions.Function1;
import kotlin.jvm.internal.SourceDebugExtension;
import net.minecraft.class_2561;
import net.minecraft.class_310;
import net.minecraft.class_327;
import net.minecraft.class_332;
import net.minecraft.class_350;
import net.minecraft.class_4280;
import net.minecraft.class_6382;
import org.jetbrains.annotations.NotNull;
import org.jetbrains.annotations.Nullable;
import org.openjdk.nashorn.tools.resources.JhjbM.___;
import org.openjdk.nashorn.tools.resources.JhjbM.___.____;

final class aaaaaa/aaaaaa/aaaaaa/aaaaaa/aaaaaa/aaaaaa/aaaaas extends class_4280<aaaaar.aaaaaa/aaaaaa/aaaaaa/aaaaaa/aaaaaa/aaaaaa/aaaaas.aaaaaa/aaaaaa/aaaaaa/aaaaaa/aaaaaa/aaaaaa/aaaaal> {
  @NotNull
  private final class_327 我草你怎么反编译我模组aaaabk;
  
  public static boolean $skidonion$91687577;
  
  public aaaaaa/aaaaaa/aaaaaa/aaaaaa/aaaaaa/aaaaaa/aaaaas(@NotNull aaaaar paramaaaaar, class_310 paramclass_310) {
    // Byte code:
    //   0: aload_2
    //   1: ldc -2007367680
    //   3: i2c
    //   4: invokestatic aaaacI : (C)Ljava/lang/Object;
    //   7: checkcast java/lang/String
    //   10: invokestatic checkNotNullParameter : (Ljava/lang/Object;Ljava/lang/String;)V
    //   13: aload_0
    //   14: aload_1
    //   15: putfield 我草你怎么反编译我模组aaaabl : Laaaaaa/aaaaaa/aaaaaa/aaaaaa/aaaaaa/aaaaaa/aaaaar;
    //   18: aload_0
    //   19: aload_2
    //   20: aload_2
    //   21: invokevirtual method_22683 : ()Lnet/minecraft/class_1041;
    //   24: invokevirtual method_4486 : ()I
    //   27: aload_2
    //   28: invokevirtual method_22683 : ()Lnet/minecraft/class_1041;
    //   31: invokevirtual method_4502 : ()I
    //   34: bipush #33
    //   36: isub
    //   37: bipush #53
    //   39: isub
    //   40: bipush #33
    //   42: bipush #18
    //   44: invokespecial <init> : (Lnet/minecraft/class_310;IIII)V
    //   47: aload_0
    //   48: aload_2
    //   49: getfield field_1772 : Lnet/minecraft/class_327;
    //   52: dup
    //   53: ldc -1816264703
    //   55: i2c
    //   56: invokestatic aaaacI : (C)Ljava/lang/Object;
    //   59: checkcast java/lang/String
    //   62: invokestatic checkNotNullExpressionValue : (Ljava/lang/Object;Ljava/lang/String;)V
    //   65: putfield 我草你怎么反编译我模组aaaabk : Lnet/minecraft/class_327;
    //   68: nop
    //   69: getstatic aaaaaa/aaaaaa/aaaaaa/aaaaaa/aaaaae/aaaaaa/aaaaaj.我草你怎么反编译我模组aaaaaa : Ljava/util/List;
    //   72: invokeinterface iterator : ()Ljava/util/Iterator;
    //   77: astore_3
    //   78: aload_3
    //   79: invokeinterface hasNext : ()Z
    //   84: ifeq -> 409
    //   87: aload_3
    //   88: invokeinterface next : ()Ljava/lang/Object;
    //   93: checkcast java/lang/String
    //   96: astore #4
    //   98: aload #4
    //   100: astore #5
    //   102: aload #5
    //   104: ifnull -> 383
    //   107: aload #5
    //   109: invokevirtual hashCode : ()I
    //   112: lookupswitch default -> 383, 80702676 -> 260, 630370341 -> 240, 657401329 -> 300, 916506880 -> 180, 1121163920 -> 220, 1902430713 -> 280, 1912904869 -> 200
    //   180: aload #5
    //   182: ldc 1663631362
    //   184: i2c
    //   185: invokestatic aaaacI : (C)Ljava/lang/Object;
    //   188: checkcast java/lang/String
    //   191: invokevirtual equals : (Ljava/lang/Object;)Z
    //   194: ifne -> 329
    //   197: goto -> 383
    //   200: aload #5
    //   202: ldc 1621688323
    //   204: i2c
    //   205: invokestatic aaaacI : (C)Ljava/lang/Object;
    //   208: checkcast java/lang/String
    //   211: invokevirtual equals : (Ljava/lang/Object;)Z
    //   214: ifne -> 356
    //   217: goto -> 383
    //   220: aload #5
    //   222: ldc -480509948
    //   224: i2c
    //   225: invokestatic aaaacI : (C)Ljava/lang/Object;
    //   228: checkcast java/lang/String
    //   231: invokevirtual equals : (Ljava/lang/Object;)Z
    //   234: ifne -> 374
    //   237: goto -> 383
    //   240: aload #5
    //   242: ldc 2051211269
    //   244: i2c
    //   245: invokestatic aaaacI : (C)Ljava/lang/Object;
    //   248: checkcast java/lang/String
    //   251: invokevirtual equals : (Ljava/lang/Object;)Z
    //   254: ifne -> 347
    //   257: goto -> 383
    //   260: aload #5
    //   262: ldc -366346234
    //   264: i2c
    //   265: invokestatic aaaacI : (C)Ljava/lang/Object;
    //   268: checkcast java/lang/String
    //   271: invokevirtual equals : (Ljava/lang/Object;)Z
    //   274: ifne -> 320
    //   277: goto -> 383
    //   280: aload #5
    //   282: ldc 287375367
    //   284: i2c
    //   285: invokestatic aaaacI : (C)Ljava/lang/Object;
    //   288: checkcast java/lang/String
    //   291: invokevirtual equals : (Ljava/lang/Object;)Z
    //   294: ifne -> 365
    //   297: goto -> 383
    //   300: aload #5
    //   302: ldc -1972699128
    //   304: i2c
    //   305: invokestatic aaaacI : (C)Ljava/lang/Object;
    //   308: checkcast java/lang/String
    //   311: invokevirtual equals : (Ljava/lang/Object;)Z
    //   314: ifne -> 338
    //   317: goto -> 383
    //   320: getstatic aaaaaa/aaaaaa/aaaaaa/aaaaaa/aaaaac/aaaaaN.我草你怎么反编译我模组aaaack : Laaaaaa/aaaaaa/aaaaaa/aaaaaa/aaaaac/aaaaaN;
    //   323: checkcast aaaaaa/aaaaaa/aaaaaa/aaaaaa/aaaaac/aaaabG
    //   326: goto -> 386
    //   329: getstatic aaaaaa/aaaaaa/aaaaaa/aaaaaa/aaaaac/aaaaaY.我草你怎么反编译我模组aaaacX : Laaaaaa/aaaaaa/aaaaaa/aaaaaa/aaaaac/aaaaaY;
    //   332: checkcast aaaaaa/aaaaaa/aaaaaa/aaaaaa/aaaaac/aaaabG
    //   335: goto -> 386
    //   338: getstatic aaaaaa/aaaaaa/aaaaaa/aaaaaa/aaaaac/aaaaae.我草你怎么反编译我模组aaaaaE : Laaaaaa/aaaaaa/aaaaaa/aaaaaa/aaaaac/aaaaae;
    //   341: checkcast aaaaaa/aaaaaa/aaaaaa/aaaaaa/aaaaac/aaaabG
    //   344: goto -> 386
    //   347: getstatic aaaaaa/aaaaaa/aaaaaa/aaaaaa/aaaaac/aaaabW.我草你怎么反编译我模组aaaacY : Laaaaaa/aaaaaa/aaaaaa/aaaaaa/aaaaac/aaaabW;
    //   350: checkcast aaaaaa/aaaaaa/aaaaaa/aaaaaa/aaaaac/aaaabG
    //   353: goto -> 386
    //   356: getstatic aaaaaa/aaaaaa/aaaaaa/aaaaaa/aaaaac/aaaaaP.我草你怎么反编译我模组aaaacW : Laaaaaa/aaaaaa/aaaaaa/aaaaaa/aaaaac/aaaaaP;
    //   359: checkcast aaaaaa/aaaaaa/aaaaaa/aaaaaa/aaaaac/aaaabG
    //   362: goto -> 386
    //   365: getstatic aaaaaa/aaaaaa/aaaaaa/aaaaaa/aaaaac/aaaaad.我草你怎么反编译我模组aaaaaa : Laaaaaa/aaaaaa/aaaaaa/aaaaaa/aaaaac/aaaaad;
    //   368: checkcast aaaaaa/aaaaaa/aaaaaa/aaaaaa/aaaaac/aaaabG
    //   371: goto -> 386
    //   374: getstatic aaaaaa/aaaaaa/aaaaaa/aaaaaa/aaaaac/aaaaax.我草你怎么反编译我模组aaaabk : Laaaaaa/aaaaaa/aaaaaa/aaaaaa/aaaaac/aaaaax;
    //   377: checkcast aaaaaa/aaaaaa/aaaaaa/aaaaaa/aaaaac/aaaabG
    //   380: goto -> 386
    //   383: goto -> 78
    //   386: astore #6
    //   388: aload_0
    //   389: new aaaaaa/aaaaaa/aaaaaa/aaaaaa/aaaaaa/aaaaaa/aaaaal
    //   392: dup
    //   393: aload_0
    //   394: aload #6
    //   396: invokespecial <init> : (Laaaaaa/aaaaaa/aaaaaa/aaaaaa/aaaaaa/aaaaaa/aaaaas;Laaaaaa/aaaaaa/aaaaaa/aaaaaa/aaaaac/aaaabG;)V
    //   399: checkcast net/minecraft/class_350$class_351
    //   402: invokevirtual method_25321 : (Lnet/minecraft/class_350$class_351;)I
    //   405: pop
    //   406: goto -> 78
    //   409: nop
    //   410: return
  }
  
  @Nullable
  public final native aaaaaa/aaaaaa/aaaaaa/aaaaaa/aaaaaa/aaaaaa/aaaaal 你为什么要破解我的代码aaaacF();
  
  protected native void 你为什么要破解我的代码aaaacG(@NotNull class_6382 paramclass_6382, @NotNull aaaaaa/aaaaaa/aaaaaa/aaaaaa/aaaaaa/aaaaaa/aaaaal paramaaaaaa/aaaaaa/aaaaaa/aaaaaa/aaaaaa/aaaaaa/aaaaal);
  
  static {
    ___.___(126, aaaaaa/aaaaaa/aaaaaa/aaaaaa/aaaaaa/aaaaaa/aaaaas.class);
    ____.___126_50(aaaaaa/aaaaaa/aaaaaa/aaaaaa/aaaaaa/aaaaaa/aaaaas.class);
  }
  
  private static native Object aaaacI(char paramChar);
  
  @SourceDebugExtension({"SMAP\nChooseGameStageScreen.kt\nKotlin\n*S Kotlin\n*F\n+ 1 ChooseGameStageScreen.kt\ncn/pixellive/mc/game/client/screen/ChooseGameStageScreen$GameStageListWidget$GameStageEntry\n+ 2 fake.kt\nkotlin/jvm/internal/FakeKt\n*L\n1#1,317:1\n1#2:318\n*E\n"})
  public final class aaaaaa/aaaaaa/aaaaaa/aaaaaa/aaaaaa/aaaaaa/aaaaal extends class_4280.class_4281<aaaaaa/aaaaaa/aaaaaa/aaaaaa/aaaaaa/aaaaaa/aaaaal> {
    @NotNull
    private final aaaabG 我草你怎么反编译我模组aaaaaV;
    
    private long 我草你怎么反编译我模组aaaaaW;
    
    public static boolean $skidonion$1669288611;
    
    public aaaaaa/aaaaaa/aaaaaa/aaaaaa/aaaaaa/aaaaaa/aaaaal(@NotNull aaaaar.aaaaaa/aaaaaa/aaaaaa/aaaaaa/aaaaaa/aaaaaa/aaaaas this$0, aaaabG param2aaaabG) {
      this.我草你怎么反编译我模组aaaaaV = param2aaaabG;
    }
    
    @NotNull
    public final native aaaabG 你为什么要破解我的代码aaaaca();
    
    @NotNull
    public native class_2561 method_37006();
    
    public native void method_25343(@NotNull class_332 param2class_332, int param2Int1, int param2Int2, int param2Int3, int param2Int4, int param2Int5, int param2Int6, int param2Int7, boolean param2Boolean, float param2Float);
    
    public native boolean method_25402(double param2Double1, double param2Double2, int param2Int);
    
    private final native void 你为什么要破解我的代码aaaacb(aaaabG param2aaaabG, Function1<? super Boolean, Unit> param2Function1);
    
    private static final native void 你为什么要破解我的代码aaaacc(Function1 param2Function1, File param2File);
    
    static {
      ___.___(63, aaaaaa/aaaaaa/aaaaaa/aaaaaa/aaaaaa/aaaaaa/aaaaal.class);
      ____.___63_70(aaaaaa/aaaaaa/aaaaaa/aaaaaa/aaaaaa/aaaaaa/aaaaal.class);
    }
    
    private static native Object aaaacd(char param2Char);
  }
}
